Workbook

Sheet 1. Sign Off & Other Checks
C2: Client Money Reconciliations Sign Off | D2: ='2. Daily Client Money Report'!B4 -> 46189
C4: Internal Reconciliation CISA & LISA | G4: Negative Balance check
C5: Checks | D5: Inputter | E5: Checker | G5: Check to ensure no user has a negative balance
C6: Update underlying Workings tabs | E6: LK | G6: Looker: | H6: Explore Tax Wrapper Money Flows & Balances
C7: Combined User Balance from Ledger vs Bulk Plum Ledger Balance for reconcilation date has been updated | D7: DB | G7: Screenshot of report
C8: External Ledger balance matches that of Plum Ledger balance on Internal workings tab | D8: DB
C9: Reconciliation difference at 0 | D9: DB
C10: All adjustments have relevant commentary and explaination | D10: DB
C11: All breaks have relevant details (user ID, order ID, explanation) | D11: DB
C12: Negative Balance check | D12: DB
C13: Check all cells are mapped correctly to workings | D13: DB
C14: Add comments for any signficant changes or omissions | D14: DB
C15: Update the overall conclusion on Daily CM report | D15: DB
C16: Final sign off
G17: No negative balances
C19: External Reconciliation CISA & LISA
C20: Check | D20: Inputter | E20: Checker
C21: Update underlying Working tabs | E21: LK
C22: External balances (Citi, Lloyds, HSBC, QNB cash) updated | D22: DB
C23: Reconciliation difference at 0 | D23: DB
C24: All adjustments have relevant commentary and explaination | D24: DB
C25: All breaks have relevant details (transaction ID, order ID, explanation) | D25: DB
C26: CASS Internal Reconciliation tab
C27: Check all cells are mapped correctly to workings | D27: DB
C28: Add comments for any signficant changes or omissions | D28: DB
C29: Update the overall conclusion | D29: DB
C30: Final sign off
C32: Unalloc Account Reconciled
C33: Check | D33: Inputter | E33: Checker
C34: Unalloc holdings accounted for | D34: DB | E34: LK | G34: ="Negative balance from the " &TEXT(D2, "dd/mm") -> Negative balance from the 16/06
C35: 10 day check | D35: DB | G35: Number | H35: Date | I35: User ID | J35: Subscription ID | K35: Product name | L35: Subscription status | M35: Balance | N35: Notes
C37: Manual combined user balace check | L37: Total | M37: =SUM(M36) -> 0
L38: Difference to prev day | M38: =M46-M37 -> 0
C39: Combined User Balance Check - CISA | D39: Amounts
C40: Internal CUB from previous day | D40: ='5. CISA Internal Workings'!F19 -> 2386124298
C41: Debits (Recon data) from Rec data | D41: 10417421
C42: Credits (Recon data) from Rec data | D42: 11826163
C43: Total | D43: =D40-D41+D42 -> 2387533039 | G43: ="Negative balance from the " & TEXT(IF(WEEKDAY(D2)=2, D2-3, D2-1), "dd/mm") -> Negative balance from the 15/06
G44: Number | H44: Date | I44: User ID | J44: Subscription ID | K44: Product name | L44: Subscription status | M44: Balance | N44: Notes
C45: Internal CUB from Rec Date | D45: ='5. CISA Internal Workings'!F18 -> 2387533039
C46: Difference | D46: =D43-D45 -> 0 | L46: Total | M46: =SUM(M45) -> 0
C49: Combined User Balance Check - LISA | D49: Amounts
C50: Internal CUB from previous day | D50: ='10. LISA Internal Workings'!F19 -> 2.1771466e+08
C51: Debits (Recon data) from Rec data | D51: 251643.28
C52: Credits (Recon data) from Rec data | D52: 946498.01
C53: Total | D53: =D50-D51+D52 -> 2.1840952e+08
C55: Internal CUB from Rec Date | D55: ='10. LISA Internal Workings'!F18 -> 2.1840952e+08
C56: Difference | D56: =D53-D55 -> 0
C61: ="Difference of £" & ROUND(ABS(D56),2) & " due to data discrepancy from " &TEXT(D2, "dd/mm") &". Amount is being investigated with Data and Engineering. No breaks causing shortfall or surplus for LISA." -> Difference of £0 due to data discrepancy from 16/06. Amount is being investigated with Data and Engineering. No breaks causing shortfall or surplus for LISA.

Sheet 2. Daily Client Money Report
A1: Saveable Daily Client Money and Asset Reporting
A4: Close of Business Date | B4: ='4. CISA - CASS Internal Rec'!E4 -> 46189
A6: Cash ISA Client Money Balances - GBP
A7: Bank | B7: Account | C7: Previous Day Balance | D7: COB Balance | E7: Variance | F7: Entity
A8: Citi Bank NA London | B8: Saveable Cash ISA UK Client Money (14747801) | C8: ='7. CISA External Workings'!I31 -> 1.7699286e+08 | D8: ='7. CISA External Workings'!I30 -> 1.7602115e+08 | E8: =D8-C8 -> -971703.8 | F8: Saveable Limited
A9: Lloyds Bank Plc | B9: Saveable Cash ISA Client Account (27551460) | C9: ='7. CISA External Workings'!I36 -> 3959844.1 | D9: ='7. CISA External Workings'!I35 -> 3959844.1 | E9: =D9-C9 -> 0 | F9: Saveable Limited
A10: Lloyds Bank Plc | B10: Saveable Cash ISA 30D Notice Client Account (27571468) | C10: ='7. CISA External Workings'!I41 -> 747535672 | D10: ='7. CISA External Workings'!I40 -> 747535672 | E10: =D10-C10 -> 0 | F10: Saveable Limited
A11: QNB | B11: Qatar National Bank (4311-000545-310) | C11: ='7. CISA External Workings'!I46 -> 1168000000 | D11: ='7. CISA External Workings'!I45 -> 1168000000 | E11: =D11-C11 -> 0 | F11: Saveable Limited
A12: BlackRock QMMF | B12: Blackrock QMMF | C12: ='7. CISA External Workings'!I56 -> 0 | D12: ='7. CISA External Workings'!I55 -> 0 | E12: =D12-C12 -> 0 | F12: Saveable Limited
A13: BBVA | B13: BBVA Easy access (01778650) | C13: ='7. CISA External Workings'!I61 -> 2.9496063e+08 | D13: ='7. CISA External Workings'!I60 -> 2.9496063e+08 | E13: =D13-C13 -> 0 | F13: Saveable Limited
A14: BBVA | B14: BBVA Notice account (06758170) | C14: ='7. CISA External Workings'!I66 -> 0 | D14: ='7. CISA External Workings'!I65 -> 0 | E14: =D14-C14 -> 0 | F14: Saveable Limited
A15: Clydesdale Bank PLC TA Virgin Money | B15: Saveable Cash ISA 95 Day Notice (12204224) | C15: ='7. CISA External Workings'!I71 -> 0 | D15: ='7. CISA External Workings'!I70 -> 0 | E15: =D15-C15 -> 0 | F15: Saveable Limited
A16: Clydesdale Bank PLC TA Virgin Money | B16: Saveable Cash ISA 65 Day Notice (12204316) | C16: ='7. CISA External Workings'!I76 -> 0 | D16: ='7. CISA External Workings'!I75 -> 0 | E16: =D16-C16 -> 0 | F16: Saveable Limited
A17: Clydesdale Bank PLC TA Virgin Money | B17: Saveable Cash ISA 30 Day Notice (12204161) | C17: ='7. CISA External Workings'!I81 -> 0 | D17: ='7. CISA External Workings'!I80 -> 0 | E17: =D17-C17 -> 0 | F17: Saveable Limited
A18: Clydesdale Bank PLC TA Virgin Money | B18: Saveable Cash ISA Instant access (12204414) | C18: ='7. CISA External Workings'!I86 -> 0 | D18: ='7. CISA External Workings'!I85 -> 0 | E18: =D18-C18 -> 0 | F18: Saveable Limited
A19: JP Morgan | B19: JP Morgan Client Money account (76919500) | C19: ='7. CISA External Workings'!I91 -> 0 | D19: ='7. CISA External Workings'!I90 -> 0 | E19: =D19-C19 -> 0 | F19: Saveable Limited
B20: Total | C20: =SUM(C8:C19) -> 2391449004 | D20: =SUM(D8:D19) -> 2390477301
D22: CISA Net Increase/decrease | E22: =SUM(E8:E19) -> -971703.8
A24: Lifetime ISA Client Money Balances - GBP
A25: Bank | B25: Account | C25: Previous Day Balance | D25: COB Balance | E25: Variance | F25: Entity
A26: CitiBank NA London | B26: Saveable Lifetime ISA UK Client Money (15242487) | C26: ='12. LISA External Workings'!I31 -> 38363170 | D26: ='12. LISA External Workings'!I30 -> 38973579 | E26: =D26-C26 -> 610408.97 | F26: Saveable Limited
A27: Lloyds Bank Plc | B27: Saveable Lifetime ISA Client Account (27561260) | C27: ='12. LISA External Workings'!I36 -> 714980.29 | D27: ='12. LISA External Workings'!I35 -> 714980.29 | E27: =D27-C27 -> 0 | F27: Saveable Limited
A28: Lloyds Bank Plc | B28: Saveable Lifetime ISA 30D Notice Client Account (27571060) | C28: ='12. LISA External Workings'!I41 -> 79300000 | D28: ='12. LISA External Workings'!I40 -> 79300000 | E28: =D28-C28 -> 0 | F28: Saveable Limited
A29: QNB | B29: Qatar National Bank (4311-000545-311) | C29: ='12. LISA External Workings'!I46 -> 100000000 | D29: ='12. LISA External Workings'!I45 -> 100000000 | E29: =D29-C29 -> 0 | F29: Saveable Limited
B30: Total | C30: =SUM(C26:C29) -> 2.1837815e+08 | D30: =SUM(D26:D29) -> 2.1898856e+08
D32: LISA Net Increase/decrease | E32: =SUM(E26:E29) -> 610408.97
D34: Total ISA increase/decrease | E34: =E22+E32 -> -361294.83
A37: Cash ISA | D37: Lifetime ISA
A38: Commentary on Variances | D38: Commentary on Variances
A39: Citibank *This account is used for user transfers, deposits and withdrawals | B39: N/A | D39: Citibank *This account is used for user transfers, deposits and withdrawals | E39: N/A
A40: Lloyds EA | B40: N/A | D40: Lloyds EA | E40: N/A
A41: Lloyds Notice | B41: N/A | D41: Lloyds Notice | E41: N/A
A42: QNB | B42: N/A | D42: QNB | E42: N/A
A43: BBVA | B43: N/A
A46: Daily Reconciliation
A47: Requirement | B47: ='5. CISA Internal Workings'!F42+'10. LISA Internal Workings'!F46 +B66 -> 2609495399
A48: Inclusive of transfers in to apply | B48: ='5. CISA Internal Workings'!M53+'10. LISA Internal Workings'!M57 -> 3507294.7
A49: Total Requirement (inclusive of Quai) | B49: =B47+B48 -> 2613002694
A50: Resource (inclusive of Quai) | B50: ='7. CISA External Workings'!O24+'12. LISA External Workings'!K21 +B67 -> 2612998057
A51: Shortfall / Surplus (inclusive of Quai) | B51: =B50-B49 +B68 -> -4636.9443
A52: Reason for internal movements | B52: =IF(ROUND('4. CISA - CASS Internal Rec'!E6,2)=0, "CISA: No surplus or shortfall movement " & TEXT(TODAY(), "dd/mm"), IF('5. CISA Internal Workings'!M80 < 0, IF(ROUND('5. CISA Internal Workings'!M80, 2) = ROUND('5. CISA Internal Workings'!M83, 2), "CISA: Overall Shortfall of £" & ROUND(ABS('5. CISA Internal Workings'!M80), 2) & CHAR(10) & "-" & '5. CISA Internal Workings'!E80 & CHAR(10) & "-" & '5. CISA Internal Workings'!H80, "CISA: Overall Shortfall of £" & ROUND(ABS('5. CISA Internal Workings'!M83), 2) & CHAR(10) & "-" & '5. CISA Internal Workings'!E80 & CHAR(10) & "-" & '5. CISA Internal Workings'!H80 & CHAR(10) & IF(ABS('5. CISA Internal Workings'!M81)>0, "-" & '5. CISA Internal Workings'!E81 & CHAR(10) & "-" & '5. CISA Internal Workings'!H81 & IF('5. CISA Internal Workings'!E82<>"", CHAR(10) & "-" & '5. CISA Internal Workings'!E82 & CHAR(10) & "-" & '5. CISA Internal Workings'!H82, ""), "") ), IF(ROUND('5. CISA Internal Workings'!M80, 2) = ROUND('5. CISA Internal Workings'!M83, 2), "CISA: Overall Surplus of £" & ROUND(ABS('5. CISA Internal Workings'!M80), 2) & CHAR(10) & "-" & '5. CISA Internal Workings'!E80 & CHAR(10) & "-" & '5. CISA Internal Workings'!H80, "CISA: Overall Surplus of £" & ROUND(ABS('5. CISA Internal Workings'!M83), 2) & CHAR(10) & "-" & '5. CISA Internal Workings'!E80 & CHAR(10) & "-" & '5. CISA Internal Workings'!H80 & CHAR(10) & IF(ABS('5. CISA Internal Workings'!M81)>0, "-" & '5. CISA Internal Workings'!E81 & CHAR(10) & "-" & '5. CISA Internal Workings'!H81 & IF('5. CISA Internal Workings'!E82<>"", CHAR(10) & "-" & '5. CISA Internal Workings'!E82 & CHAR(10) & "-" & '5. CISA Internal Workings'!H82, ""), "") ) ) ) -> CISA: Overall Shortfall of £4393.67 -Amount of £4,393.67 residual interest paid to users as part of the transfer out process -To be moved from CISA corporate interest to CM 17/06
B54: =IF(ROUND('9. LISA - CASS Internal Rec'!E6,2)=0, "LISA: No surplus or shortfall movement " & TEXT(TODAY(), "dd/mm"), IF('10. LISA Internal Workings'!M84 < 0, IF(ROUND('10. LISA Internal Workings'!M84, 2) = ROUND('10. LISA Internal Workings'!M87, 2), "LISA: Overall Shortfall of £" & ROUND(ABS('10. LISA Internal Workings'!M84), 2) & CHAR(10) & "-" & '10. LISA Internal Workings'!E84 & CHAR(10) & "-" & '10. LISA Internal Workings'!H84, "LISA: Overall Shortfall of £" & ROUND(ABS('10. LISA Internal Workings'!M87), 2) & CHAR(10) & "-" & '10. LISA Internal Workings'!E84 & CHAR(10) & "-" & '10. LISA Internal Workings'!H84 & CHAR(10) & IF(ABS('10. LISA Internal Workings'!M85)>0, "-" & '10. LISA Internal Workings'!E85 & CHAR(10) & "-" & '10. LISA Internal Workings'!H85, "") ), IF(ROUND('10. LISA Internal Workings'!M84, 2) = ROUND('10. LISA Internal Workings'!M87, 2), "LISA: Overall Surplus of £" & ROUND(ABS('10. LISA Internal Workings'!M84), 2) & CHAR(10) & "-" & '10. LISA Internal Workings'!E84 & CHAR(10) & "-" & '10. LISA Internal Workings'!H84, "LISA: Overall Surplus of £" & ROUND(ABS('10. LISA Internal Workings'!M87), 2) & CHAR(10) & "-" & '10. LISA Internal Workings'!E84 & CHAR(10) & "-" & '10. LISA Internal Workings'!H84 & CHAR(10) & IF(ABS('10. LISA Internal Workings'!M85)>0, "-" & '10. LISA Internal Workings'!E85 & CHAR(10) & "-" & '10. LISA Internal Workings'!H85, "") ) ) ) -> LISA: Overall Shortfall of £243.63 -Amount of £243.63 residual interest paid to users as part of the transfer out process -To be moved from LISA corporate interest to CM 17/06
B55: =IF(ROUND(B68,2)=0, "Quai: No surplus or shortfall movement " & TEXT(TODAY(), "dd/mm"), IF(B68 < 0, "Quai: Overall Shortfall of £" & TEXT(ABS(B68), "0.00") & CHAR(10) & "Quai to arrange amount to written off " & TEXT(TODAY(), "dd/mm"), IF(B68 > 0, "Quai: Overall Surplus of £" & TEXT(ABS(B68), "0.00") & CHAR(10) & "Quai to arrange amount to written off " & TEXT(TODAY(), "dd/mm") , ""))) -> Quai: Overall Surplus of £0.18 Quai to arrange amount to written off 17/06
A56: Additional Comments | B56: Amount of £1,315.68 is currently being held on LISA Unalloc as unidentified funds as part of ongoing HMRC government bonus differences.
A58: Stocks/Shares ISA
A59: Bank | B59: Account | C59: Previous Day Balance | D59: COB Balance | E59: Variance | F59: Entity | G59: Reconciliation Performed by
A60: Barclays UK PLC | B60: SAVEABLE LTD (90314552) - Pending Sells/Buys - Awaiting settlement | C60: 2319020.8 | E60: =D60-C60 -> -2319020.8 | F60: Saveable Limited | G60: Quai - Cash Held
A61: Winterfloods | B61: SAVEABLE LTD | C61: 1.02326e+08 | E61: =D61-C61 -> -1.02326e+08 | F61: Saveable Limited | G61: Quai - Units Held
A62: Winterfloods | B62: SAVEABLE LTD | C62: 3.7946515e+08 | E62: =D62-C62 -> -3.7946515e+08 | F62: Saveable Limited | G62: Quai - Cash Held
A65: Quai Resource & requirement
A66: Requirement | B66: 3532197
A67: Resource | B67: 3532197.1
A68: Shortfall / Surplus | B68: =B67-B66 -> 0.18
A70: Other Client Money Accounts
A71: Bank | B71: Account | C71: Previous Day Balance | D71: COB Balance | E71: Variance | F71: Entity
A72: Citi Bank NA London | B72: Saveable UK Client Money EUR (14747763) | C72: €0 | D72: €0 | E72: €0 | F72: Saveable Limited
A73: Blackrock QMMF | B73: Saveable Limited Account Cash ISA | C73: 0 Units | D73: 0 Units | E73: 0 | F73: Saveable Limited
A74: Blackrock QMMF | B74: Saveable Limited Lifetime Account Client Account | C74: 0 Units | D74: 0 Units | E74: 0 | F74: Saveable Limited

Sheet 3. Unalloc Rec
B2: UNALLOC Balance | E2: Date: | F2: ='4. CISA - CASS Internal Rec'!E4 -> 46189 | J2: Unallocated Cash Review
C3: Client money temporarily held in our Unalloc account | K3: Value | L3: Tolerance
C4: These amounts count towards the 'Combined User Balance' in the Internal Rec | J4: CISA total unallocated | K4: =M18 -> 294085.7 | L4: {=IF(K4<(0.00025*INDIRECT("'2. Daily Client Money Report'!D20")), "Total amount is within the overall tolerance level (0.025%)", "Total amount is above the overall tolerance level (0.025%)")} -> Total amount is within the overall tolerance level (0.025%)
C5: Note: Client money must be allocated in 10 business days | J5: LISA total unallocated | K5: =M47 -> 163659.42 | L5: {=IF(K5<(0.00025*INDIRECT("'2. Daily Client Money Report'!D30")), "Total amount is within the overall tolerance level (0.025%)", "Total amount is above the overall tolerance level (0.025%)")} -> Total amount is above the overall tolerance level (0.025%)
J6: 0-2 days | K6: =SUMIFS(M:M, Q:Q, ">=0", Q:Q, "<=2") -> 350308.39
J7: 3-5 days | K7: =SUMIFS(M:M, Q:Q, ">=3", Q:Q, "<=5") -> 77906.5
J8: 6-9 days | K8: =SUMIFS(M:M, Q:Q, ">=6", Q:Q, "<=9") -> 26046.54
J9: 10+ days | K9: =SUMIFS(M:M, Q:Q, ">=10") -> 3483.69
B11: CISA
C13: Source: | D13: Explore Wealth Money Flows & Balances
C14: Live Unalloc sheet | D14: CISA Unalloc Ledger and Payins - Google Sheets
C16: Looker UNALLOC balance
C18: =F2 -> 46189 | D18: COB Balance according to Looker | L18: Looker Balance | M18: 294085.7
C21: CISA Money
C22: user_id | D22: ledger_entry_id | E22: ledger_entry_created_at | F22: ledger_entry_type | G22: ledger_entry_amount | H22: product | I22: subscription_id | J22: collection_id | K22: transaction_id | L22: provider_id | M22: payin_amount | N22: transaction_type | O22: payin_created_at | Q22: Days Aged | R22: Breach notes | S22: Commentary
C23: 73df5aae-f42a-49a0-9d8f-616ca6dbebaa | D23: 019eb1df-f256-71a1-b1ce-7c7ae8b244bc | E23: 46183.591 | F23: credit | G23: 29997.68 | H23: cash_isa | I23: 9bc00e6b-ce5f-48c5-ae3a-1baabe00f337 | J23: e3a86178-e782-4b8e-a5af-c71a91f91e51 | K23: e3a86178-e782-4b8e-a5af-c71a91f91e51 | L23: 400250 51421336-2136136478 | M23: 29997.68 | N23: payin | O23: 46182.226 | Q23: =NETWORKDAYS(E23, TODAY())-1 -> 5 | R23: 26-PLU-126 - CISA | S23: N/A
C24: 73df5aae-f42a-49a0-9d8f-616ca6dbebaa | D24: 019eb6b9-c0a2-7317-ab4a-c235d039858e | E24: 46184.533 | F24: credit | G24: 18184.43 | H24: cash_isa | I24: 9bc00e6b-ce5f-48c5-ae3a-1baabe00f337 | J24: 8a36818d-cb4b-4b51-98cd-feffaecfad30 | K24: 8a36818d-cb4b-4b51-98cd-feffaecfad30 | L24: 13267202-51989231 | M24: 18184.43 | N24: payin | O24: 46183.169 | Q24: =NETWORKDAYS(E24, TODAY())-1 -> 4 | R24: N/A | S24: N/A
C25: 73df5aae-f42a-49a0-9d8f-616ca6dbebaa | D25: 019ecb64-c843-7d12-81ee-f6401245704f | E25: 46188.547 | F25: credit | G25: 64323.37 | H25: cash_isa | I25: 9bc00e6b-ce5f-48c5-ae3a-1baabe00f337 | J25: 79376e9a-a2d9-4da6-80da-2fccb69993e9 | K25: 79376e9a-a2d9-4da6-80da-2fccb69993e9 | L25: NOREF-878813225 | M25: 64323.37 | N25: payin | O25: 46185.086 | Q25: =NETWORKDAYS(E25, TODAY())-1 -> 2 | R25: N/A | S25: N/A
C26: 73df5aae-f42a-49a0-9d8f-616ca6dbebaa | D26: 019ecb64-c733-7ae4-944c-db2cb0274f72 | E26: 46188.547 | F26: credit | G26: 40492.94 | H26: cash_isa | I26: 9bc00e6b-ce5f-48c5-ae3a-1baabe00f337 | J26: d1610b83-cb8b-45f0-bea4-69fec40f5e82 | K26: d1610b83-cb8b-45f0-bea4-69fec40f5e82 | L26: NOREF-1362020235 | M26: 40492.94 | N26: payin | O26: 46185.669 | Q26: =NETWORKDAYS(E26, TODAY())-1 -> 2 | R26: N/A | S26: N/A
C27: 73df5aae-f42a-49a0-9d8f-616ca6dbebaa | D27: 019ed024-854b-7377-878e-9bd25cd97072 | E27: 46189.469 | F27: credit | G27: 21471.6 | H27: cash_isa | I27: 9bc00e6b-ce5f-48c5-ae3a-1baabe00f337 | J27: 228cd2f5-1ee0-4962-a649-82c9f17961ae | K27: 228cd2f5-1ee0-4962-a649-82c9f17961ae | L27: WK648730Ba-580073357 | M27: 21471.6 | N27: payin | O27: 46188.669 | Q27: =NETWORKDAYS(E27, TODAY())-1 -> 1 | R27: N/A | S27: N/A
C28: 73df5aae-f42a-49a0-9d8f-616ca6dbebaa | D28: 019ed024-864c-78df-b53a-e34f6f766c49 | E28: 46189.469 | F28: credit | G28: 20974.52 | H28: cash_isa | I28: 9bc00e6b-ce5f-48c5-ae3a-1baabe00f337 | J28: 084ad475-9333-4dbe-8fb5-7d7b8ad84064 | K28: 084ad475-9333-4dbe-8fb5-7d7b8ad84064 | L28: NZ656284A-1098901635 | M28: 20974.52 | N28: payin | O28: 46188.669 | Q28: =NETWORKDAYS(E28, TODAY())-1 -> 1 | R28: N/A | S28: N/A
C29: 73df5aae-f42a-49a0-9d8f-616ca6dbebaa | D29: 019ed024-873d-7252-be6e-6e408eb5a4cb | E29: 46189.469 | F29: credit | G29: 20918.18 | H29: cash_isa | I29: 9bc00e6b-ce5f-48c5-ae3a-1baabe00f337 | J29: a7a2dae7-bd10-44fc-9b1b-25271dcf0442 | K29: a7a2dae7-bd10-44fc-9b1b-25271dcf0442 | L29: JX825895D-940686763 | M29: 20918.18 | N29: payin | O29: 46188.669 | Q29: =NETWORKDAYS(E29, TODAY())-1 -> 1 | R29: N/A | S29: N/A
C30: 73df5aae-f42a-49a0-9d8f-616ca6dbebaa | D30: 019ed024-8a33-7fb5-96a0-78ffd98b3516 | E30: 46189.469 | F30: credit | G30: 7.35 | H30: cash_isa | I30: 9bc00e6b-ce5f-48c5-ae3a-1baabe00f337 | J30: 42c3a58b-fec1-43e1-b86e-f071b829ba7a | K30: 42c3a58b-fec1-43e1-b86e-f071b829ba7a | L30: NOREF-910332414 | M30: 7.35 | N30: payin | O30: 46188.454 | Q30: =NETWORKDAYS(E30, TODAY())-1 -> 1 | R30: N/A | S30: N/A
C31: 73df5aae-f42a-49a0-9d8f-616ca6dbebaa | D31: 019ed024-88f1-789c-a803-e90f28c9087e | E31: 46189.469 | F31: credit | G31: 250 | H31: cash_isa | I31: 9bc00e6b-ce5f-48c5-ae3a-1baabe00f337 | J31: 5a92f897-6035-4172-9831-90028a8a98c2 | K31: 5a92f897-6035-4172-9831-90028a8a98c2 | L31: JC321715Da-518647334 | M31: 250 | N31: payin | O31: 46188.669 | Q31: =NETWORKDAYS(E31, TODAY())-1 -> 1 | R31: N/A | S31: N/A
C32: 73df5aae-f42a-49a0-9d8f-616ca6dbebaa | D32: 019ed024-8817-7d80-9685-39944e000a98 | E32: 46189.469 | F32: credit | G32: 42534.92 | H32: cash_isa | I32: 9bc00e6b-ce5f-48c5-ae3a-1baabe00f337 | J32: a50f2b4e-4ed2-48c6-ae8b-f3052f76d926 | K32: a50f2b4e-4ed2-48c6-ae8b-f3052f76d926 | L32: YM189882D-95846103 | M32: 42534.92 | N32: payin | O32: 46188.669 | Q32: =NETWORKDAYS(E32, TODAY())-1 -> 1 | R32: N/A | S32: N/A
C33: 73df5aae-f42a-49a0-9d8f-616ca6dbebaa | D33: 019ed0b1-3052-7f73-9d08-db917a292c59 | E33: 46189.576 | F33: credit | G33: 14930.71 | H33: cash_isa | I33: 9bc00e6b-ce5f-48c5-ae3a-1baabe00f337 | J33: 37db9098-7f00-401d-be6f-68777404753c | M33: 14930.71 | Q33: =NETWORKDAYS(E33, TODAY())-1 -> 1 | R33: N/A | S33: N/A
C34: 73df5aae-f42a-49a0-9d8f-616ca6dbebaa | D34: 019ed0fa-b1c2-7819-857e-40a98c4e3541 | E34: 46189.631 | F34: credit | G34: 20000 | H34: cash_isa | I34: 9bc00e6b-ce5f-48c5-ae3a-1baabe00f337 | J34: fc861623-56a0-47e2-bd62-7aa9db1633a8 | M34: 20000 | Q34: =NETWORKDAYS(E34, TODAY())-1 -> 1 | R34: N/A | S34: N/A
L35: Sum | M35: =sum(M23:M34) -> 294085.7
L38: Diff | M38: =M35-M18 -> 0
B40: LISA
C42: Source: | D42: Explore Wealth Money Flows & Balances
C43: Live Unalloc sheet | D43: CISA Unalloc Ledger and Payins - Google Sheets
C45: Looker UNALLOC balance
C47: =F2 -> 46189 | D47: COB Balance according to Looker | L47: Looker Balance | M47: 163659.42
C50: LISA Money
C51: user_id | D51: ledger_entry_id | E51: ledger_entry_created_at | F51: ledger_entry_type | G51: ledger_entry_amount | H51: product | I51: subscription_id | J51: collection_id | K51: transaction_id | L51: provider_id | M51: payin_amount | N51: transaction_type | O51: payin_created_at | Q51: Days Aged | R51: Breach notes | S51: Commentary
C52: 73df5aae-f42a-49a0-9d8f-616ca6dbebaa | D52: 0199816b-0e35-745a-bffb-2eb385b18f78 | E52: 45925.631 | F52: credit | G52: 25.82 | H52: lisa | I52: b7a59586-5d10-4989-91c2-f2376c7a6ab2 | J52: 8ecd675b-d3b5-4b51-9aee-fc2c558679b5 | M52: 25.82 | Q52: =NETWORKDAYS(E52, TODAY())-1 -> 189 | R52: Breach raised 09/10 - added to 25-PLU-079 | S52: Amount of 25.82 applies to HMRC gov bonus. Breach raised with engineering and product 09/10
C53: 73df5aae-f42a-49a0-9d8f-616ca6dbebaa | D53: 019a265f-0027-7d29-8ff1-8f39f64358c1 | E53: 45957.661 | F53: credit | G53: 39.36 | H53: lisa | I53: b7a59586-5d10-4989-91c2-f2376c7a6ab2 | J53: 7464d141-4aaa-46a8-ae96-c3c7997dfc03 | M53: 39.36 | Q53: =NETWORKDAYS(E53, TODAY())-1 -> 167 | R53: Breach raised 09/10 - added to 25-PLU-079 | S53: Amount of 39.36 applies to HMRC gov bonus. Breach raised with engineering and product 09/10
C54: 73df5aae-f42a-49a0-9d8f-616ca6dbebaa | D54: 019c0522-3a07-719b-bcbd-b2f0eb14e013 | E54: 46050.628 | F54: credit | G54: 1250.5 | H54: lisa | I54: b7a59586-5d10-4989-91c2-f2376c7a6ab2 | J54: 7464d141-4aaa-46a8-ae96-c3c7997dfc03 | M54: 1250.5 | Q54: =NETWORKDAYS(E54, TODAY())-1 -> 100 | R54: Breach raised 09/10 - added to 25-PLU-079 | S54: Amount of 1,250.50 applies to HMRC gov bonus. Breach raised with engineering and product 09/10
C55: 73df5aae-f42a-49a0-9d8f-616ca6dbebaa | D55: 019c9e6e-9ac8-7b3e-a27b-af919f6932b8 | E55: 46080.395 | F55: credit | G55: 2509.51 | H55: lisa | I55: b7a59586-5d10-4989-91c2-f2376c7a6ab2 | J55: 7464d141-4aaa-46a8-ae96-c3c7997dfc03 | M55: 2168.01 | Q55: =NETWORKDAYS(E55, TODAY())-1 -> 78 | R55: Breach raised 09/10 - added to 25-PLU-079 | S55: - Amount of £2,509.51 applies to HMRC gov bonus. Breach raised with engineering and product 09/10. - Engineering corrected £341.50 on 23/03 and debited from the overall amount of 2,509.51 on 24/03 bringing the total difference to £2,168.01.
C56: 73df5aae-f42a-49a0-9d8f-616ca6dbebaa | D56: 019e986b-6909-779a-852a-fdf77fb1f880 | E56: 46178.649 | F56: credit | G56: 13.99 | H56: lisa | I56: b7a59586-5d10-4989-91c2-f2376c7a6ab2 | J56: 6e288a26-6f54-4606-af76-43cc91f9103c | K56: 6e288a26-6f54-4606-af76-43cc91f9103c | L56: NOREF-190470356 | M56: 13.99 | N56: payin | O56: 46177.479 | Q56: =NETWORKDAYS(E56, TODAY())-1 -> 8 | R56: N/A | S56: N/A
C57: 73df5aae-f42a-49a0-9d8f-616ca6dbebaa | D57: 019ead2b-a847-7e9b-9cf2-ad8d1ba559ad | E57: 46182.678 | F57: credit | G57: 26032.55 | H57: lisa | I57: b7a59586-5d10-4989-91c2-f2376c7a6ab2 | J57: ffe80a3e-ca2c-49f7-99e0-1fea99be39b5 | K57: ffe80a3e-ca2c-49f7-99e0-1fea99be39b5 | L57: RETURN-810653200 | M57: 26032.55 | N57: payin | O57: 46181.654 | Q57: =NETWORKDAYS(E57, TODAY())-1 -> 6 | R57: N/A | S57: N/A
C58: 73df5aae-f42a-49a0-9d8f-616ca6dbebaa | D58: 019eb0ad-e1f7-7848-a2f9-cb38e5c86b1d | E58: 46183.359 | F58: credit | G58: 15963.49 | H58: lisa | I58: b7a59586-5d10-4989-91c2-f2376c7a6ab2 | J58: 429d3d03-20ce-4949-97bc-52dd443bc473 | K58: 429d3d03-20ce-4949-97bc-52dd443bc473 | L58: NOREF-905760162 | M58: 15963.49 | N58: payin | O58: 46181.494 | Q58: =NETWORKDAYS(E58, TODAY())-1 -> 5 | R58: N/A | S58: N/A
C59: 73df5aae-f42a-49a0-9d8f-616ca6dbebaa | D59: 019eb2b6-0f93-7b2a-8031-39c79ca623c7 | E59: 46183.754 | F59: credit | G59: 703.22 | H59: lisa | I59: b7a59586-5d10-4989-91c2-f2376c7a6ab2 | J59: 04016f15-a048-4e2f-ab88-ad6abdf6ed72 | K59: 04016f15-a048-4e2f-ab88-ad6abdf6ed72 | L59: FRESCO.21302.GFX.20-45732139 | M59: 703.22 | N59: payin | O59: 46182.585 | Q59: =NETWORKDAYS(E59, TODAY())-1 -> 5 | R59: N/A | S59: N/A
C60: 73df5aae-f42a-49a0-9d8f-616ca6dbebaa | D60: 019eb6b9-6a8d-73ef-87dc-cb539797754d | E60: 46184.533 | F60: credit | G60: 108.26 | H60: lisa | I60: b7a59586-5d10-4989-91c2-f2376c7a6ab2 | J60: 11ab5e3b-6091-443a-9edf-dd35b41adeb6 | K60: 11ab5e3b-6091-443a-9edf-dd35b41adeb6 | L60: 72FEE306a-571949853 | M60: 108.26 | N60: payin | O60: 46183.393 | Q60: =NETWORKDAYS(E60, TODAY())-1 -> 4 | R60: N/A | S60: N/A
C61: 73df5aae-f42a-49a0-9d8f-616ca6dbebaa | D61: 019ebcb7-d5e1-7bf7-b141-b8a6e63065d4 | E61: 46185.697 | F61: credit | G61: 12949.42 | H61: lisa | I61: b7a59586-5d10-4989-91c2-f2376c7a6ab2 | J61: 70f1e299-11ac-4280-a6e2-1dc1137e001b | K61: 70f1e299-11ac-4280-a6e2-1dc1137e001b | L61: NOREF-838618946 | M61: 12949.42 | N61: payin | O61: 46184.635 | Q61: =NETWORKDAYS(E61, TODAY())-1 -> 3 | R61: N/A | S61: N/A
C62: 73df5aae-f42a-49a0-9d8f-616ca6dbebaa | D62: 019ecc1e-fb7b-7adf-a1b5-209ce9f1e444 | E62: 46188.688 | F62: credit | G62: 56199.56 | H62: lisa | I62: b7a59586-5d10-4989-91c2-f2376c7a6ab2 | J62: cc9da595-2186-4ffd-b8d8-6ec93cfb525a | K62: cc9da595-2186-4ffd-b8d8-6ec93cfb525a | L62: b413ebba-1125098511 | M62: 56199.56 | N62: payin | O62: 46185.1 | Q62: =NETWORKDAYS(E62, TODAY())-1 -> 2 | R62: N/A | S62: N/A
C63: 73df5aae-f42a-49a0-9d8f-616ca6dbebaa | D63: 019ecc1e-f9c0-7af4-98a2-f8ee6e2cc3bc | E63: 46188.688 | F63: credit | G63: 26992.22 | H63: lisa | I63: b7a59586-5d10-4989-91c2-f2376c7a6ab2 | J63: ac9ac199-2324-4ca2-a5db-61b4463bb5e1 | K63: ac9ac199-2324-4ca2-a5db-61b4463bb5e1 | L63: 5520f7fd-1754025676 | M63: 26992.22 | N63: payin | O63: 46185.105 | Q63: =NETWORKDAYS(E63, TODAY())-1 -> 2 | R63: N/A | S63: N/A
C64: 73df5aae-f42a-49a0-9d8f-616ca6dbebaa | D64: 019ecc1e-fc07-76a6-ae0d-2b27455a3529 | E64: 46188.688 | F64: credit | G64: 5412.33 | H64: lisa | I64: b7a59586-5d10-4989-91c2-f2376c7a6ab2 | J64: e3ede257-3bac-4de0-b9e1-bdf3a2e4663b | K64: e3ede257-3bac-4de0-b9e1-bdf3a2e4663b | L64: 65FA81EB-1878983804 | M64: 5412.33 | N64: payin | O64: 46185.54 | Q64: =NETWORKDAYS(E64, TODAY())-1 -> 2 | R64: N/A | S64: N/A
C65: 73df5aae-f42a-49a0-9d8f-616ca6dbebaa | D65: 019ed124-a6d9-770c-a0e0-67d2a0908bde | E65: 46189.663 | F65: credit | G65: 15800.69 | H65: lisa | I65: b7a59586-5d10-4989-91c2-f2376c7a6ab2 | J65: 6c7ca4f4-7fef-4b08-8ff8-2f8d2c79a1e2 | K65: 6c7ca4f4-7fef-4b08-8ff8-2f8d2c79a1e2 | L65: CDF50426-712770789 | M65: 15800.69 | N65: payin | O65: 46188.565 | Q65: =NETWORKDAYS(E65, TODAY())-1 -> 1 | R65: N/A | S65: N/A
L66: Sum | M66: =SUM(M52:M65) -> 163659.42
L69: Diff | M69: =M47-M66 -> 0

Sheet Unalloc_Data
A1: Copy data from "CISA Unalloc Ledger and Payins" with previous day's date | P1: CISA | AD1: CISA | AU1: CISA | BI1: LISA
P2: Brings previous day's data from Unalloc_Rec tab | AD2: Brings previous day's data from Unalloc_Rec sheet for comparison with the new data | AU2: Brings the final data sorted that need to be put on the Unalloc Rec tab | BI2: Brings the final data sorted that need to be put on the Unalloc Rec tab
A3: user_id | B3: ledger_entry_id | C3: ledger_entry_created_at | D3: ledger_entry_type | E3: ledger_entry_amount | F3: product | G3: subscription_id | H3: collection_id | I3: transaction_id | J3: provider_id | K3: payin_amount | L3: transaction_type | M3: payin_created_at | AD3: =IFERROR(__xludf.DUMMYFUNCTION("{FILTER('3. Unalloc Rec'!C3:O983, '3. Unalloc Rec'!H3:H983 = ""cash_isa""); QUERY(A3:M1000, ""select * where F = 'cash_isa'"", 0)}"),"73df5aae-f42a-49a0-9d8f-616ca6dbebaa") -> 73df5aae-f42a-49a0-9d8f-616ca6dbebaa | AE3: =IFERROR(__xludf.DUMMYFUNCTION("""COMPUTED_VALUE"""),"019eb1df-f256-71a1-b1ce-7c7ae8b244bc") -> 019eb1df-f256-71a1-b1ce-7c7ae8b244bc | AF3: =IFERROR(__xludf.DUMMYFUNCTION("""COMPUTED_VALUE"""),46183.59097222222) -> 46183.591 | AG3: =IFERROR(__xludf.DUMMYFUNCTION("""COMPUTED_VALUE"""),"credit") -> credit | AH3: =IFERROR(__xludf.DUMMYFUNCTION("""COMPUTED_VALUE"""),"29997.68") -> 29997.68 | AI3: =IFERROR(__xludf.DUMMYFUNCTION("""COMPUTED_VALUE"""),"cash_isa") -> cash_isa | AJ3: =IFERROR(__xludf.DUMMYFUNCTION("""COMPUTED_VALUE"""),"9bc00e6b-ce5f-48c5-ae3a-1baabe00f337") -> 9bc00e6b-ce5f-48c5-ae3a-1baabe00f337 | AK3: =IFERROR(__xludf.DUMMYFUNCTION("""COMPUTED_VALUE"""),"e3a86178-e782-4b8e-a5af-c71a91f91e51") -> e3a86178-e782-4b8e-a5af-c71a91f91e51 | AL3: =IFERROR(__xludf.DUMMYFUNCTION("""COMPUTED_VALUE"""),"e3a86178-e782-4b8e-a5af-c71a91f91e51") -> e3a86178-e782-4b8e-a5af-c71a91f91e51 | AM3: =IFERROR(__xludf.DUMMYFUNCTION("""COMPUTED_VALUE"""),"400250 51421336-2136136478") -> 400250 51421336-2136136478 | AN3: =IFERROR(__xludf.DUMMYFUNCTION("""COMPUTED_VALUE"""),29997.68) -> 29997.68 | AO3: =IFERROR(__xludf.DUMMYFUNCTION("""COMPUTED_VALUE"""),"payin") -> payin | AP3: =IFERROR(__xludf.DUMMYFUNCTION("""COMPUTED_VALUE"""),46182.22638888889) -> 46182.226 | AR3: =ROUND(VALUE(AH3),2)&"_"&TRIM(LOWER(AG3)) -> 29997.68_credit | AS3: =IF(AH3="", "", LET(current_amt, ROUND(VALUE(AH3), 2), current_dir, TRIM(LOWER(AG3)), opposite_dir, IF(current_dir="credit", "debit", "credit"), occ, COUNTIFS($AH$3:AH3, AH3, $AG$3:AG3, AG3), opp_total, COUNTIFS($AH$3:$AH$1000, AH3, $AG$3:$AG$1000, opposite_dir), IF(opp_total >= occ, "DROP", "KEEP"))) -> KEEP | AU3: =IFERROR(__xludf.DUMMYFUNCTION("SORT(FILTER(AD3:AP1000, AS3:AS1000=""KEEP""),3,TRUE)"),"73df5aae-f42a-49a0-9d8f-616ca6dbebaa") -> 73df5aae-f42a-49a0-9d8f-616ca6dbebaa | AV3: =IFERROR(__xludf.DUMMYFUNCTION("""COMPUTED_VALUE"""),"019eb1df-f256-71a1-b1ce-7c7ae8b244bc") -> 019eb1df-f256-71a1-b1ce-7c7ae8b244bc | AW3: =IFERROR(__xludf.DUMMYFUNCTION("""COMPUTED_VALUE"""),46183.59097222222) -> 46183.591 | AX3: =IFERROR(__xludf.DUMMYFUNCTION("""COMPUTED_VALUE"""),"credit") -> credit | AY3: =IFERROR(__xludf.DUMMYFUNCTION("""COMPUTED_VALUE"""),"29997.68") -> 29997.68 | AZ3: =IFERROR(__xludf.DUMMYFUNCTION("""COMPUTED_VALUE"""),"cash_isa") -> cash_isa | BA3: =IFERROR(__xludf.DUMMYFUNCTION("""COMPUTED_VALUE"""),"9bc00e6b-ce5f-48c5-ae3a-1baabe00f337") -> 9bc00e6b-ce5f-48c5-ae3a-1baabe00f337 | BB3: =IFERROR(__xludf.DUMMYFUNCTION("""COMPUTED_VALUE"""),"e3a86178-e782-4b8e-a5af-c71a91f91e51") -> e3a86178-e782-4b8e-a5af-c71a91f91e51 | BC3: =IFERROR(__xludf.DUMMYFUNCTION("""COMPUTED_VALUE"""),"e3a86178-e782-4b8e-a5af-c71a91f91e51") -> e3a86178-e782-4b8e-a5af-c71a91f91e51 | BD3: =IFERROR(__xludf.DUMMYFUNCTION("""COMPUTED_VALUE"""),"400250 51421336-2136136478") -> 400250 51421336-2136136478 | BE3: =IFERROR(__xludf.DUMMYFUNCTION("""COMPUTED_VALUE"""),29997.68) -> 29997.68 | BF3: =IFERROR(__xludf.DUMMYFUNCTION("""COMPUTED_VALUE"""),"payin") -> payin | BG3: =IFERROR(__xludf.DUMMYFUNCTION("""COMPUTED_VALUE"""),46182.22638888889) -> 46182.226 | BI3: =IFERROR(__xludf.DUMMYFUNCTION("SORT(FILTER(AD1557:AP5000, AS1557:AS5000=""KEEP""),3,TRUE)"),"73df5aae-f42a-49a0-9d8f-616ca6dbebaa") -> 73df5aae-f42a-49a0-9d8f-616ca6dbebaa | BJ3: =IFERROR(__xludf.DUMMYFUNCTION("""COMPUTED_VALUE"""),"0199816b-0e35-745a-bffb-2eb385b18f78") -> 0199816b-0e35-745a-bffb-2eb385b18f78 | BK3: =IFERROR(__xludf.DUMMYFUNCTION("""COMPUTED_VALUE"""),45925.63055555556) -> 45925.631 | BL3: =IFERROR(__xludf.DUMMYFUNCTION("""COMPUTED_VALUE"""),"credit") -> credit | BM3: =IFERROR(__xludf.DUMMYFUNCTION("""COMPUTED_VALUE"""),"25.82") -> 25.82 | BN3: =IFERROR(__xludf.DUMMYFUNCTION("""COMPUTED_VALUE"""),"lisa") -> lisa | BO3: =IFERROR(__xludf.DUMMYFUNCTION("""COMPUTED_VALUE"""),"b7a59586-5d10-4989-91c2-f2376c7a6ab2") -> b7a59586-5d10-4989-91c2-f2376c7a6ab2 | BP3: =IFERROR(__xludf.DUMMYFUNCTION("""COMPUTED_VALUE"""),"8ecd675b-d3b5-4b51-9aee-fc2c558679b5") -> 8ecd675b-d3b5-4b51-9aee-fc2c558679b5 | BS3: =IFERROR(__xludf.DUMMYFUNCTION("""COMPUTED_VALUE"""),25.82) -> 25.82
A4: 73df5aae-f42a-49a0-9d8f-616ca6dbebaa | B4: 019ecf66-4e5f-7d1d-ab8b-3f663490584d | C4: 46189.325 | D4: credit | E4: 6879.1 | F4: cash_isa | G4: 9bc00e6b-ce5f-48c5-ae3a-1baabe00f337 | H4: 91d3f2bc-40eb-40b5-abfd-b8c37565b61e | AD4: =IFERROR(__xludf.DUMMYFUNCTION("""COMPUTED_VALUE"""),"73df5aae-f42a-49a0-9d8f-616ca6dbebaa") -> 73df5aae-f42a-49a0-9d8f-616ca6dbebaa | AE4: =IFERROR(__xludf.DUMMYFUNCTION("""COMPUTED_VALUE"""),"019eb6b9-c0a2-7317-ab4a-c235d039858e") -> 019eb6b9-c0a2-7317-ab4a-c235d039858e | AF4: =IFERROR(__xludf.DUMMYFUNCTION("""COMPUTED_VALUE"""),46184.53333333333) -> 46184.533 | AG4: =IFERROR(__xludf.DUMMYFUNCTION("""COMPUTED_VALUE"""),"credit") -> credit | AH4: =IFERROR(__xludf.DUMMYFUNCTION("""COMPUTED_VALUE"""),18184.43) -> 18184.43 | AI4: =IFERROR(__xludf.DUMMYFUNCTION("""COMPUTED_VALUE"""),"cash_isa") -> cash_isa | AJ4: =IFERROR(__xludf.DUMMYFUNCTION("""COMPUTED_VALUE"""),"9bc00e6b-ce5f-48c5-ae3a-1baabe00f337") -> 9bc00e6b-ce5f-48c5-ae3a-1baabe00f337 | AK4: =IFERROR(__xludf.DUMMYFUNCTION("""COMPUTED_VALUE"""),"8a36818d-cb4b-4b51-98cd-feffaecfad30") -> 8a36818d-cb4b-4b51-98cd-feffaecfad30 | AL4: =IFERROR(__xludf.DUMMYFUNCTION("""COMPUTED_VALUE"""),"8a36818d-cb4b-4b51-98cd-feffaecfad30") -> 8a36818d-cb4b-4b51-98cd-feffaecfad30 | AM4: =IFERROR(__xludf.DUMMYFUNCTION("""COMPUTED_VALUE"""),"13267202-51989231") -> 13267202-51989231 | AN4: =IFERROR(__xludf.DUMMYFUNCTION("""COMPUTED_VALUE"""),18184.43) -> 18184.43 | AO4: =IFERROR(__xludf.DUMMYFUNCTION("""COMPUTED_VALUE"""),"payin") -> payin | AP4: =IFERROR(__xludf.DUMMYFUNCTION("""COMPUTED_VALUE"""),46183.16875) -> 46183.169 | AR4: =ROUND(VALUE(AH4),2)&"_"&TRIM(LOWER(AG4)) -> 18184.43_credit | AS4: =IF(AH4="", "", LET(current_amt, ROUND(VALUE(AH4), 2), current_dir, TRIM(LOWER(AG4)), opposite_dir, IF(current_dir="credit", "debit", "credit"), occ, COUNTIFS($AH$3:AH4, AH4, $AG$3:AG4, AG4), opp_total, COUNTIFS($AH$3:$AH$1000, AH4, $AG$3:$AG$1000, opposite_dir), IF(opp_total >= occ, "DROP", "KEEP"))) -> KEEP | AU4: =IFERROR(__xludf.DUMMYFUNCTION("""COMPUTED_VALUE"""),"73df5aae-f42a-49a0-9d8f-616ca6dbebaa") -> 73df5aae-f42a-49a0-9d8f-616ca6dbebaa | AV4: =IFERROR(__xludf.DUMMYFUNCTION("""COMPUTED_VALUE"""),"019eb6b9-c0a2-7317-ab4a-c235d039858e") -> 019eb6b9-c0a2-7317-ab4a-c235d039858e | AW4: =IFERROR(__xludf.DUMMYFUNCTION("""COMPUTED_VALUE"""),46184.53333333333) -> 46184.533 | AX4: =IFERROR(__xludf.DUMMYFUNCTION("""COMPUTED_VALUE"""),"credit") -> credit | AY4: =IFERROR(__xludf.DUMMYFUNCTION("""COMPUTED_VALUE"""),18184.43) -> 18184.43 | AZ4: =IFERROR(__xludf.DUMMYFUNCTION("""COMPUTED_VALUE"""),"cash_isa") -> cash_isa | BA4: =IFERROR(__xludf.DUMMYFUNCTION("""COMPUTED_VALUE"""),"9bc00e6b-ce5f-48c5-ae3a-1baabe00f337") -> 9bc00e6b-ce5f-48c5-ae3a-1baabe00f337 | BB4: =IFERROR(__xludf.DUMMYFUNCTION("""COMPUTED_VALUE"""),"8a36818d-cb4b-4b51-98cd-feffaecfad30") -> 8a36818d-cb4b-4b51-98cd-feffaecfad30 | BC4: =IFERROR(__xludf.DUMMYFUNCTION("""COMPUTED_VALUE"""),"8a36818d-cb4b-4b51-98cd-feffaecfad30") -> 8a36818d-cb4b-4b51-98cd-feffaecfad30 | BD4: =IFERROR(__xludf.DUMMYFUNCTION("""COMPUTED_VALUE"""),"13267202-51989231") -> 13267202-51989231 | BE4: =IFERROR(__xludf.DUMMYFUNCTION("""COMPUTED_VALUE"""),18184.43) -> 18184.43 | BF4: =IFERROR(__xludf.DUMMYFUNCTION("""COMPUTED_VALUE"""),"payin") -> payin | BG4: =IFERROR(__xludf.DUMMYFUNCTION("""COMPUTED_VALUE"""),46183.16875) -> 46183.169 | BI4: =IFERROR(__xludf.DUMMYFUNCTION("""COMPUTED_VALUE"""),"73df5aae-f42a-49a0-9d8f-616ca6dbebaa") -> 73df5aae-f42a-49a0-9d8f-616ca6dbebaa | BJ4: =IFERROR(__xludf.DUMMYFUNCTION("""COMPUTED_VALUE"""),"019a265f-0027-7d29-8ff1-8f39f64358c1") -> 019a265f-0027-7d29-8ff1-8f39f64358c1 | BK4: =IFERROR(__xludf.DUMMYFUNCTION("""COMPUTED_VALUE"""),45957.66111111111) -> 45957.661 | BL4: =IFERROR(__xludf.DUMMYFUNCTION("""COMPUTED_VALUE"""),"credit") -> credit | BM4: =IFERROR(__xludf.DUMMYFUNCTION("""COMPUTED_VALUE"""),"39.36") -> 39.36 | BN4: =IFERROR(__xludf.DUMMYFUNCTION("""COMPUTED_VALUE"""),"lisa") -> lisa | BO4: =IFERROR(__xludf.DUMMYFUNCTION("""COMPUTED_VALUE"""),"b7a59586-5d10-4989-91c2-f2376c7a6ab2") -> b7a59586-5d10-4989-91c2-f2376c7a6ab2 | BP4: =IFERROR(__xludf.DUMMYFUNCTION("""COMPUTED_VALUE"""),"7464d141-4aaa-46a8-ae96-c3c7997dfc03") -> 7464d141-4aaa-46a8-ae96-c3c7997dfc03 | BS4: =IFERROR(__xludf.DUMMYFUNCTION("""COMPUTED_VALUE"""),39.36) -> 39.36
A5: 73df5aae-f42a-49a0-9d8f-616ca6dbebaa | B5: 019ecf67-f3f8-7864-b2db-1d9be3c1983e | C5: 46189.326 | D5: debit | E5: 6879.1 | F5: cash_isa | G5: 9bc00e6b-ce5f-48c5-ae3a-1baabe00f337 | H5: 91d3f2bc-40eb-40b5-abfd-b8c37565b61e | AD5: =IFERROR(__xludf.DUMMYFUNCTION("""COMPUTED_VALUE"""),"73df5aae-f42a-49a0-9d8f-616ca6dbebaa") -> 73df5aae-f42a-49a0-9d8f-616ca6dbebaa | AE5: =IFERROR(__xludf.DUMMYFUNCTION("""COMPUTED_VALUE"""),"019ecb64-c843-7d12-81ee-f6401245704f") -> 019ecb64-c843-7d12-81ee-f6401245704f | AF5: =IFERROR(__xludf.DUMMYFUNCTION("""COMPUTED_VALUE"""),46188.54675925926) -> 46188.547 | AG5: =IFERROR(__xludf.DUMMYFUNCTION("""COMPUTED_VALUE"""),"credit") -> credit | AH5: =IFERROR(__xludf.DUMMYFUNCTION("""COMPUTED_VALUE"""),64323.37) -> 64323.37 | AI5: =IFERROR(__xludf.DUMMYFUNCTION("""COMPUTED_VALUE"""),"cash_isa") -> cash_isa | AJ5: =IFERROR(__xludf.DUMMYFUNCTION("""COMPUTED_VALUE"""),"9bc00e6b-ce5f-48c5-ae3a-1baabe00f337") -> 9bc00e6b-ce5f-48c5-ae3a-1baabe00f337 | AK5: =IFERROR(__xludf.DUMMYFUNCTION("""COMPUTED_VALUE"""),"79376e9a-a2d9-4da6-80da-2fccb69993e9") -> 79376e9a-a2d9-4da6-80da-2fccb69993e9 | AL5: =IFERROR(__xludf.DUMMYFUNCTION("""COMPUTED_VALUE"""),"79376e9a-a2d9-4da6-80da-2fccb69993e9") -> 79376e9a-a2d9-4da6-80da-2fccb69993e9 | AM5: =IFERROR(__xludf.DUMMYFUNCTION("""COMPUTED_VALUE"""),"NOREF-878813225") -> NOREF-878813225 | AN5: =IFERROR(__xludf.DUMMYFUNCTION("""COMPUTED_VALUE"""),64323.37) -> 64323.37 | AO5: =IFERROR(__xludf.DUMMYFUNCTION("""COMPUTED_VALUE"""),"payin") -> payin | AP5: =IFERROR(__xludf.DUMMYFUNCTION("""COMPUTED_VALUE"""),46185.08598379629) -> 46185.086 | AR5: =ROUND(VALUE(AH5),2)&"_"&TRIM(LOWER(AG5)) -> 64323.37_credit | AS5: =IF(AH5="", "", LET(current_amt, ROUND(VALUE(AH5), 2), current_dir, TRIM(LOWER(AG5)), opposite_dir, IF(current_dir="credit", "debit", "credit"), occ, COUNTIFS($AH$3:AH5, AH5, $AG$3:AG5, AG5), opp_total, COUNTIFS($AH$3:$AH$1000, AH5, $AG$3:$AG$1000, opposite_dir), IF(opp_total >= occ, "DROP", "KEEP"))) -> KEEP | AU5: =IFERROR(__xludf.DUMMYFUNCTION("""COMPUTED_VALUE"""),"73df5aae-f42a-49a0-9d8f-616ca6dbebaa") -> 73df5aae-f42a-49a0-9d8f-616ca6dbebaa | AV5: =IFERROR(__xludf.DUMMYFUNCTION("""COMPUTED_VALUE"""),"019ecb64-c843-7d12-81ee-f6401245704f") -> 019ecb64-c843-7d12-81ee-f6401245704f | AW5: =IFERROR(__xludf.DUMMYFUNCTION("""COMPUTED_VALUE"""),46188.54675925926) -> 46188.547 | AX5: =IFERROR(__xludf.DUMMYFUNCTION("""COMPUTED_VALUE"""),"credit") -> credit | AY5: =IFERROR(__xludf.DUMMYFUNCTION("""COMPUTED_VALUE"""),64323.37) -> 64323.37 | AZ5: =IFERROR(__xludf.DUMMYFUNCTION("""COMPUTED_VALUE"""),"cash_isa") -> cash_isa | BA5: =IFERROR(__xludf.DUMMYFUNCTION("""COMPUTED_VALUE"""),"9bc00e6b-ce5f-48c5-ae3a-1baabe00f337") -> 9bc00e6b-ce5f-48c5-ae3a-1baabe00f337 | BB5: =IFERROR(__xludf.DUMMYFUNCTION("""COMPUTED_VALUE"""),"79376e9a-a2d9-4da6-80da-2fccb69993e9") -> 79376e9a-a2d9-4da6-80da-2fccb69993e9 | BC5: =IFERROR(__xludf.DUMMYFUNCTION("""COMPUTED_VALUE"""),"79376e9a-a2d9-4da6-80da-2fccb69993e9") -> 79376e9a-a2d9-4da6-80da-2fccb69993e9 | BD5: =IFERROR(__xludf.DUMMYFUNCTION("""COMPUTED_VALUE"""),"NOREF-878813225") -> NOREF-878813225 | BE5: =IFERROR(__xludf.DUMMYFUNCTION("""COMPUTED_VALUE"""),64323.37) -> 64323.37 | BF5: =IFERROR(__xludf.DUMMYFUNCTION("""COMPUTED_VALUE"""),"payin") -> payin | BG5: =IFERROR(__xludf.DUMMYFUNCTION("""COMPUTED_VALUE"""),46185.08598379629) -> 46185.086 | BI5: =IFERROR(__xludf.DUMMYFUNCTION("""COMPUTED_VALUE"""),"73df5aae-f42a-49a0-9d8f-616ca6dbebaa") -> 73df5aae-f42a-49a0-9d8f-616ca6dbebaa | BJ5: =IFERROR(__xludf.DUMMYFUNCTION("""COMPUTED_VALUE"""),"019c0522-3a07-719b-bcbd-b2f0eb14e013") -> 019c0522-3a07-719b-bcbd-b2f0eb14e013 | BK5: =IFERROR(__xludf.DUMMYFUNCTION("""COMPUTED_VALUE"""),46050.62777777778) -> 46050.628 | BL5: =IFERROR(__xludf.DUMMYFUNCTION("""COMPUTED_VALUE"""),"credit") -> credit | BM5: =IFERROR(__xludf.DUMMYFUNCTION("""COMPUTED_VALUE"""),"1250.5") -> 1250.5 | BN5: =IFERROR(__xludf.DUMMYFUNCTION("""COMPUTED_VALUE"""),"lisa") -> lisa | BO5: =IFERROR(__xludf.DUMMYFUNCTION("""COMPUTED_VALUE"""),"b7a59586-5d10-4989-91c2-f2376c7a6ab2") -> b7a59586-5d10-4989-91c2-f2376c7a6ab2 | BP5: =IFERROR(__xludf.DUMMYFUNCTION("""COMPUTED_VALUE"""),"7464d141-4aaa-46a8-ae96-c3c7997dfc03") -> 7464d141-4aaa-46a8-ae96-c3c7997dfc03 | BS5: =IFERROR(__xludf.DUMMYFUNCTION("""COMPUTED_VALUE"""),1250.5) -> 1250.5
A6: 73df5aae-f42a-49a0-9d8f-616ca6dbebaa | B6: 019ecf6b-b130-7c98-ab0b-5639f735de4f | C6: 46189.329 | D6: credit | E6: 1000 | F6: cash_isa | G6: 9bc00e6b-ce5f-48c5-ae3a-1baabe00f337 | H6: 594e43b2-4c16-4cdd-9a32-89078ce028d1 | AD6: =IFERROR(__xludf.DUMMYFUNCTION("""COMPUTED_VALUE"""),"73df5aae-f42a-49a0-9d8f-616ca6dbebaa") -> 73df5aae-f42a-49a0-9d8f-616ca6dbebaa | AE6: =IFERROR(__xludf.DUMMYFUNCTION("""COMPUTED_VALUE"""),"019ecb64-c733-7ae4-944c-db2cb0274f72") -> 019ecb64-c733-7ae4-944c-db2cb0274f72 | AF6: =IFERROR(__xludf.DUMMYFUNCTION("""COMPUTED_VALUE"""),46188.54675925926) -> 46188.547 | AG6: =IFERROR(__xludf.DUMMYFUNCTION("""COMPUTED_VALUE"""),"credit") -> credit | AH6: =IFERROR(__xludf.DUMMYFUNCTION("""COMPUTED_VALUE"""),40492.94) -> 40492.94 | AI6: =IFERROR(__xludf.DUMMYFUNCTION("""COMPUTED_VALUE"""),"cash_isa") -> cash_isa | AJ6: =IFERROR(__xludf.DUMMYFUNCTION("""COMPUTED_VALUE"""),"9bc00e6b-ce5f-48c5-ae3a-1baabe00f337") -> 9bc00e6b-ce5f-48c5-ae3a-1baabe00f337 | AK6: =IFERROR(__xludf.DUMMYFUNCTION("""COMPUTED_VALUE"""),"d1610b83-cb8b-45f0-bea4-69fec40f5e82") -> d1610b83-cb8b-45f0-bea4-69fec40f5e82 | AL6: =IFERROR(__xludf.DUMMYFUNCTION("""COMPUTED_VALUE"""),"d1610b83-cb8b-45f0-bea4-69fec40f5e82") -> d1610b83-cb8b-45f0-bea4-69fec40f5e82 | AM6: =IFERROR(__xludf.DUMMYFUNCTION("""COMPUTED_VALUE"""),"NOREF-1362020235") -> NOREF-1362020235 | AN6: =IFERROR(__xludf.DUMMYFUNCTION("""COMPUTED_VALUE"""),40492.94) -> 40492.94 | AO6: =IFERROR(__xludf.DUMMYFUNCTION("""COMPUTED_VALUE"""),"payin") -> payin | AP6: =IFERROR(__xludf.DUMMYFUNCTION("""COMPUTED_VALUE"""),46185.668761574074) -> 46185.669 | AR6: =ROUND(VALUE(AH6),2)&"_"&TRIM(LOWER(AG6)) -> 40492.94_credit | AS6: =IF(AH6="", "", LET(current_amt, ROUND(VALUE(AH6), 2), current_dir, TRIM(LOWER(AG6)), opposite_dir, IF(current_dir="credit", "debit", "credit"), occ, COUNTIFS($AH$3:AH6, AH6, $AG$3:AG6, AG6), opp_total, COUNTIFS($AH$3:$AH$1000, AH6, $AG$3:$AG$1000, opposite_dir), IF(opp_total >= occ, "DROP", "KEEP"))) -> KEEP | AU6: =IFERROR(__xludf.DUMMYFUNCTION("""COMPUTED_VALUE"""),"73df5aae-f42a-49a0-9d8f-616ca6dbebaa") -> 73df5aae-f42a-49a0-9d8f-616ca6dbebaa | AV6: =IFERROR(__xludf.DUMMYFUNCTION("""COMPUTED_VALUE"""),"019ecb64-c733-7ae4-944c-db2cb0274f72") -> 019ecb64-c733-7ae4-944c-db2cb0274f72 | AW6: =IFERROR(__xludf.DUMMYFUNCTION("""COMPUTED_VALUE"""),46188.54675925926) -> 46188.547 | AX6: =IFERROR(__xludf.DUMMYFUNCTION("""COMPUTED_VALUE"""),"credit") -> credit | AY6: =IFERROR(__xludf.DUMMYFUNCTION("""COMPUTED_VALUE"""),40492.94) -> 40492.94 | AZ6: =IFERROR(__xludf.DUMMYFUNCTION("""COMPUTED_VALUE"""),"cash_isa") -> cash_isa | BA6: =IFERROR(__xludf.DUMMYFUNCTION("""COMPUTED_VALUE"""),"9bc00e6b-ce5f-48c5-ae3a-1baabe00f337") -> 9bc00e6b-ce5f-48c5-ae3a-1baabe00f337 | BB6: =IFERROR(__xludf.DUMMYFUNCTION("""COMPUTED_VALUE"""),"d1610b83-cb8b-45f0-bea4-69fec40f5e82") -> d1610b83-cb8b-45f0-bea4-69fec40f5e82 | BC6: =IFERROR(__xludf.DUMMYFUNCTION("""COMPUTED_VALUE"""),"d1610b83-cb8b-45f0-bea4-69fec40f5e82") -> d1610b83-cb8b-45f0-bea4-69fec40f5e82 | BD6: =IFERROR(__xludf.DUMMYFUNCTION("""COMPUTED_VALUE"""),"NOREF-1362020235") -> NOREF-1362020235 | BE6: =IFERROR(__xludf.DUMMYFUNCTION("""COMPUTED_VALUE"""),40492.94) -> 40492.94 | BF6: =IFERROR(__xludf.DUMMYFUNCTION("""COMPUTED_VALUE"""),"payin") -> payin | BG6: =IFERROR(__xludf.DUMMYFUNCTION("""COMPUTED_VALUE"""),46185.668761574074) -> 46185.669 | BI6: =IFERROR(__xludf.DUMMYFUNCTION("""COMPUTED_VALUE"""),"73df5aae-f42a-49a0-9d8f-616ca6dbebaa") -> 73df5aae-f42a-49a0-9d8f-616ca6dbebaa | BJ6: =IFERROR(__xludf.DUMMYFUNCTION("""COMPUTED_VALUE"""),"019c9e6e-9ac8-7b3e-a27b-af919f6932b8") -> 019c9e6e-9ac8-7b3e-a27b-af919f6932b8 | BK6: =IFERROR(__xludf.DUMMYFUNCTION("""COMPUTED_VALUE"""),46080.39513888889) -> 46080.395 | BL6: =IFERROR(__xludf.DUMMYFUNCTION("""COMPUTED_VALUE"""),"credit") -> credit | BM6: =IFERROR(__xludf.DUMMYFUNCTION("""COMPUTED_VALUE"""),"2509.51") -> 2509.51 | BN6: =IFERROR(__xludf.DUMMYFUNCTION("""COMPUTED_VALUE"""),"lisa") -> lisa | BO6: =IFERROR(__xludf.DUMMYFUNCTION("""COMPUTED_VALUE"""),"b7a59586-5d10-4989-91c2-f2376c7a6ab2") -> b7a59586-5d10-4989-91c2-f2376c7a6ab2 | BP6: =IFERROR(__xludf.DUMMYFUNCTION("""COMPUTED_VALUE"""),"7464d141-4aaa-46a8-ae96-c3c7997dfc03") -> 7464d141-4aaa-46a8-ae96-c3c7997dfc03 | BS6: =IFERROR(__xludf.DUMMYFUNCTION("""COMPUTED_VALUE"""),2168.01) -> 2168.01
A7: 73df5aae-f42a-49a0-9d8f-616ca6dbebaa | B7: 019ecf6d-7783-75cc-a067-1d4535a564d3 | C7: 46189.33 | D7: debit | E7: 1000 | F7: cash_isa | G7: 9bc00e6b-ce5f-48c5-ae3a-1baabe00f337 | H7: 594e43b2-4c16-4cdd-9a32-89078ce028d1 | AD7: =IFERROR(__xludf.DUMMYFUNCTION("""COMPUTED_VALUE"""),"73df5aae-f42a-49a0-9d8f-616ca6dbebaa") -> 73df5aae-f42a-49a0-9d8f-616ca6dbebaa | AE7: =IFERROR(__xludf.DUMMYFUNCTION("""COMPUTED_VALUE"""),"019ed024-854b-7377-878e-9bd25cd97072") -> 019ed024-854b-7377-878e-9bd25cd97072 | AF7: =IFERROR(__xludf.DUMMYFUNCTION("""COMPUTED_VALUE"""),46189.468923611115) -> 46189.469 | AG7: =IFERROR(__xludf.DUMMYFUNCTION("""COMPUTED_VALUE"""),"credit") -> credit | AH7: =IFERROR(__xludf.DUMMYFUNCTION("""COMPUTED_VALUE"""),21471.6) -> 21471.6 | AI7: =IFERROR(__xludf.DUMMYFUNCTION("""COMPUTED_VALUE"""),"cash_isa") -> cash_isa | AJ7: =IFERROR(__xludf.DUMMYFUNCTION("""COMPUTED_VALUE"""),"9bc00e6b-ce5f-48c5-ae3a-1baabe00f337") -> 9bc00e6b-ce5f-48c5-ae3a-1baabe00f337 | AK7: =IFERROR(__xludf.DUMMYFUNCTION("""COMPUTED_VALUE"""),"228cd2f5-1ee0-4962-a649-82c9f17961ae") -> 228cd2f5-1ee0-4962-a649-82c9f17961ae | AL7: =IFERROR(__xludf.DUMMYFUNCTION("""COMPUTED_VALUE"""),"228cd2f5-1ee0-4962-a649-82c9f17961ae") -> 228cd2f5-1ee0-4962-a649-82c9f17961ae | AM7: =IFERROR(__xludf.DUMMYFUNCTION("""COMPUTED_VALUE"""),"WK648730Ba-580073357") -> WK648730Ba-580073357 | AN7: =IFERROR(__xludf.DUMMYFUNCTION("""COMPUTED_VALUE"""),21471.6) -> 21471.6 | AO7: =IFERROR(__xludf.DUMMYFUNCTION("""COMPUTED_VALUE"""),"payin") -> payin | AP7: =IFERROR(__xludf.DUMMYFUNCTION("""COMPUTED_VALUE"""),46188.66883101852) -> 46188.669 | AR7: =ROUND(VALUE(AH7),2)&"_"&TRIM(LOWER(AG7)) -> 21471.6_credit | AS7: =IF(AH7="", "", LET(current_amt, ROUND(VALUE(AH7), 2), current_dir, TRIM(LOWER(AG7)), opposite_dir, IF(current_dir="credit", "debit", "credit"), occ, COUNTIFS($AH$3:AH7, AH7, $AG$3:AG7, AG7), opp_total, COUNTIFS($AH$3:$AH$1000, AH7, $AG$3:$AG$1000, opposite_dir), IF(opp_total >= occ, "DROP", "KEEP"))) -> KEEP | AU7: =IFERROR(__xludf.DUMMYFUNCTION("""COMPUTED_VALUE"""),"73df5aae-f42a-49a0-9d8f-616ca6dbebaa") -> 73df5aae-f42a-49a0-9d8f-616ca6dbebaa | AV7: =IFERROR(__xludf.DUMMYFUNCTION("""COMPUTED_VALUE"""),"019ecfae-a956-7cee-9cd6-cc020e483641") -> 019ecfae-a956-7cee-9cd6-cc020e483641 | AW7: =IFERROR(__xludf.DUMMYFUNCTION("""COMPUTED_VALUE"""),46189.379525462966) -> 46189.38 | AX7: =IFERROR(__xludf.DUMMYFUNCTION("""COMPUTED_VALUE"""),"debit") -> debit | AY7: =IFERROR(__xludf.DUMMYFUNCTION("""COMPUTED_VALUE"""),13326.74) -> 13326.74 | AZ7: =IFERROR(__xludf.DUMMYFUNCTION("""COMPUTED_VALUE"""),"cash_isa") -> cash_isa | BA7: =IFERROR(__xludf.DUMMYFUNCTION("""COMPUTED_VALUE"""),"9bc00e6b-ce5f-48c5-ae3a-1baabe00f337") -> 9bc00e6b-ce5f-48c5-ae3a-1baabe00f337 | BB7: =IFERROR(__xludf.DUMMYFUNCTION("""COMPUTED_VALUE"""),"f0a37a7e-0033-47e7-97ae-2a9b66aa8fa6") -> f0a37a7e-0033-47e7-97ae-2a9b66aa8fa6 | BC7: =IFERROR(__xludf.DUMMYFUNCTION("""COMPUTED_VALUE"""),"f0a37a7e-0033-47e7-97ae-2a9b66aa8fa6") -> f0a37a7e-0033-47e7-97ae-2a9b66aa8fa6 | BE7: =IFERROR(__xludf.DUMMYFUNCTION("""COMPUTED_VALUE"""),13326.74) -> 13326.74 | BF7: =IFERROR(__xludf.DUMMYFUNCTION("""COMPUTED_VALUE"""),"payout") -> payout | BG7: =IFERROR(__xludf.DUMMYFUNCTION("""COMPUTED_VALUE"""),46183.25782407407) -> 46183.258 | BI7: =IFERROR(__xludf.DUMMYFUNCTION("""COMPUTED_VALUE"""),"73df5aae-f42a-49a0-9d8f-616ca6dbebaa") -> 73df5aae-f42a-49a0-9d8f-616ca6dbebaa | BJ7: =IFERROR(__xludf.DUMMYFUNCTION("""COMPUTED_VALUE"""),"019e986b-6909-779a-852a-fdf77fb1f880") -> 019e986b-6909-779a-852a-fdf77fb1f880 | BK7: =IFERROR(__xludf.DUMMYFUNCTION("""COMPUTED_VALUE"""),46178.64857638889) -> 46178.649 | BL7: =IFERROR(__xludf.DUMMYFUNCTION("""COMPUTED_VALUE"""),"credit") -> credit | BM7: =IFERROR(__xludf.DUMMYFUNCTION("""COMPUTED_VALUE"""),13.99) -> 13.99 | BN7: =IFERROR(__xludf.DUMMYFUNCTION("""COMPUTED_VALUE"""),"lisa") -> lisa | BO7: =IFERROR(__xludf.DUMMYFUNCTION("""COMPUTED_VALUE"""),"b7a59586-5d10-4989-91c2-f2376c7a6ab2") -> b7a59586-5d10-4989-91c2-f2376c7a6ab2 | BP7: =IFERROR(__xludf.DUMMYFUNCTION("""COMPUTED_VALUE"""),"6e288a26-6f54-4606-af76-43cc91f9103c") -> 6e288a26-6f54-4606-af76-43cc91f9103c | BQ7: =IFERROR(__xludf.DUMMYFUNCTION("""COMPUTED_VALUE"""),"6e288a26-6f54-4606-af76-43cc91f9103c") -> 6e288a26-6f54-4606-af76-43cc91f9103c | BR7: =IFERROR(__xludf.DUMMYFUNCTION("""COMPUTED_VALUE"""),"NOREF-190470356") -> NOREF-190470356 | BS7: =IFERROR(__xludf.DUMMYFUNCTION("""COMPUTED_VALUE"""),13.99) -> 13.99 | BT7: =IFERROR(__xludf.DUMMYFUNCTION("""COMPUTED_VALUE"""),"payin") -> payin | BU7: =IFERROR(__xludf.DUMMYFUNCTION("""COMPUTED_VALUE"""),46177.47902777778) -> 46177.479
A8: 73df5aae-f42a-49a0-9d8f-616ca6dbebaa | B8: 019ecf6e-8f11-753c-8898-9bf70a4b7f21 | C8: 46189.331 | D8: credit | E8: 21769.77 | F8: cash_isa | G8: 9bc00e6b-ce5f-48c5-ae3a-1baabe00f337 | H8: 9438e43a-27ed-4543-a6a9-a8d6dcc297fa | AD8: =IFERROR(__xludf.DUMMYFUNCTION("""COMPUTED_VALUE"""),"73df5aae-f42a-49a0-9d8f-616ca6dbebaa") -> 73df5aae-f42a-49a0-9d8f-616ca6dbebaa | AE8: =IFERROR(__xludf.DUMMYFUNCTION("""COMPUTED_VALUE"""),"019ed024-864c-78df-b53a-e34f6f766c49") -> 019ed024-864c-78df-b53a-e34f6f766c49 | AF8: =IFERROR(__xludf.DUMMYFUNCTION("""COMPUTED_VALUE"""),46189.468923611115) -> 46189.469 | AG8: =IFERROR(__xludf.DUMMYFUNCTION("""COMPUTED_VALUE"""),"credit") -> credit | AH8: =IFERROR(__xludf.DUMMYFUNCTION("""COMPUTED_VALUE"""),20974.52) -> 20974.52 | AI8: =IFERROR(__xludf.DUMMYFUNCTION("""COMPUTED_VALUE"""),"cash_isa") -> cash_isa | AJ8: =IFERROR(__xludf.DUMMYFUNCTION("""COMPUTED_VALUE"""),"9bc00e6b-ce5f-48c5-ae3a-1baabe00f337") -> 9bc00e6b-ce5f-48c5-ae3a-1baabe00f337 | AK8: =IFERROR(__xludf.DUMMYFUNCTION("""COMPUTED_VALUE"""),"084ad475-9333-4dbe-8fb5-7d7b8ad84064") -> 084ad475-9333-4dbe-8fb5-7d7b8ad84064 | AL8: =IFERROR(__xludf.DUMMYFUNCTION("""COMPUTED_VALUE"""),"084ad475-9333-4dbe-8fb5-7d7b8ad84064") -> 084ad475-9333-4dbe-8fb5-7d7b8ad84064 | AM8: =IFERROR(__xludf.DUMMYFUNCTION("""COMPUTED_VALUE"""),"NZ656284A-1098901635") -> NZ656284A-1098901635 | AN8: =IFERROR(__xludf.DUMMYFUNCTION("""COMPUTED_VALUE"""),20974.52) -> 20974.52 | AO8: =IFERROR(__xludf.DUMMYFUNCTION("""COMPUTED_VALUE"""),"payin") -> payin | AP8: =IFERROR(__xludf.DUMMYFUNCTION("""COMPUTED_VALUE"""),46188.66883101852) -> 46188.669 | AR8: =ROUND(VALUE(AH8),2)&"_"&TRIM(LOWER(AG8)) -> 20974.52_credit | AS8: =IF(AH8="", "", LET(current_amt, ROUND(VALUE(AH8), 2), current_dir, TRIM(LOWER(AG8)), opposite_dir, IF(current_dir="credit", "debit", "credit"), occ, COUNTIFS($AH$3:AH8, AH8, $AG$3:AG8, AG8), opp_total, COUNTIFS($AH$3:$AH$1000, AH8, $AG$3:$AG$1000, opposite_dir), IF(opp_total >= occ, "DROP", "KEEP"))) -> KEEP | AU8: =IFERROR(__xludf.DUMMYFUNCTION("""COMPUTED_VALUE"""),"73df5aae-f42a-49a0-9d8f-616ca6dbebaa") -> 73df5aae-f42a-49a0-9d8f-616ca6dbebaa | AV8: =IFERROR(__xludf.DUMMYFUNCTION("""COMPUTED_VALUE"""),"019ecfb2-4980-7229-903f-40db4994fdf1") -> 019ecfb2-4980-7229-903f-40db4994fdf1 | AW8: =IFERROR(__xludf.DUMMYFUNCTION("""COMPUTED_VALUE"""),46189.382268518515) -> 46189.382 | AX8: =IFERROR(__xludf.DUMMYFUNCTION("""COMPUTED_VALUE"""),"debit") -> debit | AY8: =IFERROR(__xludf.DUMMYFUNCTION("""COMPUTED_VALUE"""),18989.0) -> 18989 | AZ8: =IFERROR(__xludf.DUMMYFUNCTION("""COMPUTED_VALUE"""),"cash_isa") -> cash_isa | BA8: =IFERROR(__xludf.DUMMYFUNCTION("""COMPUTED_VALUE"""),"9bc00e6b-ce5f-48c5-ae3a-1baabe00f337") -> 9bc00e6b-ce5f-48c5-ae3a-1baabe00f337 | BB8: =IFERROR(__xludf.DUMMYFUNCTION("""COMPUTED_VALUE"""),"d02fd859-d682-4368-bc53-bdd594a15f1b") -> d02fd859-d682-4368-bc53-bdd594a15f1b | BC8: =IFERROR(__xludf.DUMMYFUNCTION("""COMPUTED_VALUE"""),"d02fd859-d682-4368-bc53-bdd594a15f1b") -> d02fd859-d682-4368-bc53-bdd594a15f1b | BD8: =IFERROR(__xludf.DUMMYFUNCTION("""COMPUTED_VALUE"""),"Return of Funds-501102174") -> Return of Funds-501102174 | BE8: =IFERROR(__xludf.DUMMYFUNCTION("""COMPUTED_VALUE"""),18989.0) -> 18989 | BF8: =IFERROR(__xludf.DUMMYFUNCTION("""COMPUTED_VALUE"""),"payin") -> payin | BG8: =IFERROR(__xludf.DUMMYFUNCTION("""COMPUTED_VALUE"""),46181.562314814815) -> 46181.562 | BI8: =IFERROR(__xludf.DUMMYFUNCTION("""COMPUTED_VALUE"""),"73df5aae-f42a-49a0-9d8f-616ca6dbebaa") -> 73df5aae-f42a-49a0-9d8f-616ca6dbebaa | BJ8: =IFERROR(__xludf.DUMMYFUNCTION("""COMPUTED_VALUE"""),"019ead2b-a847-7e9b-9cf2-ad8d1ba559ad") -> 019ead2b-a847-7e9b-9cf2-ad8d1ba559ad | BK8: =IFERROR(__xludf.DUMMYFUNCTION("""COMPUTED_VALUE"""),46182.67800925926) -> 46182.678 | BL8: =IFERROR(__xludf.DUMMYFUNCTION("""COMPUTED_VALUE"""),"credit") -> credit | BM8: =IFERROR(__xludf.DUMMYFUNCTION("""COMPUTED_VALUE"""),26032.55) -> 26032.55 | BN8: =IFERROR(__xludf.DUMMYFUNCTION("""COMPUTED_VALUE"""),"lisa") -> lisa | BO8: =IFERROR(__xludf.DUMMYFUNCTION("""COMPUTED_VALUE"""),"b7a59586-5d10-4989-91c2-f2376c7a6ab2") -> b7a59586-5d10-4989-91c2-f2376c7a6ab2 | BP8: =IFERROR(__xludf.DUMMYFUNCTION("""COMPUTED_VALUE"""),"ffe80a3e-ca2c-49f7-99e0-1fea99be39b5") -> ffe80a3e-ca2c-49f7-99e0-1fea99be39b5 | BQ8: =IFERROR(__xludf.DUMMYFUNCTION("""COMPUTED_VALUE"""),"ffe80a3e-ca2c-49f7-99e0-1fea99be39b5") -> ffe80a3e-ca2c-49f7-99e0-1fea99be39b5 | BR8: =IFERROR(__xludf.DUMMYFUNCTION("""COMPUTED_VALUE"""),"RETURN-810653200") -> RETURN-810653200 | BS8: =IFERROR(__xludf.DUMMYFUNCTION("""COMPUTED_VALUE"""),26032.55) -> 26032.55 | BT8: =IFERROR(__xludf.DUMMYFUNCTION("""COMPUTED_VALUE"""),"payin") -> payin | BU8: =IFERROR(__xludf.DUMMYFUNCTION("""COMPUTED_VALUE"""),46181.65377314815) -> 46181.654
A9: 73df5aae-f42a-49a0-9d8f-616ca6dbebaa | B9: 019ecf6f-d53d-72ab-945b-6e5f498392aa | C9: 46189.332 | D9: debit | E9: 21769.77 | F9: cash_isa | G9: 9bc00e6b-ce5f-48c5-ae3a-1baabe00f337 | H9: 9438e43a-27ed-4543-a6a9-a8d6dcc297fa | AD9: =IFERROR(__xludf.DUMMYFUNCTION("""COMPUTED_VALUE"""),"73df5aae-f42a-49a0-9d8f-616ca6dbebaa") -> 73df5aae-f42a-49a0-9d8f-616ca6dbebaa | AE9: =IFERROR(__xludf.DUMMYFUNCTION("""COMPUTED_VALUE"""),"019ed024-873d-7252-be6e-6e408eb5a4cb") -> 019ed024-873d-7252-be6e-6e408eb5a4cb | AF9: =IFERROR(__xludf.DUMMYFUNCTION("""COMPUTED_VALUE"""),46189.468923611115) -> 46189.469 | AG9: =IFERROR(__xludf.DUMMYFUNCTION("""COMPUTED_VALUE"""),"credit") -> credit | AH9: =IFERROR(__xludf.DUMMYFUNCTION("""COMPUTED_VALUE"""),20918.18) -> 20918.18 | AI9: =IFERROR(__xludf.DUMMYFUNCTION("""COMPUTED_VALUE"""),"cash_isa") -> cash_isa | AJ9: =IFERROR(__xludf.DUMMYFUNCTION("""COMPUTED_VALUE"""),"9bc00e6b-ce5f-48c5-ae3a-1baabe00f337") -> 9bc00e6b-ce5f-48c5-ae3a-1baabe00f337 | AK9: =IFERROR(__xludf.DUMMYFUNCTION("""COMPUTED_VALUE"""),"a7a2dae7-bd10-44fc-9b1b-25271dcf0442") -> a7a2dae7-bd10-44fc-9b1b-25271dcf0442 | AL9: =IFERROR(__xludf.DUMMYFUNCTION("""COMPUTED_VALUE"""),"a7a2dae7-bd10-44fc-9b1b-25271dcf0442") -> a7a2dae7-bd10-44fc-9b1b-25271dcf0442 | AM9: =IFERROR(__xludf.DUMMYFUNCTION("""COMPUTED_VALUE"""),"JX825895D-940686763") -> JX825895D-940686763 | AN9: =IFERROR(__xludf.DUMMYFUNCTION("""COMPUTED_VALUE"""),20918.18) -> 20918.18 | AO9: =IFERROR(__xludf.DUMMYFUNCTION("""COMPUTED_VALUE"""),"payin") -> payin | AP9: =IFERROR(__xludf.DUMMYFUNCTION("""COMPUTED_VALUE"""),46188.6688425926) -> 46188.669 | AR9: =ROUND(VALUE(AH9),2)&"_"&TRIM(LOWER(AG9)) -> 20918.18_credit | AS9: =IF(AH9="", "", LET(current_amt, ROUND(VALUE(AH9), 2), current_dir, TRIM(LOWER(AG9)), opposite_dir, IF(current_dir="credit", "debit", "credit"), occ, COUNTIFS($AH$3:AH9, AH9, $AG$3:AG9, AG9), opp_total, COUNTIFS($AH$3:$AH$1000, AH9, $AG$3:$AG$1000, opposite_dir), IF(opp_total >= occ, "DROP", "KEEP"))) -> KEEP | AU9: =IFERROR(__xludf.DUMMYFUNCTION("""COMPUTED_VALUE"""),"73df5aae-f42a-49a0-9d8f-616ca6dbebaa") -> 73df5aae-f42a-49a0-9d8f-616ca6dbebaa | AV9: =IFERROR(__xludf.DUMMYFUNCTION("""COMPUTED_VALUE"""),"019ed015-c5dc-794f-b403-b3a6b5e5bcb3") -> 019ed015-c5dc-794f-b403-b3a6b5e5bcb3 | AW9: =IFERROR(__xludf.DUMMYFUNCTION("""COMPUTED_VALUE"""),46189.45773148148) -> 46189.458 | AX9: =IFERROR(__xludf.DUMMYFUNCTION("""COMPUTED_VALUE"""),"debit") -> debit | AY9: =IFERROR(__xludf.DUMMYFUNCTION("""COMPUTED_VALUE"""),2000.0) -> 2000 | AZ9: =IFERROR(__xludf.DUMMYFUNCTION("""COMPUTED_VALUE"""),"cash_isa") -> cash_isa | BA9: =IFERROR(__xludf.DUMMYFUNCTION("""COMPUTED_VALUE"""),"9bc00e6b-ce5f-48c5-ae3a-1baabe00f337") -> 9bc00e6b-ce5f-48c5-ae3a-1baabe00f337 | BB9: =IFERROR(__xludf.DUMMYFUNCTION("""COMPUTED_VALUE"""),"484d47c0-4ba1-45b5-8762-e933a96e2578") -> 484d47c0-4ba1-45b5-8762-e933a96e2578 | BI9: =IFERROR(__xludf.DUMMYFUNCTION("""COMPUTED_VALUE"""),"73df5aae-f42a-49a0-9d8f-616ca6dbebaa") -> 73df5aae-f42a-49a0-9d8f-616ca6dbebaa | BJ9: =IFERROR(__xludf.DUMMYFUNCTION("""COMPUTED_VALUE"""),"019eb0ad-e1f7-7848-a2f9-cb38e5c86b1d") -> 019eb0ad-e1f7-7848-a2f9-cb38e5c86b1d | BK9: =IFERROR(__xludf.DUMMYFUNCTION("""COMPUTED_VALUE"""),46183.35932870371) -> 46183.359 | BL9: =IFERROR(__xludf.DUMMYFUNCTION("""COMPUTED_VALUE"""),"credit") -> credit | BM9: =IFERROR(__xludf.DUMMYFUNCTION("""COMPUTED_VALUE"""),15963.49) -> 15963.49 | BN9: =IFERROR(__xludf.DUMMYFUNCTION("""COMPUTED_VALUE"""),"lisa") -> lisa | BO9: =IFERROR(__xludf.DUMMYFUNCTION("""COMPUTED_VALUE"""),"b7a59586-5d10-4989-91c2-f2376c7a6ab2") -> b7a59586-5d10-4989-91c2-f2376c7a6ab2 | BP9: =IFERROR(__xludf.DUMMYFUNCTION("""COMPUTED_VALUE"""),"429d3d03-20ce-4949-97bc-52dd443bc473") -> 429d3d03-20ce-4949-97bc-52dd443bc473 | BQ9: =IFERROR(__xludf.DUMMYFUNCTION("""COMPUTED_VALUE"""),"429d3d03-20ce-4949-97bc-52dd443bc473") -> 429d3d03-20ce-4949-97bc-52dd443bc473 | BR9: =IFERROR(__xludf.DUMMYFUNCTION("""COMPUTED_VALUE"""),"NOREF-905760162") -> NOREF-905760162 | BS9: =IFERROR(__xludf.DUMMYFUNCTION("""COMPUTED_VALUE"""),15963.49) -> 15963.49 | BT9: =IFERROR(__xludf.DUMMYFUNCTION("""COMPUTED_VALUE"""),"payin") -> payin | BU9: =IFERROR(__xludf.DUMMYFUNCTION("""COMPUTED_VALUE"""),46181.49357638889) -> 46181.494
A10: 73df5aae-f42a-49a0-9d8f-616ca6dbebaa | B10: 019ecf71-0f39-7517-ba66-2d9a255cf8fb | C10: 46189.333 | D10: credit | E10: 12001.69 | F10: cash_isa | G10: 9bc00e6b-ce5f-48c5-ae3a-1baabe00f337 | H10: 43fda8b1-46b9-42e8-ae27-47e24487252b | AD10: =IFERROR(__xludf.DUMMYFUNCTION("""COMPUTED_VALUE"""),"73df5aae-f42a-49a0-9d8f-616ca6dbebaa") -> 73df5aae-f42a-49a0-9d8f-616ca6dbebaa | AE10: =IFERROR(__xludf.DUMMYFUNCTION("""COMPUTED_VALUE"""),"019ed024-8a33-7fb5-96a0-78ffd98b3516") -> 019ed024-8a33-7fb5-96a0-78ffd98b3516 | AF10: =IFERROR(__xludf.DUMMYFUNCTION("""COMPUTED_VALUE"""),46189.468935185185) -> 46189.469 | AG10: =IFERROR(__xludf.DUMMYFUNCTION("""COMPUTED_VALUE"""),"credit") -> credit | AH10: =IFERROR(__xludf.DUMMYFUNCTION("""COMPUTED_VALUE"""),7.35) -> 7.35 | AI10: =IFERROR(__xludf.DUMMYFUNCTION("""COMPUTED_VALUE"""),"cash_isa") -> cash_isa | AJ10: =IFERROR(__xludf.DUMMYFUNCTION("""COMPUTED_VALUE"""),"9bc00e6b-ce5f-48c5-ae3a-1baabe00f337") -> 9bc00e6b-ce5f-48c5-ae3a-1baabe00f337 | AK10: =IFERROR(__xludf.DUMMYFUNCTION("""COMPUTED_VALUE"""),"42c3a58b-fec1-43e1-b86e-f071b829ba7a") -> 42c3a58b-fec1-43e1-b86e-f071b829ba7a | AL10: =IFERROR(__xludf.DUMMYFUNCTION("""COMPUTED_VALUE"""),"42c3a58b-fec1-43e1-b86e-f071b829ba7a") -> 42c3a58b-fec1-43e1-b86e-f071b829ba7a | AM10: =IFERROR(__xludf.DUMMYFUNCTION("""COMPUTED_VALUE"""),"NOREF-910332414") -> NOREF-910332414 | AN10: =IFERROR(__xludf.DUMMYFUNCTION("""COMPUTED_VALUE"""),7.35) -> 7.35 | AO10: =IFERROR(__xludf.DUMMYFUNCTION("""COMPUTED_VALUE"""),"payin") -> payin | AP10: =IFERROR(__xludf.DUMMYFUNCTION("""COMPUTED_VALUE"""),46188.454293981486) -> 46188.454 | AR10: =ROUND(VALUE(AH10),2)&"_"&TRIM(LOWER(AG10)) -> 7.35_credit | AS10: =IF(AH10="", "", LET(current_amt, ROUND(VALUE(AH10), 2), current_dir, TRIM(LOWER(AG10)), opposite_dir, IF(current_dir="credit", "debit", "credit"), occ, COUNTIFS($AH$3:AH10, AH10, $AG$3:AG10, AG10), opp_total, COUNTIFS($AH$3:$AH$1000, AH10, $AG$3:$AG$1000, opposite_dir), IF(opp_total >= occ, "DROP", "KEEP"))) -> KEEP | AU10: =IFERROR(__xludf.DUMMYFUNCTION("""COMPUTED_VALUE"""),"73df5aae-f42a-49a0-9d8f-616ca6dbebaa") -> 73df5aae-f42a-49a0-9d8f-616ca6dbebaa | AV10: =IFERROR(__xludf.DUMMYFUNCTION("""COMPUTED_VALUE"""),"019ed015-d33d-7f61-8bb3-deadbf0d9c07") -> 019ed015-d33d-7f61-8bb3-deadbf0d9c07 | AW10: =IFERROR(__xludf.DUMMYFUNCTION("""COMPUTED_VALUE"""),46189.457777777774) -> 46189.458 | AX10: =IFERROR(__xludf.DUMMYFUNCTION("""COMPUTED_VALUE"""),"debit") -> debit | AY10: =IFERROR(__xludf.DUMMYFUNCTION("""COMPUTED_VALUE"""),3100.0) -> 3100 | AZ10: =IFERROR(__xludf.DUMMYFUNCTION("""COMPUTED_VALUE"""),"cash_isa") -> cash_isa | BA10: =IFERROR(__xludf.DUMMYFUNCTION("""COMPUTED_VALUE"""),"9bc00e6b-ce5f-48c5-ae3a-1baabe00f337") -> 9bc00e6b-ce5f-48c5-ae3a-1baabe00f337 | BB10: =IFERROR(__xludf.DUMMYFUNCTION("""COMPUTED_VALUE"""),"635da7fc-5835-4ab2-807a-a13c63aab420") -> 635da7fc-5835-4ab2-807a-a13c63aab420 | BI10: =IFERROR(__xludf.DUMMYFUNCTION("""COMPUTED_VALUE"""),"73df5aae-f42a-49a0-9d8f-616ca6dbebaa") -> 73df5aae-f42a-49a0-9d8f-616ca6dbebaa | BJ10: =IFERROR(__xludf.DUMMYFUNCTION("""COMPUTED_VALUE"""),"019eb2b6-0f93-7b2a-8031-39c79ca623c7") -> 019eb2b6-0f93-7b2a-8031-39c79ca623c7 | BK10: =IFERROR(__xludf.DUMMYFUNCTION("""COMPUTED_VALUE"""),46183.753900462965) -> 46183.754 | BL10: =IFERROR(__xludf.DUMMYFUNCTION("""COMPUTED_VALUE"""),"credit") -> credit | BM10: =IFERROR(__xludf.DUMMYFUNCTION("""COMPUTED_VALUE"""),703.22) -> 703.22 | BN10: =IFERROR(__xludf.DUMMYFUNCTION("""COMPUTED_VALUE"""),"lisa") -> lisa | BO10: =IFERROR(__xludf.DUMMYFUNCTION("""COMPUTED_VALUE"""),"b7a59586-5d10-4989-91c2-f2376c7a6ab2") -> b7a59586-5d10-4989-91c2-f2376c7a6ab2 | BP10: =IFERROR(__xludf.DUMMYFUNCTION("""COMPUTED_VALUE"""),"04016f15-a048-4e2f-ab88-ad6abdf6ed72") -> 04016f15-a048-4e2f-ab88-ad6abdf6ed72 | BQ10: =IFERROR(__xludf.DUMMYFUNCTION("""COMPUTED_VALUE"""),"04016f15-a048-4e2f-ab88-ad6abdf6ed72") -> 04016f15-a048-4e2f-ab88-ad6abdf6ed72 | BR10: =IFERROR(__xludf.DUMMYFUNCTION("""COMPUTED_VALUE"""),"FRESCO.21302.GFX.20-45732139") -> FRESCO.21302.GFX.20-45732139 | BS10: =IFERROR(__xludf.DUMMYFUNCTION("""COMPUTED_VALUE"""),703.22) -> 703.22 | BT10: =IFERROR(__xludf.DUMMYFUNCTION("""COMPUTED_VALUE"""),"payin") -> payin | BU10: =IFERROR(__xludf.DUMMYFUNCTION("""COMPUTED_VALUE"""),46182.584872685184) -> 46182.585
A11: 73df5aae-f42a-49a0-9d8f-616ca6dbebaa | B11: 019ecf73-786f-735a-8d04-a5ef897c515a | C11: 46189.335 | D11: debit | E11: 12001.69 | F11: cash_isa | G11: 9bc00e6b-ce5f-48c5-ae3a-1baabe00f337 | H11: 43fda8b1-46b9-42e8-ae27-47e24487252b | AD11: =IFERROR(__xludf.DUMMYFUNCTION("""COMPUTED_VALUE"""),"73df5aae-f42a-49a0-9d8f-616ca6dbebaa") -> 73df5aae-f42a-49a0-9d8f-616ca6dbebaa | AE11: =IFERROR(__xludf.DUMMYFUNCTION("""COMPUTED_VALUE"""),"019ed024-88f1-789c-a803-e90f28c9087e") -> 019ed024-88f1-789c-a803-e90f28c9087e | AF11: =IFERROR(__xludf.DUMMYFUNCTION("""COMPUTED_VALUE"""),46189.468935185185) -> 46189.469 | AG11: =IFERROR(__xludf.DUMMYFUNCTION("""COMPUTED_VALUE"""),"credit") -> credit | AH11: =IFERROR(__xludf.DUMMYFUNCTION("""COMPUTED_VALUE"""),250.0) -> 250 | AI11: =IFERROR(__xludf.DUMMYFUNCTION("""COMPUTED_VALUE"""),"cash_isa") -> cash_isa | AJ11: =IFERROR(__xludf.DUMMYFUNCTION("""COMPUTED_VALUE"""),"9bc00e6b-ce5f-48c5-ae3a-1baabe00f337") -> 9bc00e6b-ce5f-48c5-ae3a-1baabe00f337 | AK11: =IFERROR(__xludf.DUMMYFUNCTION("""COMPUTED_VALUE"""),"5a92f897-6035-4172-9831-90028a8a98c2") -> 5a92f897-6035-4172-9831-90028a8a98c2 | AL11: =IFERROR(__xludf.DUMMYFUNCTION("""COMPUTED_VALUE"""),"5a92f897-6035-4172-9831-90028a8a98c2") -> 5a92f897-6035-4172-9831-90028a8a98c2 | AM11: =IFERROR(__xludf.DUMMYFUNCTION("""COMPUTED_VALUE"""),"JC321715Da-518647334") -> JC321715Da-518647334 | AN11: =IFERROR(__xludf.DUMMYFUNCTION("""COMPUTED_VALUE"""),250.0) -> 250 | AO11: =IFERROR(__xludf.DUMMYFUNCTION("""COMPUTED_VALUE"""),"payin") -> payin | AP11: =IFERROR(__xludf.DUMMYFUNCTION("""COMPUTED_VALUE"""),46188.66883101852) -> 46188.669 | AR11: =ROUND(VALUE(AH11),2)&"_"&TRIM(LOWER(AG11)) -> 250_credit | AS11: =IF(AH11="", "", LET(current_amt, ROUND(VALUE(AH11), 2), current_dir, TRIM(LOWER(AG11)), opposite_dir, IF(current_dir="credit", "debit", "credit"), occ, COUNTIFS($AH$3:AH11, AH11, $AG$3:AG11, AG11), opp_total, COUNTIFS($AH$3:$AH$1000, AH11, $AG$3:$AG$1000, opposite_dir), IF(opp_total >= occ, "DROP", "KEEP"))) -> KEEP | AU11: =IFERROR(__xludf.DUMMYFUNCTION("""COMPUTED_VALUE"""),"73df5aae-f42a-49a0-9d8f-616ca6dbebaa") -> 73df5aae-f42a-49a0-9d8f-616ca6dbebaa | AV11: =IFERROR(__xludf.DUMMYFUNCTION("""COMPUTED_VALUE"""),"019ed024-854b-7377-878e-9bd25cd97072") -> 019ed024-854b-7377-878e-9bd25cd97072 | AW11: =IFERROR(__xludf.DUMMYFUNCTION("""COMPUTED_VALUE"""),46189.468923611115) -> 46189.469 | AX11: =IFERROR(__xludf.DUMMYFUNCTION("""COMPUTED_VALUE"""),"credit") -> credit | AY11: =IFERROR(__xludf.DUMMYFUNCTION("""COMPUTED_VALUE"""),21471.6) -> 21471.6 | AZ11: =IFERROR(__xludf.DUMMYFUNCTION("""COMPUTED_VALUE"""),"cash_isa") -> cash_isa | BA11: =IFERROR(__xludf.DUMMYFUNCTION("""COMPUTED_VALUE"""),"9bc00e6b-ce5f-48c5-ae3a-1baabe00f337") -> 9bc00e6b-ce5f-48c5-ae3a-1baabe00f337 | BB11: =IFERROR(__xludf.DUMMYFUNCTION("""COMPUTED_VALUE"""),"228cd2f5-1ee0-4962-a649-82c9f17961ae") -> 228cd2f5-1ee0-4962-a649-82c9f17961ae | BC11: =IFERROR(__xludf.DUMMYFUNCTION("""COMPUTED_VALUE"""),"228cd2f5-1ee0-4962-a649-82c9f17961ae") -> 228cd2f5-1ee0-4962-a649-82c9f17961ae | BD11: =IFERROR(__xludf.DUMMYFUNCTION("""COMPUTED_VALUE"""),"WK648730Ba-580073357") -> WK648730Ba-580073357 | BE11: =IFERROR(__xludf.DUMMYFUNCTION("""COMPUTED_VALUE"""),21471.6) -> 21471.6 | BF11: =IFERROR(__xludf.DUMMYFUNCTION("""COMPUTED_VALUE"""),"payin") -> payin | BG11: =IFERROR(__xludf.DUMMYFUNCTION("""COMPUTED_VALUE"""),46188.66883101852) -> 46188.669 | BI11: =IFERROR(__xludf.DUMMYFUNCTION("""COMPUTED_VALUE"""),"73df5aae-f42a-49a0-9d8f-616ca6dbebaa") -> 73df5aae-f42a-49a0-9d8f-616ca6dbebaa | BJ11: =IFERROR(__xludf.DUMMYFUNCTION("""COMPUTED_VALUE"""),"019eb6b9-6a8d-73ef-87dc-cb539797754d") -> 019eb6b9-6a8d-73ef-87dc-cb539797754d | BK11: =IFERROR(__xludf.DUMMYFUNCTION("""COMPUTED_VALUE"""),46184.533159722225) -> 46184.533 | BL11: =IFERROR(__xludf.DUMMYFUNCTION("""COMPUTED_VALUE"""),"credit") -> credit | BM11: =IFERROR(__xludf.DUMMYFUNCTION("""COMPUTED_VALUE"""),108.26) -> 108.26 | BN11: =IFERROR(__xludf.DUMMYFUNCTION("""COMPUTED_VALUE"""),"lisa") -> lisa | BO11: =IFERROR(__xludf.DUMMYFUNCTION("""COMPUTED_VALUE"""),"b7a59586-5d10-4989-91c2-f2376c7a6ab2") -> b7a59586-5d10-4989-91c2-f2376c7a6ab2 | BP11: =IFERROR(__xludf.DUMMYFUNCTION("""COMPUTED_VALUE"""),"11ab5e3b-6091-443a-9edf-dd35b41adeb6") -> 11ab5e3b-6091-443a-9edf-dd35b41adeb6 | BQ11: =IFERROR(__xludf.DUMMYFUNCTION("""COMPUTED_VALUE"""),"11ab5e3b-6091-443a-9edf-dd35b41adeb6") -> 11ab5e3b-6091-443a-9edf-dd35b41adeb6 | BR11: =IFERROR(__xludf.DUMMYFUNCTION("""COMPUTED_VALUE"""),"72FEE306a-571949853") -> 72FEE306a-571949853 | BS11: =IFERROR(__xludf.DUMMYFUNCTION("""COMPUTED_VALUE"""),108.26) -> 108.26 | BT11: =IFERROR(__xludf.DUMMYFUNCTION("""COMPUTED_VALUE"""),"payin") -> payin | BU11: =IFERROR(__xludf.DUMMYFUNCTION("""COMPUTED_VALUE"""),46183.39266203703) -> 46183.393
A12: 73df5aae-f42a-49a0-9d8f-616ca6dbebaa | B12: 019ecf74-d8d6-7b98-aed4-3cd32fccee78 | C12: 46189.336 | D12: credit | E12: 21791.12 | F12: cash_isa | G12: 9bc00e6b-ce5f-48c5-ae3a-1baabe00f337 | H12: 68bf96ba-6b4e-4626-989e-f5394ed71986 | AD12: =IFERROR(__xludf.DUMMYFUNCTION("""COMPUTED_VALUE"""),"73df5aae-f42a-49a0-9d8f-616ca6dbebaa") -> 73df5aae-f42a-49a0-9d8f-616ca6dbebaa | AE12: =IFERROR(__xludf.DUMMYFUNCTION("""COMPUTED_VALUE"""),"019ed024-8817-7d80-9685-39944e000a98") -> 019ed024-8817-7d80-9685-39944e000a98 | AF12: =IFERROR(__xludf.DUMMYFUNCTION("""COMPUTED_VALUE"""),46189.468935185185) -> 46189.469 | AG12: =IFERROR(__xludf.DUMMYFUNCTION("""COMPUTED_VALUE"""),"credit") -> credit | AH12: =IFERROR(__xludf.DUMMYFUNCTION("""COMPUTED_VALUE"""),42534.92) -> 42534.92 | AI12: =IFERROR(__xludf.DUMMYFUNCTION("""COMPUTED_VALUE"""),"cash_isa") -> cash_isa | AJ12: =IFERROR(__xludf.DUMMYFUNCTION("""COMPUTED_VALUE"""),"9bc00e6b-ce5f-48c5-ae3a-1baabe00f337") -> 9bc00e6b-ce5f-48c5-ae3a-1baabe00f337 | AK12: =IFERROR(__xludf.DUMMYFUNCTION("""COMPUTED_VALUE"""),"a50f2b4e-4ed2-48c6-ae8b-f3052f76d926") -> a50f2b4e-4ed2-48c6-ae8b-f3052f76d926 | AL12: =IFERROR(__xludf.DUMMYFUNCTION("""COMPUTED_VALUE"""),"a50f2b4e-4ed2-48c6-ae8b-f3052f76d926") -> a50f2b4e-4ed2-48c6-ae8b-f3052f76d926 | AM12: =IFERROR(__xludf.DUMMYFUNCTION("""COMPUTED_VALUE"""),"YM189882D-95846103") -> YM189882D-95846103 | AN12: =IFERROR(__xludf.DUMMYFUNCTION("""COMPUTED_VALUE"""),42534.92) -> 42534.92 | AO12: =IFERROR(__xludf.DUMMYFUNCTION("""COMPUTED_VALUE"""),"payin") -> payin | AP12: =IFERROR(__xludf.DUMMYFUNCTION("""COMPUTED_VALUE"""),46188.6688425926) -> 46188.669 | AR12: =ROUND(VALUE(AH12),2)&"_"&TRIM(LOWER(AG12)) -> 42534.92_credit | AS12: =IF(AH12="", "", LET(current_amt, ROUND(VALUE(AH12), 2), current_dir, TRIM(LOWER(AG12)), opposite_dir, IF(current_dir="credit", "debit", "credit"), occ, COUNTIFS($AH$3:AH12, AH12, $AG$3:AG12, AG12), opp_total, COUNTIFS($AH$3:$AH$1000, AH12, $AG$3:$AG$1000, opposite_dir), IF(opp_total >= occ, "DROP", "KEEP"))) -> KEEP | AU12: =IFERROR(__xludf.DUMMYFUNCTION("""COMPUTED_VALUE"""),"73df5aae-f42a-49a0-9d8f-616ca6dbebaa") -> 73df5aae-f42a-49a0-9d8f-616ca6dbebaa | AV12: =IFERROR(__xludf.DUMMYFUNCTION("""COMPUTED_VALUE"""),"019ed024-864c-78df-b53a-e34f6f766c49") -> 019ed024-864c-78df-b53a-e34f6f766c49 | AW12: =IFERROR(__xludf.DUMMYFUNCTION("""COMPUTED_VALUE"""),46189.468923611115) -> 46189.469 | AX12: =IFERROR(__xludf.DUMMYFUNCTION("""COMPUTED_VALUE"""),"credit") -> credit | AY12: =IFERROR(__xludf.DUMMYFUNCTION("""COMPUTED_VALUE"""),20974.52) -> 20974.52 | AZ12: =IFERROR(__xludf.DUMMYFUNCTION("""COMPUTED_VALUE"""),"cash_isa") -> cash_isa | BA12: =IFERROR(__xludf.DUMMYFUNCTION("""COMPUTED_VALUE"""),"9bc00e6b-ce5f-48c5-ae3a-1baabe00f337") -> 9bc00e6b-ce5f-48c5-ae3a-1baabe00f337 | BB12: =IFERROR(__xludf.DUMMYFUNCTION("""COMPUTED_VALUE"""),"084ad475-9333-4dbe-8fb5-7d7b8ad84064") -> 084ad475-9333-4dbe-8fb5-7d7b8ad84064 | BC12: =IFERROR(__xludf.DUMMYFUNCTION("""COMPUTED_VALUE"""),"084ad475-9333-4dbe-8fb5-7d7b8ad84064") -> 084ad475-9333-4dbe-8fb5-7d7b8ad84064 | BD12: =IFERROR(__xludf.DUMMYFUNCTION("""COMPUTED_VALUE"""),"NZ656284A-1098901635") -> NZ656284A-1098901635 | BE12: =IFERROR(__xludf.DUMMYFUNCTION("""COMPUTED_VALUE"""),20974.52) -> 20974.52 | BF12: =IFERROR(__xludf.DUMMYFUNCTION("""COMPUTED_VALUE"""),"payin") -> payin | BG12: =IFERROR(__xludf.DUMMYFUNCTION("""COMPUTED_VALUE"""),46188.66883101852) -> 46188.669 | BI12: =IFERROR(__xludf.DUMMYFUNCTION("""COMPUTED_VALUE"""),"73df5aae-f42a-49a0-9d8f-616ca6dbebaa") -> 73df5aae-f42a-49a0-9d8f-616ca6dbebaa | BJ12: =IFERROR(__xludf.DUMMYFUNCTION("""COMPUTED_VALUE"""),"019ebcb7-d5e1-7bf7-b141-b8a6e63065d4") -> 019ebcb7-d5e1-7bf7-b141-b8a6e63065d4 | BK12: =IFERROR(__xludf.DUMMYFUNCTION("""COMPUTED_VALUE"""),46185.69704861111) -> 46185.697 | BL12: =IFERROR(__xludf.DUMMYFUNCTION("""COMPUTED_VALUE"""),"credit") -> credit | BM12: =IFERROR(__xludf.DUMMYFUNCTION("""COMPUTED_VALUE"""),12949.42) -> 12949.42 | BN12: =IFERROR(__xludf.DUMMYFUNCTION("""COMPUTED_VALUE"""),"lisa") -> lisa | BO12: =IFERROR(__xludf.DUMMYFUNCTION("""COMPUTED_VALUE"""),"b7a59586-5d10-4989-91c2-f2376c7a6ab2") -> b7a59586-5d10-4989-91c2-f2376c7a6ab2 | BP12: =IFERROR(__xludf.DUMMYFUNCTION("""COMPUTED_VALUE"""),"70f1e299-11ac-4280-a6e2-1dc1137e001b") -> 70f1e299-11ac-4280-a6e2-1dc1137e001b | BQ12: =IFERROR(__xludf.DUMMYFUNCTION("""COMPUTED_VALUE"""),"70f1e299-11ac-4280-a6e2-1dc1137e001b") -> 70f1e299-11ac-4280-a6e2-1dc1137e001b | BR12: =IFERROR(__xludf.DUMMYFUNCTION("""COMPUTED_VALUE"""),"NOREF-838618946") -> NOREF-838618946 | BS12: =IFERROR(__xludf.DUMMYFUNCTION("""COMPUTED_VALUE"""),12949.42) -> 12949.42 | BT12: =IFERROR(__xludf.DUMMYFUNCTION("""COMPUTED_VALUE"""),"payin") -> payin | BU12: =IFERROR(__xludf.DUMMYFUNCTION("""COMPUTED_VALUE"""),46184.635046296295) -> 46184.635
A13: 73df5aae-f42a-49a0-9d8f-616ca6dbebaa | B13: 019ecf76-bf63-76d6-aa04-0abf78a5d505 | C13: 46189.337 | D13: debit | E13: 21791.12 | F13: cash_isa | G13: 9bc00e6b-ce5f-48c5-ae3a-1baabe00f337 | H13: 68bf96ba-6b4e-4626-989e-f5394ed71986 | AD13: =IFERROR(__xludf.DUMMYFUNCTION("""COMPUTED_VALUE"""),"73df5aae-f42a-49a0-9d8f-616ca6dbebaa") -> 73df5aae-f42a-49a0-9d8f-616ca6dbebaa | AE13: =IFERROR(__xludf.DUMMYFUNCTION("""COMPUTED_VALUE"""),"019ed0b1-3052-7f73-9d08-db917a292c59") -> 019ed0b1-3052-7f73-9d08-db917a292c59 | AF13: =IFERROR(__xludf.DUMMYFUNCTION("""COMPUTED_VALUE"""),46189.575625) -> 46189.576 | AG13: =IFERROR(__xludf.DUMMYFUNCTION("""COMPUTED_VALUE"""),"credit") -> credit | AH13: =IFERROR(__xludf.DUMMYFUNCTION("""COMPUTED_VALUE"""),14930.71) -> 14930.71 | AI13: =IFERROR(__xludf.DUMMYFUNCTION("""COMPUTED_VALUE"""),"cash_isa") -> cash_isa | AJ13: =IFERROR(__xludf.DUMMYFUNCTION("""COMPUTED_VALUE"""),"9bc00e6b-ce5f-48c5-ae3a-1baabe00f337") -> 9bc00e6b-ce5f-48c5-ae3a-1baabe00f337 | AK13: =IFERROR(__xludf.DUMMYFUNCTION("""COMPUTED_VALUE"""),"37db9098-7f00-401d-be6f-68777404753c") -> 37db9098-7f00-401d-be6f-68777404753c | AN13: =IFERROR(__xludf.DUMMYFUNCTION("""COMPUTED_VALUE"""),14930.71) -> 14930.71 | AR13: =ROUND(VALUE(AH13),2)&"_"&TRIM(LOWER(AG13)) -> 14930.71_credit | AS13: =IF(AH13="", "", LET(current_amt, ROUND(VALUE(AH13), 2), current_dir, TRIM(LOWER(AG13)), opposite_dir, IF(current_dir="credit", "debit", "credit"), occ, COUNTIFS($AH$3:AH13, AH13, $AG$3:AG13, AG13), opp_total, COUNTIFS($AH$3:$AH$1000, AH13, $AG$3:$AG$1000, opposite_dir), IF(opp_total >= occ, "DROP", "KEEP"))) -> KEEP | AU13: =IFERROR(__xludf.DUMMYFUNCTION("""COMPUTED_VALUE"""),"73df5aae-f42a-49a0-9d8f-616ca6dbebaa") -> 73df5aae-f42a-49a0-9d8f-616ca6dbebaa | AV13: =IFERROR(__xludf.DUMMYFUNCTION("""COMPUTED_VALUE"""),"019ed024-873d-7252-be6e-6e408eb5a4cb") -> 019ed024-873d-7252-be6e-6e408eb5a4cb | AW13: =IFERROR(__xludf.DUMMYFUNCTION("""COMPUTED_VALUE"""),46189.468923611115) -> 46189.469 | AX13: =IFERROR(__xludf.DUMMYFUNCTION("""COMPUTED_VALUE"""),"credit") -> credit | AY13: =IFERROR(__xludf.DUMMYFUNCTION("""COMPUTED_VALUE"""),20918.18) -> 20918.18 | AZ13: =IFERROR(__xludf.DUMMYFUNCTION("""COMPUTED_VALUE"""),"cash_isa") -> cash_isa | BA13: =IFERROR(__xludf.DUMMYFUNCTION("""COMPUTED_VALUE"""),"9bc00e6b-ce5f-48c5-ae3a-1baabe00f337") -> 9bc00e6b-ce5f-48c5-ae3a-1baabe00f337 | BB13: =IFERROR(__xludf.DUMMYFUNCTION("""COMPUTED_VALUE"""),"a7a2dae7-bd10-44fc-9b1b-25271dcf0442") -> a7a2dae7-bd10-44fc-9b1b-25271dcf0442 | BC13: =IFERROR(__xludf.DUMMYFUNCTION("""COMPUTED_VALUE"""),"a7a2dae7-bd10-44fc-9b1b-25271dcf0442") -> a7a2dae7-bd10-44fc-9b1b-25271dcf0442 | BD13: =IFERROR(__xludf.DUMMYFUNCTION("""COMPUTED_VALUE"""),"JX825895D-940686763") -> JX825895D-940686763 | BE13: =IFERROR(__xludf.DUMMYFUNCTION("""COMPUTED_VALUE"""),20918.18) -> 20918.18 | BF13: =IFERROR(__xludf.DUMMYFUNCTION("""COMPUTED_VALUE"""),"payin") -> payin | BG13: =IFERROR(__xludf.DUMMYFUNCTION("""COMPUTED_VALUE"""),46188.6688425926) -> 46188.669 | BI13: =IFERROR(__xludf.DUMMYFUNCTION("""COMPUTED_VALUE"""),"73df5aae-f42a-49a0-9d8f-616ca6dbebaa") -> 73df5aae-f42a-49a0-9d8f-616ca6dbebaa | BJ13: =IFERROR(__xludf.DUMMYFUNCTION("""COMPUTED_VALUE"""),"019ecc1e-fb7b-7adf-a1b5-209ce9f1e444") -> 019ecc1e-fb7b-7adf-a1b5-209ce9f1e444 | BK13: =IFERROR(__xludf.DUMMYFUNCTION("""COMPUTED_VALUE"""),46188.687997685185) -> 46188.688 | BL13: =IFERROR(__xludf.DUMMYFUNCTION("""COMPUTED_VALUE"""),"credit") -> credit | BM13: =IFERROR(__xludf.DUMMYFUNCTION("""COMPUTED_VALUE"""),56199.56) -> 56199.56 | BN13: =IFERROR(__xludf.DUMMYFUNCTION("""COMPUTED_VALUE"""),"lisa") -> lisa | BO13: =IFERROR(__xludf.DUMMYFUNCTION("""COMPUTED_VALUE"""),"b7a59586-5d10-4989-91c2-f2376c7a6ab2") -> b7a59586-5d10-4989-91c2-f2376c7a6ab2 | BP13: =IFERROR(__xludf.DUMMYFUNCTION("""COMPUTED_VALUE"""),"cc9da595-2186-4ffd-b8d8-6ec93cfb525a") -> cc9da595-2186-4ffd-b8d8-6ec93cfb525a | BQ13: =IFERROR(__xludf.DUMMYFUNCTION("""COMPUTED_VALUE"""),"cc9da595-2186-4ffd-b8d8-6ec93cfb525a") -> cc9da595-2186-4ffd-b8d8-6ec93cfb525a | BR13: =IFERROR(__xludf.DUMMYFUNCTION("""COMPUTED_VALUE"""),"b413ebba-1125098511") -> b413ebba-1125098511 | BS13: =IFERROR(__xludf.DUMMYFUNCTION("""COMPUTED_VALUE"""),56199.56) -> 56199.56 | BT13: =IFERROR(__xludf.DUMMYFUNCTION("""COMPUTED_VALUE"""),"payin") -> payin | BU13: =IFERROR(__xludf.DUMMYFUNCTION("""COMPUTED_VALUE"""),46185.09993055556) -> 46185.1
A14: 73df5aae-f42a-49a0-9d8f-616ca6dbebaa | B14: 019ecf7a-e489-72cd-9b73-1bd7516d5e2f | C14: 46189.34 | D14: credit | E14: 51998.41 | F14: cash_isa | G14: 9bc00e6b-ce5f-48c5-ae3a-1baabe00f337 | H14: 205cdd7c-d2ed-4603-9ba0-b085b08ee3ed | AD14: =IFERROR(__xludf.DUMMYFUNCTION("""COMPUTED_VALUE"""),"73df5aae-f42a-49a0-9d8f-616ca6dbebaa") -> 73df5aae-f42a-49a0-9d8f-616ca6dbebaa | AE14: =IFERROR(__xludf.DUMMYFUNCTION("""COMPUTED_VALUE"""),"019ed0fa-b1c2-7819-857e-40a98c4e3541") -> 019ed0fa-b1c2-7819-857e-40a98c4e3541 | AF14: =IFERROR(__xludf.DUMMYFUNCTION("""COMPUTED_VALUE"""),46189.631377314814) -> 46189.631 | AG14: =IFERROR(__xludf.DUMMYFUNCTION("""COMPUTED_VALUE"""),"credit") -> credit | AH14: =IFERROR(__xludf.DUMMYFUNCTION("""COMPUTED_VALUE"""),20000.0) -> 20000 | AI14: =IFERROR(__xludf.DUMMYFUNCTION("""COMPUTED_VALUE"""),"cash_isa") -> cash_isa | AJ14: =IFERROR(__xludf.DUMMYFUNCTION("""COMPUTED_VALUE"""),"9bc00e6b-ce5f-48c5-ae3a-1baabe00f337") -> 9bc00e6b-ce5f-48c5-ae3a-1baabe00f337 | AK14: =IFERROR(__xludf.DUMMYFUNCTION("""COMPUTED_VALUE"""),"fc861623-56a0-47e2-bd62-7aa9db1633a8") -> fc861623-56a0-47e2-bd62-7aa9db1633a8 | AN14: =IFERROR(__xludf.DUMMYFUNCTION("""COMPUTED_VALUE"""),20000.0) -> 20000 | AR14: =ROUND(VALUE(AH14),2)&"_"&TRIM(LOWER(AG14)) -> 20000_credit | AS14: =IF(AH14="", "", LET(current_amt, ROUND(VALUE(AH14), 2), current_dir, TRIM(LOWER(AG14)), opposite_dir, IF(current_dir="credit", "debit", "credit"), occ, COUNTIFS($AH$3:AH14, AH14, $AG$3:AG14, AG14), opp_total, COUNTIFS($AH$3:$AH$1000, AH14, $AG$3:$AG$1000, opposite_dir), IF(opp_total >= occ, "DROP", "KEEP"))) -> DROP | AU14: =IFERROR(__xludf.DUMMYFUNCTION("""COMPUTED_VALUE"""),"73df5aae-f42a-49a0-9d8f-616ca6dbebaa") -> 73df5aae-f42a-49a0-9d8f-616ca6dbebaa | AV14: =IFERROR(__xludf.DUMMYFUNCTION("""COMPUTED_VALUE"""),"019ed024-854b-7377-878e-9bd25cd97072") -> 019ed024-854b-7377-878e-9bd25cd97072 | AW14: =IFERROR(__xludf.DUMMYFUNCTION("""COMPUTED_VALUE"""),46189.468923611115) -> 46189.469 | AX14: =IFERROR(__xludf.DUMMYFUNCTION("""COMPUTED_VALUE"""),"credit") -> credit | AY14: =IFERROR(__xludf.DUMMYFUNCTION("""COMPUTED_VALUE"""),21471.6) -> 21471.6 | AZ14: =IFERROR(__xludf.DUMMYFUNCTION("""COMPUTED_VALUE"""),"cash_isa") -> cash_isa | BA14: =IFERROR(__xludf.DUMMYFUNCTION("""COMPUTED_VALUE"""),"9bc00e6b-ce5f-48c5-ae3a-1baabe00f337") -> 9bc00e6b-ce5f-48c5-ae3a-1baabe00f337 | BB14: =IFERROR(__xludf.DUMMYFUNCTION("""COMPUTED_VALUE"""),"228cd2f5-1ee0-4962-a649-82c9f17961ae") -> 228cd2f5-1ee0-4962-a649-82c9f17961ae | BC14: =IFERROR(__xludf.DUMMYFUNCTION("""COMPUTED_VALUE"""),"228cd2f5-1ee0-4962-a649-82c9f17961ae") -> 228cd2f5-1ee0-4962-a649-82c9f17961ae | BD14: =IFERROR(__xludf.DUMMYFUNCTION("""COMPUTED_VALUE"""),"WK648730Ba-580073357") -> WK648730Ba-580073357 | BE14: =IFERROR(__xludf.DUMMYFUNCTION("""COMPUTED_VALUE"""),21471.6) -> 21471.6 | BF14: =IFERROR(__xludf.DUMMYFUNCTION("""COMPUTED_VALUE"""),"payin") -> payin | BG14: =IFERROR(__xludf.DUMMYFUNCTION("""COMPUTED_VALUE"""),46188.66883101852) -> 46188.669 | BI14: =IFERROR(__xludf.DUMMYFUNCTION("""COMPUTED_VALUE"""),"73df5aae-f42a-49a0-9d8f-616ca6dbebaa") -> 73df5aae-f42a-49a0-9d8f-616ca6dbebaa | BJ14: =IFERROR(__xludf.DUMMYFUNCTION("""COMPUTED_VALUE"""),"019ecc1e-f9c0-7af4-98a2-f8ee6e2cc3bc") -> 019ecc1e-f9c0-7af4-98a2-f8ee6e2cc3bc | BK14: =IFERROR(__xludf.DUMMYFUNCTION("""COMPUTED_VALUE"""),46188.687997685185) -> 46188.688 | BL14: =IFERROR(__xludf.DUMMYFUNCTION("""COMPUTED_VALUE"""),"credit") -> credit | BM14: =IFERROR(__xludf.DUMMYFUNCTION("""COMPUTED_VALUE"""),26992.22) -> 26992.22 | BN14: =IFERROR(__xludf.DUMMYFUNCTION("""COMPUTED_VALUE"""),"lisa") -> lisa | BO14: =IFERROR(__xludf.DUMMYFUNCTION("""COMPUTED_VALUE"""),"b7a59586-5d10-4989-91c2-f2376c7a6ab2") -> b7a59586-5d10-4989-91c2-f2376c7a6ab2 | BP14: =IFERROR(__xludf.DUMMYFUNCTION("""COMPUTED_VALUE"""),"ac9ac199-2324-4ca2-a5db-61b4463bb5e1") -> ac9ac199-2324-4ca2-a5db-61b4463bb5e1 | BQ14: =IFERROR(__xludf.DUMMYFUNCTION("""COMPUTED_VALUE"""),"ac9ac199-2324-4ca2-a5db-61b4463bb5e1") -> ac9ac199-2324-4ca2-a5db-61b4463bb5e1 | BR14: =IFERROR(__xludf.DUMMYFUNCTION("""COMPUTED_VALUE"""),"5520f7fd-1754025676") -> 5520f7fd-1754025676 | BS14: =IFERROR(__xludf.DUMMYFUNCTION("""COMPUTED_VALUE"""),26992.22) -> 26992.22 | BT14: =IFERROR(__xludf.DUMMYFUNCTION("""COMPUTED_VALUE"""),"payin") -> payin | BU14: =IFERROR(__xludf.DUMMYFUNCTION("""COMPUTED_VALUE"""),46185.104837962965) -> 46185.105
A15: 73df5aae-f42a-49a0-9d8f-616ca6dbebaa | B15: 019ecf7c-55ad-7427-9bb9-58b36cfaddae | C15: 46189.341 | D15: debit | E15: 51998.41 | F15: cash_isa | G15: 9bc00e6b-ce5f-48c5-ae3a-1baabe00f337 | H15: 205cdd7c-d2ed-4603-9ba0-b085b08ee3ed | AD15: =IFERROR(__xludf.DUMMYFUNCTION("""COMPUTED_VALUE"""),"73df5aae-f42a-49a0-9d8f-616ca6dbebaa") -> 73df5aae-f42a-49a0-9d8f-616ca6dbebaa | AE15: =IFERROR(__xludf.DUMMYFUNCTION("""COMPUTED_VALUE"""),"019ecf66-4e5f-7d1d-ab8b-3f663490584d") -> 019ecf66-4e5f-7d1d-ab8b-3f663490584d | AF15: =IFERROR(__xludf.DUMMYFUNCTION("""COMPUTED_VALUE"""),46189.324641203704) -> 46189.325 | AG15: =IFERROR(__xludf.DUMMYFUNCTION("""COMPUTED_VALUE"""),"credit") -> credit | AH15: =IFERROR(__xludf.DUMMYFUNCTION("""COMPUTED_VALUE"""),6879.1) -> 6879.1 | AI15: =IFERROR(__xludf.DUMMYFUNCTION("""COMPUTED_VALUE"""),"cash_isa") -> cash_isa | AJ15: =IFERROR(__xludf.DUMMYFUNCTION("""COMPUTED_VALUE"""),"9bc00e6b-ce5f-48c5-ae3a-1baabe00f337") -> 9bc00e6b-ce5f-48c5-ae3a-1baabe00f337 | AK15: =IFERROR(__xludf.DUMMYFUNCTION("""COMPUTED_VALUE"""),"91d3f2bc-40eb-40b5-abfd-b8c37565b61e") -> 91d3f2bc-40eb-40b5-abfd-b8c37565b61e | AR15: =ROUND(VALUE(AH15),2)&"_"&TRIM(LOWER(AG15)) -> 6879.1_credit | AS15: =IF(AH15="", "", LET(current_amt, ROUND(VALUE(AH15), 2), current_dir, TRIM(LOWER(AG15)), opposite_dir, IF(current_dir="credit", "debit", "credit"), occ, COUNTIFS($AH$3:AH15, AH15, $AG$3:AG15, AG15), opp_total, COUNTIFS($AH$3:$AH$1000, AH15, $AG$3:$AG$1000, opposite_dir), IF(opp_total >= occ, "DROP", "KEEP"))) -> DROP | AU15: =IFERROR(__xludf.DUMMYFUNCTION("""COMPUTED_VALUE"""),"73df5aae-f42a-49a0-9d8f-616ca6dbebaa") -> 73df5aae-f42a-49a0-9d8f-616ca6dbebaa | AV15: =IFERROR(__xludf.DUMMYFUNCTION("""COMPUTED_VALUE"""),"019ed024-864c-78df-b53a-e34f6f766c49") -> 019ed024-864c-78df-b53a-e34f6f766c49 | AW15: =IFERROR(__xludf.DUMMYFUNCTION("""COMPUTED_VALUE"""),46189.468923611115) -> 46189.469 | AX15: =IFERROR(__xludf.DUMMYFUNCTION("""COMPUTED_VALUE"""),"credit") -> credit | AY15: =IFERROR(__xludf.DUMMYFUNCTION("""COMPUTED_VALUE"""),20974.52) -> 20974.52 | AZ15: =IFERROR(__xludf.DUMMYFUNCTION("""COMPUTED_VALUE"""),"cash_isa") -> cash_isa | BA15: =IFERROR(__xludf.DUMMYFUNCTION("""COMPUTED_VALUE"""),"9bc00e6b-ce5f-48c5-ae3a-1baabe00f337") -> 9bc00e6b-ce5f-48c5-ae3a-1baabe00f337 | BB15: =IFERROR(__xludf.DUMMYFUNCTION("""COMPUTED_VALUE"""),"084ad475-9333-4dbe-8fb5-7d7b8ad84064") -> 084ad475-9333-4dbe-8fb5-7d7b8ad84064 | BC15: =IFERROR(__xludf.DUMMYFUNCTION("""COMPUTED_VALUE"""),"084ad475-9333-4dbe-8fb5-7d7b8ad84064") -> 084ad475-9333-4dbe-8fb5-7d7b8ad84064 | BD15: =IFERROR(__xludf.DUMMYFUNCTION("""COMPUTED_VALUE"""),"NZ656284A-1098901635") -> NZ656284A-1098901635 | BE15: =IFERROR(__xludf.DUMMYFUNCTION("""COMPUTED_VALUE"""),20974.52) -> 20974.52 | BF15: =IFERROR(__xludf.DUMMYFUNCTION("""COMPUTED_VALUE"""),"payin") -> payin | BG15: =IFERROR(__xludf.DUMMYFUNCTION("""COMPUTED_VALUE"""),46188.66883101852) -> 46188.669 | BI15: =IFERROR(__xludf.DUMMYFUNCTION("""COMPUTED_VALUE"""),"73df5aae-f42a-49a0-9d8f-616ca6dbebaa") -> 73df5aae-f42a-49a0-9d8f-616ca6dbebaa | BJ15: =IFERROR(__xludf.DUMMYFUNCTION("""COMPUTED_VALUE"""),"019ecc1e-fc07-76a6-ae0d-2b27455a3529") -> 019ecc1e-fc07-76a6-ae0d-2b27455a3529 | BK15: =IFERROR(__xludf.DUMMYFUNCTION("""COMPUTED_VALUE"""),46188.687997685185) -> 46188.688 | BL15: =IFERROR(__xludf.DUMMYFUNCTION("""COMPUTED_VALUE"""),"credit") -> credit | BM15: =IFERROR(__xludf.DUMMYFUNCTION("""COMPUTED_VALUE"""),5412.33) -> 5412.33 | BN15: =IFERROR(__xludf.DUMMYFUNCTION("""COMPUTED_VALUE"""),"lisa") -> lisa | BO15: =IFERROR(__xludf.DUMMYFUNCTION("""COMPUTED_VALUE"""),"b7a59586-5d10-4989-91c2-f2376c7a6ab2") -> b7a59586-5d10-4989-91c2-f2376c7a6ab2 | BP15: =IFERROR(__xludf.DUMMYFUNCTION("""COMPUTED_VALUE"""),"e3ede257-3bac-4de0-b9e1-bdf3a2e4663b") -> e3ede257-3bac-4de0-b9e1-bdf3a2e4663b | BQ15: =IFERROR(__xludf.DUMMYFUNCTION("""COMPUTED_VALUE"""),"e3ede257-3bac-4de0-b9e1-bdf3a2e4663b") -> e3ede257-3bac-4de0-b9e1-bdf3a2e4663b | BR15: =IFERROR(__xludf.DUMMYFUNCTION("""COMPUTED_VALUE"""),"65FA81EB-1878983804") -> 65FA81EB-1878983804 | BS15: =IFERROR(__xludf.DUMMYFUNCTION("""COMPUTED_VALUE"""),5412.33) -> 5412.33 | BT15: =IFERROR(__xludf.DUMMYFUNCTION("""COMPUTED_VALUE"""),"payin") -> payin | BU15: =IFERROR(__xludf.DUMMYFUNCTION("""COMPUTED_VALUE"""),46185.54) -> 46185.54
A16: 73df5aae-f42a-49a0-9d8f-616ca6dbebaa | B16: 019ecf7e-7e01-76e2-ad1b-8a434ab054a0 | C16: 46189.343 | D16: credit | E16: 41.57 | F16: cash_isa | G16: 9bc00e6b-ce5f-48c5-ae3a-1baabe00f337 | H16: 5d9ab65f-d47d-440b-86fc-aada0df5983e | AD16: =IFERROR(__xludf.DUMMYFUNCTION("""COMPUTED_VALUE"""),"73df5aae-f42a-49a0-9d8f-616ca6dbebaa") -> 73df5aae-f42a-49a0-9d8f-616ca6dbebaa | AE16: =IFERROR(__xludf.DUMMYFUNCTION("""COMPUTED_VALUE"""),"019ecf67-f3f8-7864-b2db-1d9be3c1983e") -> 019ecf67-f3f8-7864-b2db-1d9be3c1983e | AF16: =IFERROR(__xludf.DUMMYFUNCTION("""COMPUTED_VALUE"""),46189.325891203705) -> 46189.326 | AG16: =IFERROR(__xludf.DUMMYFUNCTION("""COMPUTED_VALUE"""),"debit") -> debit | AH16: =IFERROR(__xludf.DUMMYFUNCTION("""COMPUTED_VALUE"""),6879.1) -> 6879.1 | AI16: =IFERROR(__xludf.DUMMYFUNCTION("""COMPUTED_VALUE"""),"cash_isa") -> cash_isa | AJ16: =IFERROR(__xludf.DUMMYFUNCTION("""COMPUTED_VALUE"""),"9bc00e6b-ce5f-48c5-ae3a-1baabe00f337") -> 9bc00e6b-ce5f-48c5-ae3a-1baabe00f337 | AK16: =IFERROR(__xludf.DUMMYFUNCTION("""COMPUTED_VALUE"""),"91d3f2bc-40eb-40b5-abfd-b8c37565b61e") -> 91d3f2bc-40eb-40b5-abfd-b8c37565b61e | AR16: =ROUND(VALUE(AH16),2)&"_"&TRIM(LOWER(AG16)) -> 6879.1_debit | AS16: =IF(AH16="", "", LET(current_amt, ROUND(VALUE(AH16), 2), current_dir, TRIM(LOWER(AG16)), opposite_dir, IF(current_dir="credit", "debit", "credit"), occ, COUNTIFS($AH$3:AH16, AH16, $AG$3:AG16, AG16), opp_total, COUNTIFS($AH$3:$AH$1000, AH16, $AG$3:$AG$1000, opposite_dir), IF(opp_total >= occ, "DROP", "KEEP"))) -> DROP | AU16: =IFERROR(__xludf.DUMMYFUNCTION("""COMPUTED_VALUE"""),"73df5aae-f42a-49a0-9d8f-616ca6dbebaa") -> 73df5aae-f42a-49a0-9d8f-616ca6dbebaa | AV16: =IFERROR(__xludf.DUMMYFUNCTION("""COMPUTED_VALUE"""),"019ed024-873d-7252-be6e-6e408eb5a4cb") -> 019ed024-873d-7252-be6e-6e408eb5a4cb | AW16: =IFERROR(__xludf.DUMMYFUNCTION("""COMPUTED_VALUE"""),46189.468923611115) -> 46189.469 | AX16: =IFERROR(__xludf.DUMMYFUNCTION("""COMPUTED_VALUE"""),"credit") -> credit | AY16: =IFERROR(__xludf.DUMMYFUNCTION("""COMPUTED_VALUE"""),20918.18) -> 20918.18 | AZ16: =IFERROR(__xludf.DUMMYFUNCTION("""COMPUTED_VALUE"""),"cash_isa") -> cash_isa | BA16: =IFERROR(__xludf.DUMMYFUNCTION("""COMPUTED_VALUE"""),"9bc00e6b-ce5f-48c5-ae3a-1baabe00f337") -> 9bc00e6b-ce5f-48c5-ae3a-1baabe00f337 | BB16: =IFERROR(__xludf.DUMMYFUNCTION("""COMPUTED_VALUE"""),"a7a2dae7-bd10-44fc-9b1b-25271dcf0442") -> a7a2dae7-bd10-44fc-9b1b-25271dcf0442 | BC16: =IFERROR(__xludf.DUMMYFUNCTION("""COMPUTED_VALUE"""),"a7a2dae7-bd10-44fc-9b1b-25271dcf0442") -> a7a2dae7-bd10-44fc-9b1b-25271dcf0442 | BD16: =IFERROR(__xludf.DUMMYFUNCTION("""COMPUTED_VALUE"""),"JX825895D-940686763") -> JX825895D-940686763 | BE16: =IFERROR(__xludf.DUMMYFUNCTION("""COMPUTED_VALUE"""),20918.18) -> 20918.18 | BF16: =IFERROR(__xludf.DUMMYFUNCTION("""COMPUTED_VALUE"""),"payin") -> payin | BG16: =IFERROR(__xludf.DUMMYFUNCTION("""COMPUTED_VALUE"""),46188.6688425926) -> 46188.669 | BI16: =IFERROR(__xludf.DUMMYFUNCTION("""COMPUTED_VALUE"""),"73df5aae-f42a-49a0-9d8f-616ca6dbebaa") -> 73df5aae-f42a-49a0-9d8f-616ca6dbebaa | BJ16: =IFERROR(__xludf.DUMMYFUNCTION("""COMPUTED_VALUE"""),"019ecfa0-3f18-7e31-adfb-8ce2d8bdb8ee") -> 019ecfa0-3f18-7e31-adfb-8ce2d8bdb8ee | BK16: =IFERROR(__xludf.DUMMYFUNCTION("""COMPUTED_VALUE"""),46189.36858796296) -> 46189.369 | BL16: =IFERROR(__xludf.DUMMYFUNCTION("""COMPUTED_VALUE"""),"debit") -> debit | BM16: =IFERROR(__xludf.DUMMYFUNCTION("""COMPUTED_VALUE"""),2947.19) -> 2947.19 | BN16: =IFERROR(__xludf.DUMMYFUNCTION("""COMPUTED_VALUE"""),"lisa") -> lisa | BO16: =IFERROR(__xludf.DUMMYFUNCTION("""COMPUTED_VALUE"""),"b7a59586-5d10-4989-91c2-f2376c7a6ab2") -> b7a59586-5d10-4989-91c2-f2376c7a6ab2 | BP16: =IFERROR(__xludf.DUMMYFUNCTION("""COMPUTED_VALUE"""),"1935cc33-9511-4da6-9e60-9efd3b40b01f") -> 1935cc33-9511-4da6-9e60-9efd3b40b01f | BQ16: =IFERROR(__xludf.DUMMYFUNCTION("""COMPUTED_VALUE"""),"1935cc33-9511-4da6-9e60-9efd3b40b01f") -> 1935cc33-9511-4da6-9e60-9efd3b40b01f | BR16: =IFERROR(__xludf.DUMMYFUNCTION("""COMPUTED_VALUE"""),"2B5BA2F8-2009140117") -> 2B5BA2F8-2009140117 | BS16: =IFERROR(__xludf.DUMMYFUNCTION("""COMPUTED_VALUE"""),2947.19) -> 2947.19 | BT16: =IFERROR(__xludf.DUMMYFUNCTION("""COMPUTED_VALUE"""),"payin") -> payin | BU16: =IFERROR(__xludf.DUMMYFUNCTION("""COMPUTED_VALUE"""),46175.52678240741) -> 46175.527
A17: 73df5aae-f42a-49a0-9d8f-616ca6dbebaa | B17: 019ecf7f-4053-7b98-956f-d28b77a4465d | C17: 46189.344 | D17: credit | E17: 64323.91 | F17: cash_isa | G17: 9bc00e6b-ce5f-48c5-ae3a-1baabe00f337 | H17: 0e6bf5a2-5f83-4dba-882b-f61da8185090 | AD17: =IFERROR(__xludf.DUMMYFUNCTION("""COMPUTED_VALUE"""),"73df5aae-f42a-49a0-9d8f-616ca6dbebaa") -> 73df5aae-f42a-49a0-9d8f-616ca6dbebaa | AE17: =IFERROR(__xludf.DUMMYFUNCTION("""COMPUTED_VALUE"""),"019ecf6b-b130-7c98-ab0b-5639f735de4f") -> 019ecf6b-b130-7c98-ab0b-5639f735de4f | AF17: =IFERROR(__xludf.DUMMYFUNCTION("""COMPUTED_VALUE"""),46189.32872685185) -> 46189.329 | AG17: =IFERROR(__xludf.DUMMYFUNCTION("""COMPUTED_VALUE"""),"credit") -> credit | AH17: =IFERROR(__xludf.DUMMYFUNCTION("""COMPUTED_VALUE"""),1000.0) -> 1000 | AI17: =IFERROR(__xludf.DUMMYFUNCTION("""COMPUTED_VALUE"""),"cash_isa") -> cash_isa | AJ17: =IFERROR(__xludf.DUMMYFUNCTION("""COMPUTED_VALUE"""),"9bc00e6b-ce5f-48c5-ae3a-1baabe00f337") -> 9bc00e6b-ce5f-48c5-ae3a-1baabe00f337 | AK17: =IFERROR(__xludf.DUMMYFUNCTION("""COMPUTED_VALUE"""),"594e43b2-4c16-4cdd-9a32-89078ce028d1") -> 594e43b2-4c16-4cdd-9a32-89078ce028d1 | AR17: =ROUND(VALUE(AH17),2)&"_"&TRIM(LOWER(AG17)) -> 1000_credit | AS17: =IF(AH17="", "", LET(current_amt, ROUND(VALUE(AH17), 2), current_dir, TRIM(LOWER(AG17)), opposite_dir, IF(current_dir="credit", "debit", "credit"), occ, COUNTIFS($AH$3:AH17, AH17, $AG$3:AG17, AG17), opp_total, COUNTIFS($AH$3:$AH$1000, AH17, $AG$3:$AG$1000, opposite_dir), IF(opp_total >= occ, "DROP", "KEEP"))) -> DROP | AU17: =IFERROR(__xludf.DUMMYFUNCTION("""COMPUTED_VALUE"""),"73df5aae-f42a-49a0-9d8f-616ca6dbebaa") -> 73df5aae-f42a-49a0-9d8f-616ca6dbebaa | AV17: =IFERROR(__xludf.DUMMYFUNCTION("""COMPUTED_VALUE"""),"019ed024-8a33-7fb5-96a0-78ffd98b3516") -> 019ed024-8a33-7fb5-96a0-78ffd98b3516 | AW17: =IFERROR(__xludf.DUMMYFUNCTION("""COMPUTED_VALUE"""),46189.468935185185) -> 46189.469 | AX17: =IFERROR(__xludf.DUMMYFUNCTION("""COMPUTED_VALUE"""),"credit") -> credit | AY17: =IFERROR(__xludf.DUMMYFUNCTION("""COMPUTED_VALUE"""),7.35) -> 7.35 | AZ17: =IFERROR(__xludf.DUMMYFUNCTION("""COMPUTED_VALUE"""),"cash_isa") -> cash_isa | BA17: =IFERROR(__xludf.DUMMYFUNCTION("""COMPUTED_VALUE"""),"9bc00e6b-ce5f-48c5-ae3a-1baabe00f337") -> 9bc00e6b-ce5f-48c5-ae3a-1baabe00f337 | BB17: =IFERROR(__xludf.DUMMYFUNCTION("""COMPUTED_VALUE"""),"42c3a58b-fec1-43e1-b86e-f071b829ba7a") -> 42c3a58b-fec1-43e1-b86e-f071b829ba7a | BC17: =IFERROR(__xludf.DUMMYFUNCTION("""COMPUTED_VALUE"""),"42c3a58b-fec1-43e1-b86e-f071b829ba7a") -> 42c3a58b-fec1-43e1-b86e-f071b829ba7a | BD17: =IFERROR(__xludf.DUMMYFUNCTION("""COMPUTED_VALUE"""),"NOREF-910332414") -> NOREF-910332414 | BE17: =IFERROR(__xludf.DUMMYFUNCTION("""COMPUTED_VALUE"""),7.35) -> 7.35 | BF17: =IFERROR(__xludf.DUMMYFUNCTION("""COMPUTED_VALUE"""),"payin") -> payin | BG17: =IFERROR(__xludf.DUMMYFUNCTION("""COMPUTED_VALUE"""),46188.454293981486) -> 46188.454 | BI17: =IFERROR(__xludf.DUMMYFUNCTION("""COMPUTED_VALUE"""),"73df5aae-f42a-49a0-9d8f-616ca6dbebaa") -> 73df5aae-f42a-49a0-9d8f-616ca6dbebaa | BJ17: =IFERROR(__xludf.DUMMYFUNCTION("""COMPUTED_VALUE"""),"019ed106-8d18-738d-8a7e-5bc8a77ccb6c") -> 019ed106-8d18-738d-8a7e-5bc8a77ccb6c | BK17: =IFERROR(__xludf.DUMMYFUNCTION("""COMPUTED_VALUE"""),46189.64037037037) -> 46189.64 | BL17: =IFERROR(__xludf.DUMMYFUNCTION("""COMPUTED_VALUE"""),"debit") -> debit | BM17: =IFERROR(__xludf.DUMMYFUNCTION("""COMPUTED_VALUE"""),21205.46) -> 21205.46 | BN17: =IFERROR(__xludf.DUMMYFUNCTION("""COMPUTED_VALUE"""),"lisa") -> lisa | BO17: =IFERROR(__xludf.DUMMYFUNCTION("""COMPUTED_VALUE"""),"b7a59586-5d10-4989-91c2-f2376c7a6ab2") -> b7a59586-5d10-4989-91c2-f2376c7a6ab2 | BP17: =IFERROR(__xludf.DUMMYFUNCTION("""COMPUTED_VALUE"""),"629fffa4-8403-483e-bfcf-bd8f562531f6") -> 629fffa4-8403-483e-bfcf-bd8f562531f6
A18: 73df5aae-f42a-49a0-9d8f-616ca6dbebaa | B18: 019ecf80-33b1-7893-b131-a45c80eb3ade | C18: 46189.344 | D18: debit | E18: 41.57 | F18: cash_isa | G18: 9bc00e6b-ce5f-48c5-ae3a-1baabe00f337 | H18: 5d9ab65f-d47d-440b-86fc-aada0df5983e | AD18: =IFERROR(__xludf.DUMMYFUNCTION("""COMPUTED_VALUE"""),"73df5aae-f42a-49a0-9d8f-616ca6dbebaa") -> 73df5aae-f42a-49a0-9d8f-616ca6dbebaa | AE18: =IFERROR(__xludf.DUMMYFUNCTION("""COMPUTED_VALUE"""),"019ecf6d-7783-75cc-a067-1d4535a564d3") -> 019ecf6d-7783-75cc-a067-1d4535a564d3 | AF18: =IFERROR(__xludf.DUMMYFUNCTION("""COMPUTED_VALUE"""),46189.33006944445) -> 46189.33 | AG18: =IFERROR(__xludf.DUMMYFUNCTION("""COMPUTED_VALUE"""),"debit") -> debit | AH18: =IFERROR(__xludf.DUMMYFUNCTION("""COMPUTED_VALUE"""),1000.0) -> 1000 | AI18: =IFERROR(__xludf.DUMMYFUNCTION("""COMPUTED_VALUE"""),"cash_isa") -> cash_isa | AJ18: =IFERROR(__xludf.DUMMYFUNCTION("""COMPUTED_VALUE"""),"9bc00e6b-ce5f-48c5-ae3a-1baabe00f337") -> 9bc00e6b-ce5f-48c5-ae3a-1baabe00f337 | AK18: =IFERROR(__xludf.DUMMYFUNCTION("""COMPUTED_VALUE"""),"594e43b2-4c16-4cdd-9a32-89078ce028d1") -> 594e43b2-4c16-4cdd-9a32-89078ce028d1 | AR18: =ROUND(VALUE(AH18),2)&"_"&TRIM(LOWER(AG18)) -> 1000_debit | AS18: =IF(AH18="", "", LET(current_amt, ROUND(VALUE(AH18), 2), current_dir, TRIM(LOWER(AG18)), opposite_dir, IF(current_dir="credit", "debit", "credit"), occ, COUNTIFS($AH$3:AH18, AH18, $AG$3:AG18, AG18), opp_total, COUNTIFS($AH$3:$AH$1000, AH18, $AG$3:$AG$1000, opposite_dir), IF(opp_total >= occ, "DROP", "KEEP"))) -> DROP | AU18: =IFERROR(__xludf.DUMMYFUNCTION("""COMPUTED_VALUE"""),"73df5aae-f42a-49a0-9d8f-616ca6dbebaa") -> 73df5aae-f42a-49a0-9d8f-616ca6dbebaa | AV18: =IFERROR(__xludf.DUMMYFUNCTION("""COMPUTED_VALUE"""),"019ed024-88f1-789c-a803-e90f28c9087e") -> 019ed024-88f1-789c-a803-e90f28c9087e | AW18: =IFERROR(__xludf.DUMMYFUNCTION("""COMPUTED_VALUE"""),46189.468935185185) -> 46189.469 | AX18: =IFERROR(__xludf.DUMMYFUNCTION("""COMPUTED_VALUE"""),"credit") -> credit | AY18: =IFERROR(__xludf.DUMMYFUNCTION("""COMPUTED_VALUE"""),250.0) -> 250 | AZ18: =IFERROR(__xludf.DUMMYFUNCTION("""COMPUTED_VALUE"""),"cash_isa") -> cash_isa | BA18: =IFERROR(__xludf.DUMMYFUNCTION("""COMPUTED_VALUE"""),"9bc00e6b-ce5f-48c5-ae3a-1baabe00f337") -> 9bc00e6b-ce5f-48c5-ae3a-1baabe00f337 | BB18: =IFERROR(__xludf.DUMMYFUNCTION("""COMPUTED_VALUE"""),"5a92f897-6035-4172-9831-90028a8a98c2") -> 5a92f897-6035-4172-9831-90028a8a98c2 | BC18: =IFERROR(__xludf.DUMMYFUNCTION("""COMPUTED_VALUE"""),"5a92f897-6035-4172-9831-90028a8a98c2") -> 5a92f897-6035-4172-9831-90028a8a98c2 | BD18: =IFERROR(__xludf.DUMMYFUNCTION("""COMPUTED_VALUE"""),"JC321715Da-518647334") -> JC321715Da-518647334 | BE18: =IFERROR(__xludf.DUMMYFUNCTION("""COMPUTED_VALUE"""),250.0) -> 250 | BF18: =IFERROR(__xludf.DUMMYFUNCTION("""COMPUTED_VALUE"""),"payin") -> payin | BG18: =IFERROR(__xludf.DUMMYFUNCTION("""COMPUTED_VALUE"""),46188.66883101852) -> 46188.669 | BI18: =IFERROR(__xludf.DUMMYFUNCTION("""COMPUTED_VALUE"""),"73df5aae-f42a-49a0-9d8f-616ca6dbebaa") -> 73df5aae-f42a-49a0-9d8f-616ca6dbebaa | BJ18: =IFERROR(__xludf.DUMMYFUNCTION("""COMPUTED_VALUE"""),"019ed10b-87fe-7bfe-9ab3-43b1831a7655") -> 019ed10b-87fe-7bfe-9ab3-43b1831a7655 | BK18: =IFERROR(__xludf.DUMMYFUNCTION("""COMPUTED_VALUE"""),46189.64414351852) -> 46189.644 | BL18: =IFERROR(__xludf.DUMMYFUNCTION("""COMPUTED_VALUE"""),"debit") -> debit | BM18: =IFERROR(__xludf.DUMMYFUNCTION("""COMPUTED_VALUE"""),26943.49) -> 26943.49 | BN18: =IFERROR(__xludf.DUMMYFUNCTION("""COMPUTED_VALUE"""),"lisa") -> lisa | BO18: =IFERROR(__xludf.DUMMYFUNCTION("""COMPUTED_VALUE"""),"b7a59586-5d10-4989-91c2-f2376c7a6ab2") -> b7a59586-5d10-4989-91c2-f2376c7a6ab2 | BP18: =IFERROR(__xludf.DUMMYFUNCTION("""COMPUTED_VALUE"""),"abd21e39-3692-4dad-953e-1ce78659b0dc") -> abd21e39-3692-4dad-953e-1ce78659b0dc
A19: 73df5aae-f42a-49a0-9d8f-616ca6dbebaa | B19: 019ecf81-99d5-7b76-843e-8be19854b4e5 | C19: 46189.345 | D19: credit | E19: 5983.9 | F19: cash_isa | G19: 9bc00e6b-ce5f-48c5-ae3a-1baabe00f337 | H19: c2e67f69-0639-42c8-ad6e-b466688be698 | AD19: =IFERROR(__xludf.DUMMYFUNCTION("""COMPUTED_VALUE"""),"73df5aae-f42a-49a0-9d8f-616ca6dbebaa") -> 73df5aae-f42a-49a0-9d8f-616ca6dbebaa | AE19: =IFERROR(__xludf.DUMMYFUNCTION("""COMPUTED_VALUE"""),"019ecf6e-8f11-753c-8898-9bf70a4b7f21") -> 019ecf6e-8f11-753c-8898-9bf70a4b7f21 | AF19: =IFERROR(__xludf.DUMMYFUNCTION("""COMPUTED_VALUE"""),46189.33090277778) -> 46189.331 | AG19: =IFERROR(__xludf.DUMMYFUNCTION("""COMPUTED_VALUE"""),"credit") -> credit | AH19: =IFERROR(__xludf.DUMMYFUNCTION("""COMPUTED_VALUE"""),21769.77) -> 21769.77 | AI19: =IFERROR(__xludf.DUMMYFUNCTION("""COMPUTED_VALUE"""),"cash_isa") -> cash_isa | AJ19: =IFERROR(__xludf.DUMMYFUNCTION("""COMPUTED_VALUE"""),"9bc00e6b-ce5f-48c5-ae3a-1baabe00f337") -> 9bc00e6b-ce5f-48c5-ae3a-1baabe00f337 | AK19: =IFERROR(__xludf.DUMMYFUNCTION("""COMPUTED_VALUE"""),"9438e43a-27ed-4543-a6a9-a8d6dcc297fa") -> 9438e43a-27ed-4543-a6a9-a8d6dcc297fa | AR19: =ROUND(VALUE(AH19),2)&"_"&TRIM(LOWER(AG19)) -> 21769.77_credit | AS19: =IF(AH19="", "", LET(current_amt, ROUND(VALUE(AH19), 2), current_dir, TRIM(LOWER(AG19)), opposite_dir, IF(current_dir="credit", "debit", "credit"), occ, COUNTIFS($AH$3:AH19, AH19, $AG$3:AG19, AG19), opp_total, COUNTIFS($AH$3:$AH$1000, AH19, $AG$3:$AG$1000, opposite_dir), IF(opp_total >= occ, "DROP", "KEEP"))) -> DROP | AU19: =IFERROR(__xludf.DUMMYFUNCTION("""COMPUTED_VALUE"""),"73df5aae-f42a-49a0-9d8f-616ca6dbebaa") -> 73df5aae-f42a-49a0-9d8f-616ca6dbebaa | AV19: =IFERROR(__xludf.DUMMYFUNCTION("""COMPUTED_VALUE"""),"019ed024-8817-7d80-9685-39944e000a98") -> 019ed024-8817-7d80-9685-39944e000a98 | AW19: =IFERROR(__xludf.DUMMYFUNCTION("""COMPUTED_VALUE"""),46189.468935185185) -> 46189.469 | AX19: =IFERROR(__xludf.DUMMYFUNCTION("""COMPUTED_VALUE"""),"credit") -> credit | AY19: =IFERROR(__xludf.DUMMYFUNCTION("""COMPUTED_VALUE"""),42534.92) -> 42534.92 | AZ19: =IFERROR(__xludf.DUMMYFUNCTION("""COMPUTED_VALUE"""),"cash_isa") -> cash_isa | BA19: =IFERROR(__xludf.DUMMYFUNCTION("""COMPUTED_VALUE"""),"9bc00e6b-ce5f-48c5-ae3a-1baabe00f337") -> 9bc00e6b-ce5f-48c5-ae3a-1baabe00f337 | BB19: =IFERROR(__xludf.DUMMYFUNCTION("""COMPUTED_VALUE"""),"a50f2b4e-4ed2-48c6-ae8b-f3052f76d926") -> a50f2b4e-4ed2-48c6-ae8b-f3052f76d926 | BC19: =IFERROR(__xludf.DUMMYFUNCTION("""COMPUTED_VALUE"""),"a50f2b4e-4ed2-48c6-ae8b-f3052f76d926") -> a50f2b4e-4ed2-48c6-ae8b-f3052f76d926 | BD19: =IFERROR(__xludf.DUMMYFUNCTION("""COMPUTED_VALUE"""),"YM189882D-95846103") -> YM189882D-95846103 | BE19: =IFERROR(__xludf.DUMMYFUNCTION("""COMPUTED_VALUE"""),42534.92) -> 42534.92 | BF19: =IFERROR(__xludf.DUMMYFUNCTION("""COMPUTED_VALUE"""),"payin") -> payin | BG19: =IFERROR(__xludf.DUMMYFUNCTION("""COMPUTED_VALUE"""),46188.6688425926) -> 46188.669 | BI19: =IFERROR(__xludf.DUMMYFUNCTION("""COMPUTED_VALUE"""),"73df5aae-f42a-49a0-9d8f-616ca6dbebaa") -> 73df5aae-f42a-49a0-9d8f-616ca6dbebaa | BJ19: =IFERROR(__xludf.DUMMYFUNCTION("""COMPUTED_VALUE"""),"019ed10e-c95e-7385-85da-4610da8ec41d") -> 019ed10e-c95e-7385-85da-4610da8ec41d | BK19: =IFERROR(__xludf.DUMMYFUNCTION("""COMPUTED_VALUE"""),46189.646620370375) -> 46189.647 | BL19: =IFERROR(__xludf.DUMMYFUNCTION("""COMPUTED_VALUE"""),"debit") -> debit | BM19: =IFERROR(__xludf.DUMMYFUNCTION("""COMPUTED_VALUE"""),17528.76) -> 17528.76 | BN19: =IFERROR(__xludf.DUMMYFUNCTION("""COMPUTED_VALUE"""),"lisa") -> lisa | BO19: =IFERROR(__xludf.DUMMYFUNCTION("""COMPUTED_VALUE"""),"b7a59586-5d10-4989-91c2-f2376c7a6ab2") -> b7a59586-5d10-4989-91c2-f2376c7a6ab2 | BP19: =IFERROR(__xludf.DUMMYFUNCTION("""COMPUTED_VALUE"""),"422fddac-6442-4981-a853-f69f70a6b24e") -> 422fddac-6442-4981-a853-f69f70a6b24e
A20: 73df5aae-f42a-49a0-9d8f-616ca6dbebaa | B20: 019ecf82-6586-7984-9b18-d51401b605bd | C20: 46189.346 | D20: debit | E20: 64323.91 | F20: cash_isa | G20: 9bc00e6b-ce5f-48c5-ae3a-1baabe00f337 | H20: 0e6bf5a2-5f83-4dba-882b-f61da8185090 | AD20: =IFERROR(__xludf.DUMMYFUNCTION("""COMPUTED_VALUE"""),"73df5aae-f42a-49a0-9d8f-616ca6dbebaa") -> 73df5aae-f42a-49a0-9d8f-616ca6dbebaa | AE20: =IFERROR(__xludf.DUMMYFUNCTION("""COMPUTED_VALUE"""),"019ecf6f-d53d-72ab-945b-6e5f498392aa") -> 019ecf6f-d53d-72ab-945b-6e5f498392aa | AF20: =IFERROR(__xludf.DUMMYFUNCTION("""COMPUTED_VALUE"""),46189.33186342593) -> 46189.332 | AG20: =IFERROR(__xludf.DUMMYFUNCTION("""COMPUTED_VALUE"""),"debit") -> debit | AH20: =IFERROR(__xludf.DUMMYFUNCTION("""COMPUTED_VALUE"""),21769.77) -> 21769.77 | AI20: =IFERROR(__xludf.DUMMYFUNCTION("""COMPUTED_VALUE"""),"cash_isa") -> cash_isa | AJ20: =IFERROR(__xludf.DUMMYFUNCTION("""COMPUTED_VALUE"""),"9bc00e6b-ce5f-48c5-ae3a-1baabe00f337") -> 9bc00e6b-ce5f-48c5-ae3a-1baabe00f337 | AK20: =IFERROR(__xludf.DUMMYFUNCTION("""COMPUTED_VALUE"""),"9438e43a-27ed-4543-a6a9-a8d6dcc297fa") -> 9438e43a-27ed-4543-a6a9-a8d6dcc297fa | AR20: =ROUND(VALUE(AH20),2)&"_"&TRIM(LOWER(AG20)) -> 21769.77_debit | AS20: =IF(AH20="", "", LET(current_amt, ROUND(VALUE(AH20), 2), current_dir, TRIM(LOWER(AG20)), opposite_dir, IF(current_dir="credit", "debit", "credit"), occ, COUNTIFS($AH$3:AH20, AH20, $AG$3:AG20, AG20), opp_total, COUNTIFS($AH$3:$AH$1000, AH20, $AG$3:$AG$1000, opposite_dir), IF(opp_total >= occ, "DROP", "KEEP"))) -> DROP | AU20: =IFERROR(__xludf.DUMMYFUNCTION("""COMPUTED_VALUE"""),"73df5aae-f42a-49a0-9d8f-616ca6dbebaa") -> 73df5aae-f42a-49a0-9d8f-616ca6dbebaa | AV20: =IFERROR(__xludf.DUMMYFUNCTION("""COMPUTED_VALUE"""),"019ed024-8a33-7fb5-96a0-78ffd98b3516") -> 019ed024-8a33-7fb5-96a0-78ffd98b3516 | AW20: =IFERROR(__xludf.DUMMYFUNCTION("""COMPUTED_VALUE"""),46189.468935185185) -> 46189.469 | AX20: =IFERROR(__xludf.DUMMYFUNCTION("""COMPUTED_VALUE"""),"credit") -> credit | AY20: =IFERROR(__xludf.DUMMYFUNCTION("""COMPUTED_VALUE"""),7.35) -> 7.35 | AZ20: =IFERROR(__xludf.DUMMYFUNCTION("""COMPUTED_VALUE"""),"cash_isa") -> cash_isa | BA20: =IFERROR(__xludf.DUMMYFUNCTION("""COMPUTED_VALUE"""),"9bc00e6b-ce5f-48c5-ae3a-1baabe00f337") -> 9bc00e6b-ce5f-48c5-ae3a-1baabe00f337 | BB20: =IFERROR(__xludf.DUMMYFUNCTION("""COMPUTED_VALUE"""),"42c3a58b-fec1-43e1-b86e-f071b829ba7a") -> 42c3a58b-fec1-43e1-b86e-f071b829ba7a | BC20: =IFERROR(__xludf.DUMMYFUNCTION("""COMPUTED_VALUE"""),"42c3a58b-fec1-43e1-b86e-f071b829ba7a") -> 42c3a58b-fec1-43e1-b86e-f071b829ba7a | BD20: =IFERROR(__xludf.DUMMYFUNCTION("""COMPUTED_VALUE"""),"NOREF-910332414") -> NOREF-910332414 | BE20: =IFERROR(__xludf.DUMMYFUNCTION("""COMPUTED_VALUE"""),7.35) -> 7.35 | BF20: =IFERROR(__xludf.DUMMYFUNCTION("""COMPUTED_VALUE"""),"payin") -> payin | BG20: =IFERROR(__xludf.DUMMYFUNCTION("""COMPUTED_VALUE"""),46188.454293981486) -> 46188.454 | BI20: =IFERROR(__xludf.DUMMYFUNCTION("""COMPUTED_VALUE"""),"73df5aae-f42a-49a0-9d8f-616ca6dbebaa") -> 73df5aae-f42a-49a0-9d8f-616ca6dbebaa | BJ20: =IFERROR(__xludf.DUMMYFUNCTION("""COMPUTED_VALUE"""),"019ed111-80c9-71c2-80c7-3a0950730587") -> 019ed111-80c9-71c2-80c7-3a0950730587 | BK20: =IFERROR(__xludf.DUMMYFUNCTION("""COMPUTED_VALUE"""),46189.648680555554) -> 46189.649 | BL20: =IFERROR(__xludf.DUMMYFUNCTION("""COMPUTED_VALUE"""),"debit") -> debit | BM20: =IFERROR(__xludf.DUMMYFUNCTION("""COMPUTED_VALUE"""),1000.42) -> 1000.42 | BN20: =IFERROR(__xludf.DUMMYFUNCTION("""COMPUTED_VALUE"""),"lisa") -> lisa | BO20: =IFERROR(__xludf.DUMMYFUNCTION("""COMPUTED_VALUE"""),"b7a59586-5d10-4989-91c2-f2376c7a6ab2") -> b7a59586-5d10-4989-91c2-f2376c7a6ab2 | BP20: =IFERROR(__xludf.DUMMYFUNCTION("""COMPUTED_VALUE"""),"4e841ef5-73e4-4848-91ba-916bf1dd82de") -> 4e841ef5-73e4-4848-91ba-916bf1dd82de | BQ20: =IFERROR(__xludf.DUMMYFUNCTION("""COMPUTED_VALUE"""),"4e841ef5-73e4-4848-91ba-916bf1dd82de") -> 4e841ef5-73e4-4848-91ba-916bf1dd82de | BR20: =IFERROR(__xludf.DUMMYFUNCTION("""COMPUTED_VALUE"""),"6362d774-321174183") -> 6362d774-321174183 | BS20: =IFERROR(__xludf.DUMMYFUNCTION("""COMPUTED_VALUE"""),1000.42) -> 1000.42 | BT20: =IFERROR(__xludf.DUMMYFUNCTION("""COMPUTED_VALUE"""),"payin") -> payin | BU20: =IFERROR(__xludf.DUMMYFUNCTION("""COMPUTED_VALUE"""),46175.11004629629) -> 46175.11
A21: 73df5aae-f42a-49a0-9d8f-616ca6dbebaa | B21: 019ecf82-dc4b-7660-bc65-34689d6a0cb5 | C21: 46189.346 | D21: debit | E21: 5983.9 | F21: cash_isa | G21: 9bc00e6b-ce5f-48c5-ae3a-1baabe00f337 | H21: c2e67f69-0639-42c8-ad6e-b466688be698 | AD21: =IFERROR(__xludf.DUMMYFUNCTION("""COMPUTED_VALUE"""),"73df5aae-f42a-49a0-9d8f-616ca6dbebaa") -> 73df5aae-f42a-49a0-9d8f-616ca6dbebaa | AE21: =IFERROR(__xludf.DUMMYFUNCTION("""COMPUTED_VALUE"""),"019ecf71-0f39-7517-ba66-2d9a255cf8fb") -> 019ecf71-0f39-7517-ba66-2d9a255cf8fb | AF21: =IFERROR(__xludf.DUMMYFUNCTION("""COMPUTED_VALUE"""),46189.33280092593) -> 46189.333 | AG21: =IFERROR(__xludf.DUMMYFUNCTION("""COMPUTED_VALUE"""),"credit") -> credit | AH21: =IFERROR(__xludf.DUMMYFUNCTION("""COMPUTED_VALUE"""),12001.69) -> 12001.69 | AI21: =IFERROR(__xludf.DUMMYFUNCTION("""COMPUTED_VALUE"""),"cash_isa") -> cash_isa | AJ21: =IFERROR(__xludf.DUMMYFUNCTION("""COMPUTED_VALUE"""),"9bc00e6b-ce5f-48c5-ae3a-1baabe00f337") -> 9bc00e6b-ce5f-48c5-ae3a-1baabe00f337 | AK21: =IFERROR(__xludf.DUMMYFUNCTION("""COMPUTED_VALUE"""),"43fda8b1-46b9-42e8-ae27-47e24487252b") -> 43fda8b1-46b9-42e8-ae27-47e24487252b | AR21: =ROUND(VALUE(AH21),2)&"_"&TRIM(LOWER(AG21)) -> 12001.69_credit | AS21: =IF(AH21="", "", LET(current_amt, ROUND(VALUE(AH21), 2), current_dir, TRIM(LOWER(AG21)), opposite_dir, IF(current_dir="credit", "debit", "credit"), occ, COUNTIFS($AH$3:AH21, AH21, $AG$3:AG21, AG21), opp_total, COUNTIFS($AH$3:$AH$1000, AH21, $AG$3:$AG$1000, opposite_dir), IF(opp_total >= occ, "DROP", "KEEP"))) -> DROP | AU21: =IFERROR(__xludf.DUMMYFUNCTION("""COMPUTED_VALUE"""),"73df5aae-f42a-49a0-9d8f-616ca6dbebaa") -> 73df5aae-f42a-49a0-9d8f-616ca6dbebaa | AV21: =IFERROR(__xludf.DUMMYFUNCTION("""COMPUTED_VALUE"""),"019ed024-88f1-789c-a803-e90f28c9087e") -> 019ed024-88f1-789c-a803-e90f28c9087e | AW21: =IFERROR(__xludf.DUMMYFUNCTION("""COMPUTED_VALUE"""),46189.468935185185) -> 46189.469 | AX21: =IFERROR(__xludf.DUMMYFUNCTION("""COMPUTED_VALUE"""),"credit") -> credit | AY21: =IFERROR(__xludf.DUMMYFUNCTION("""COMPUTED_VALUE"""),250.0) -> 250 | AZ21: =IFERROR(__xludf.DUMMYFUNCTION("""COMPUTED_VALUE"""),"cash_isa") -> cash_isa | BA21: =IFERROR(__xludf.DUMMYFUNCTION("""COMPUTED_VALUE"""),"9bc00e6b-ce5f-48c5-ae3a-1baabe00f337") -> 9bc00e6b-ce5f-48c5-ae3a-1baabe00f337 | BB21: =IFERROR(__xludf.DUMMYFUNCTION("""COMPUTED_VALUE"""),"5a92f897-6035-4172-9831-90028a8a98c2") -> 5a92f897-6035-4172-9831-90028a8a98c2 | BC21: =IFERROR(__xludf.DUMMYFUNCTION("""COMPUTED_VALUE"""),"5a92f897-6035-4172-9831-90028a8a98c2") -> 5a92f897-6035-4172-9831-90028a8a98c2 | BD21: =IFERROR(__xludf.DUMMYFUNCTION("""COMPUTED_VALUE"""),"JC321715Da-518647334") -> JC321715Da-518647334 | BE21: =IFERROR(__xludf.DUMMYFUNCTION("""COMPUTED_VALUE"""),250.0) -> 250 | BF21: =IFERROR(__xludf.DUMMYFUNCTION("""COMPUTED_VALUE"""),"payin") -> payin | BG21: =IFERROR(__xludf.DUMMYFUNCTION("""COMPUTED_VALUE"""),46188.66883101852) -> 46188.669 | BI21: =IFERROR(__xludf.DUMMYFUNCTION("""COMPUTED_VALUE"""),"73df5aae-f42a-49a0-9d8f-616ca6dbebaa") -> 73df5aae-f42a-49a0-9d8f-616ca6dbebaa | BJ21: =IFERROR(__xludf.DUMMYFUNCTION("""COMPUTED_VALUE"""),"019ed112-f8af-78aa-8996-cea5aa226d4d") -> 019ed112-f8af-78aa-8996-cea5aa226d4d | BK21: =IFERROR(__xludf.DUMMYFUNCTION("""COMPUTED_VALUE"""),46189.64979166667) -> 46189.65 | BL21: =IFERROR(__xludf.DUMMYFUNCTION("""COMPUTED_VALUE"""),"debit") -> debit | BM21: =IFERROR(__xludf.DUMMYFUNCTION("""COMPUTED_VALUE"""),287.51) -> 287.51 | BN21: =IFERROR(__xludf.DUMMYFUNCTION("""COMPUTED_VALUE"""),"lisa") -> lisa | BO21: =IFERROR(__xludf.DUMMYFUNCTION("""COMPUTED_VALUE"""),"b7a59586-5d10-4989-91c2-f2376c7a6ab2") -> b7a59586-5d10-4989-91c2-f2376c7a6ab2 | BP21: =IFERROR(__xludf.DUMMYFUNCTION("""COMPUTED_VALUE"""),"269f467b-4dc9-4274-b31d-aced2ae027f2") -> 269f467b-4dc9-4274-b31d-aced2ae027f2 | BQ21: =IFERROR(__xludf.DUMMYFUNCTION("""COMPUTED_VALUE"""),"269f467b-4dc9-4274-b31d-aced2ae027f2") -> 269f467b-4dc9-4274-b31d-aced2ae027f2 | BR21: =IFERROR(__xludf.DUMMYFUNCTION("""COMPUTED_VALUE"""),"OPF620134950-422241025") -> OPF620134950-422241025 | BS21: =IFERROR(__xludf.DUMMYFUNCTION("""COMPUTED_VALUE"""),287.51) -> 287.51 | BT21: =IFERROR(__xludf.DUMMYFUNCTION("""COMPUTED_VALUE"""),"payin") -> payin | BU21: =IFERROR(__xludf.DUMMYFUNCTION("""COMPUTED_VALUE"""),46175.39371527778) -> 46175.394
A22: 73df5aae-f42a-49a0-9d8f-616ca6dbebaa | B22: 019ecf84-2564-7568-86d7-f5bc38db90ce | C22: 46189.347 | D22: credit | E22: 43516.22 | F22: cash_isa | G22: 9bc00e6b-ce5f-48c5-ae3a-1baabe00f337 | H22: d7cdd0e3-4ed8-45e6-9437-21b31d2214e9 | AD22: =IFERROR(__xludf.DUMMYFUNCTION("""COMPUTED_VALUE"""),"73df5aae-f42a-49a0-9d8f-616ca6dbebaa") -> 73df5aae-f42a-49a0-9d8f-616ca6dbebaa | AE22: =IFERROR(__xludf.DUMMYFUNCTION("""COMPUTED_VALUE"""),"019ecf73-786f-735a-8d04-a5ef897c515a") -> 019ecf73-786f-735a-8d04-a5ef897c515a | AF22: =IFERROR(__xludf.DUMMYFUNCTION("""COMPUTED_VALUE"""),46189.33462962963) -> 46189.335 | AG22: =IFERROR(__xludf.DUMMYFUNCTION("""COMPUTED_VALUE"""),"debit") -> debit | AH22: =IFERROR(__xludf.DUMMYFUNCTION("""COMPUTED_VALUE"""),12001.69) -> 12001.69 | AI22: =IFERROR(__xludf.DUMMYFUNCTION("""COMPUTED_VALUE"""),"cash_isa") -> cash_isa | AJ22: =IFERROR(__xludf.DUMMYFUNCTION("""COMPUTED_VALUE"""),"9bc00e6b-ce5f-48c5-ae3a-1baabe00f337") -> 9bc00e6b-ce5f-48c5-ae3a-1baabe00f337 | AK22: =IFERROR(__xludf.DUMMYFUNCTION("""COMPUTED_VALUE"""),"43fda8b1-46b9-42e8-ae27-47e24487252b") -> 43fda8b1-46b9-42e8-ae27-47e24487252b | AR22: =ROUND(VALUE(AH22),2)&"_"&TRIM(LOWER(AG22)) -> 12001.69_debit | AS22: =IF(AH22="", "", LET(current_amt, ROUND(VALUE(AH22), 2), current_dir, TRIM(LOWER(AG22)), opposite_dir, IF(current_dir="credit", "debit", "credit"), occ, COUNTIFS($AH$3:AH22, AH22, $AG$3:AG22, AG22), opp_total, COUNTIFS($AH$3:$AH$1000, AH22, $AG$3:$AG$1000, opposite_dir), IF(opp_total >= occ, "DROP", "KEEP"))) -> DROP | AU22: =IFERROR(__xludf.DUMMYFUNCTION("""COMPUTED_VALUE"""),"73df5aae-f42a-49a0-9d8f-616ca6dbebaa") -> 73df5aae-f42a-49a0-9d8f-616ca6dbebaa | AV22: =IFERROR(__xludf.DUMMYFUNCTION("""COMPUTED_VALUE"""),"019ed024-8817-7d80-9685-39944e000a98") -> 019ed024-8817-7d80-9685-39944e000a98 | AW22: =IFERROR(__xludf.DUMMYFUNCTION("""COMPUTED_VALUE"""),46189.468935185185) -> 46189.469 | AX22: =IFERROR(__xludf.DUMMYFUNCTION("""COMPUTED_VALUE"""),"credit") -> credit | AY22: =IFERROR(__xludf.DUMMYFUNCTION("""COMPUTED_VALUE"""),42534.92) -> 42534.92 | AZ22: =IFERROR(__xludf.DUMMYFUNCTION("""COMPUTED_VALUE"""),"cash_isa") -> cash_isa | BA22: =IFERROR(__xludf.DUMMYFUNCTION("""COMPUTED_VALUE"""),"9bc00e6b-ce5f-48c5-ae3a-1baabe00f337") -> 9bc00e6b-ce5f-48c5-ae3a-1baabe00f337 | BB22: =IFERROR(__xludf.DUMMYFUNCTION("""COMPUTED_VALUE"""),"a50f2b4e-4ed2-48c6-ae8b-f3052f76d926") -> a50f2b4e-4ed2-48c6-ae8b-f3052f76d926 | BC22: =IFERROR(__xludf.DUMMYFUNCTION("""COMPUTED_VALUE"""),"a50f2b4e-4ed2-48c6-ae8b-f3052f76d926") -> a50f2b4e-4ed2-48c6-ae8b-f3052f76d926 | BD22: =IFERROR(__xludf.DUMMYFUNCTION("""COMPUTED_VALUE"""),"YM189882D-95846103") -> YM189882D-95846103 | BE22: =IFERROR(__xludf.DUMMYFUNCTION("""COMPUTED_VALUE"""),42534.92) -> 42534.92 | BF22: =IFERROR(__xludf.DUMMYFUNCTION("""COMPUTED_VALUE"""),"payin") -> payin | BG22: =IFERROR(__xludf.DUMMYFUNCTION("""COMPUTED_VALUE"""),46188.6688425926) -> 46188.669 | BI22: =IFERROR(__xludf.DUMMYFUNCTION("""COMPUTED_VALUE"""),"73df5aae-f42a-49a0-9d8f-616ca6dbebaa") -> 73df5aae-f42a-49a0-9d8f-616ca6dbebaa | BJ22: =IFERROR(__xludf.DUMMYFUNCTION("""COMPUTED_VALUE"""),"019ed112-f7af-7caa-9686-de7b4e8d9dfb") -> 019ed112-f7af-7caa-9686-de7b4e8d9dfb | BK22: =IFERROR(__xludf.DUMMYFUNCTION("""COMPUTED_VALUE"""),46189.64979166667) -> 46189.65 | BL22: =IFERROR(__xludf.DUMMYFUNCTION("""COMPUTED_VALUE"""),"debit") -> debit | BM22: =IFERROR(__xludf.DUMMYFUNCTION("""COMPUTED_VALUE"""),14249.6) -> 14249.6 | BN22: =IFERROR(__xludf.DUMMYFUNCTION("""COMPUTED_VALUE"""),"lisa") -> lisa | BO22: =IFERROR(__xludf.DUMMYFUNCTION("""COMPUTED_VALUE"""),"b7a59586-5d10-4989-91c2-f2376c7a6ab2") -> b7a59586-5d10-4989-91c2-f2376c7a6ab2 | BP22: =IFERROR(__xludf.DUMMYFUNCTION("""COMPUTED_VALUE"""),"3bcaf2ad-dac4-40c4-9479-a43fde56f84f") -> 3bcaf2ad-dac4-40c4-9479-a43fde56f84f | BQ22: =IFERROR(__xludf.DUMMYFUNCTION("""COMPUTED_VALUE"""),"3bcaf2ad-dac4-40c4-9479-a43fde56f84f") -> 3bcaf2ad-dac4-40c4-9479-a43fde56f84f | BR22: =IFERROR(__xludf.DUMMYFUNCTION("""COMPUTED_VALUE"""),"NOREF-1340928121") -> NOREF-1340928121 | BS22: =IFERROR(__xludf.DUMMYFUNCTION("""COMPUTED_VALUE"""),14249.6) -> 14249.6 | BT22: =IFERROR(__xludf.DUMMYFUNCTION("""COMPUTED_VALUE"""),"payin") -> payin | BU22: =IFERROR(__xludf.DUMMYFUNCTION("""COMPUTED_VALUE"""),46175.46650462963) -> 46175.467
A23: 73df5aae-f42a-49a0-9d8f-616ca6dbebaa | B23: 019ecf85-3437-7732-9d69-781ef136ee47 | C23: 46189.348 | D23: credit | E23: 33950.32 | F23: cash_isa | G23: 9bc00e6b-ce5f-48c5-ae3a-1baabe00f337 | H23: b62bdbfd-3364-49ee-bdea-86f10c50c819 | AD23: =IFERROR(__xludf.DUMMYFUNCTION("""COMPUTED_VALUE"""),"73df5aae-f42a-49a0-9d8f-616ca6dbebaa") -> 73df5aae-f42a-49a0-9d8f-616ca6dbebaa | AE23: =IFERROR(__xludf.DUMMYFUNCTION("""COMPUTED_VALUE"""),"019ecf74-d8d6-7b98-aed4-3cd32fccee78") -> 019ecf74-d8d6-7b98-aed4-3cd32fccee78 | AF23: =IFERROR(__xludf.DUMMYFUNCTION("""COMPUTED_VALUE"""),46189.3356712963) -> 46189.336 | AG23: =IFERROR(__xludf.DUMMYFUNCTION("""COMPUTED_VALUE"""),"credit") -> credit | AH23: =IFERROR(__xludf.DUMMYFUNCTION("""COMPUTED_VALUE"""),21791.12) -> 21791.12 | AI23: =IFERROR(__xludf.DUMMYFUNCTION("""COMPUTED_VALUE"""),"cash_isa") -> cash_isa | AJ23: =IFERROR(__xludf.DUMMYFUNCTION("""COMPUTED_VALUE"""),"9bc00e6b-ce5f-48c5-ae3a-1baabe00f337") -> 9bc00e6b-ce5f-48c5-ae3a-1baabe00f337 | AK23: =IFERROR(__xludf.DUMMYFUNCTION("""COMPUTED_VALUE"""),"68bf96ba-6b4e-4626-989e-f5394ed71986") -> 68bf96ba-6b4e-4626-989e-f5394ed71986 | AR23: =ROUND(VALUE(AH23),2)&"_"&TRIM(LOWER(AG23)) -> 21791.12_credit | AS23: =IF(AH23="", "", LET(current_amt, ROUND(VALUE(AH23), 2), current_dir, TRIM(LOWER(AG23)), opposite_dir, IF(current_dir="credit", "debit", "credit"), occ, COUNTIFS($AH$3:AH23, AH23, $AG$3:AG23, AG23), opp_total, COUNTIFS($AH$3:$AH$1000, AH23, $AG$3:$AG$1000, opposite_dir), IF(opp_total >= occ, "DROP", "KEEP"))) -> DROP | AU23: =IFERROR(__xludf.DUMMYFUNCTION("""COMPUTED_VALUE"""),"73df5aae-f42a-49a0-9d8f-616ca6dbebaa") -> 73df5aae-f42a-49a0-9d8f-616ca6dbebaa | AV23: =IFERROR(__xludf.DUMMYFUNCTION("""COMPUTED_VALUE"""),"019ed0b1-3052-7f73-9d08-db917a292c59") -> 019ed0b1-3052-7f73-9d08-db917a292c59 | AW23: =IFERROR(__xludf.DUMMYFUNCTION("""COMPUTED_VALUE"""),46189.575625) -> 46189.576 | AX23: =IFERROR(__xludf.DUMMYFUNCTION("""COMPUTED_VALUE"""),"credit") -> credit | AY23: =IFERROR(__xludf.DUMMYFUNCTION("""COMPUTED_VALUE"""),14930.71) -> 14930.71 | AZ23: =IFERROR(__xludf.DUMMYFUNCTION("""COMPUTED_VALUE"""),"cash_isa") -> cash_isa | BA23: =IFERROR(__xludf.DUMMYFUNCTION("""COMPUTED_VALUE"""),"9bc00e6b-ce5f-48c5-ae3a-1baabe00f337") -> 9bc00e6b-ce5f-48c5-ae3a-1baabe00f337 | BB23: =IFERROR(__xludf.DUMMYFUNCTION("""COMPUTED_VALUE"""),"37db9098-7f00-401d-be6f-68777404753c") -> 37db9098-7f00-401d-be6f-68777404753c | BE23: =IFERROR(__xludf.DUMMYFUNCTION("""COMPUTED_VALUE"""),14930.71) -> 14930.71 | BI23: =IFERROR(__xludf.DUMMYFUNCTION("""COMPUTED_VALUE"""),"73df5aae-f42a-49a0-9d8f-616ca6dbebaa") -> 73df5aae-f42a-49a0-9d8f-616ca6dbebaa | BJ23: =IFERROR(__xludf.DUMMYFUNCTION("""COMPUTED_VALUE"""),"019ed119-0d06-7305-887b-bea851e02e7c") -> 019ed119-0d06-7305-887b-bea851e02e7c | BK23: =IFERROR(__xludf.DUMMYFUNCTION("""COMPUTED_VALUE"""),46189.65439814815) -> 46189.654 | BL23: =IFERROR(__xludf.DUMMYFUNCTION("""COMPUTED_VALUE"""),"debit") -> debit | BM23: =IFERROR(__xludf.DUMMYFUNCTION("""COMPUTED_VALUE"""),21409.16) -> 21409.16 | BN23: =IFERROR(__xludf.DUMMYFUNCTION("""COMPUTED_VALUE"""),"lisa") -> lisa | BO23: =IFERROR(__xludf.DUMMYFUNCTION("""COMPUTED_VALUE"""),"b7a59586-5d10-4989-91c2-f2376c7a6ab2") -> b7a59586-5d10-4989-91c2-f2376c7a6ab2 | BP23: =IFERROR(__xludf.DUMMYFUNCTION("""COMPUTED_VALUE"""),"c3704b90-6ee3-4441-a76b-af7641bd865e") -> c3704b90-6ee3-4441-a76b-af7641bd865e | BQ23: =IFERROR(__xludf.DUMMYFUNCTION("""COMPUTED_VALUE"""),"c3704b90-6ee3-4441-a76b-af7641bd865e") -> c3704b90-6ee3-4441-a76b-af7641bd865e | BR23: =IFERROR(__xludf.DUMMYFUNCTION("""COMPUTED_VALUE"""),"28f40f33-1429865569") -> 28f40f33-1429865569 | BS23: =IFERROR(__xludf.DUMMYFUNCTION("""COMPUTED_VALUE"""),21409.16) -> 21409.16 | BT23: =IFERROR(__xludf.DUMMYFUNCTION("""COMPUTED_VALUE"""),"payin") -> payin | BU23: =IFERROR(__xludf.DUMMYFUNCTION("""COMPUTED_VALUE"""),46185.09847222222) -> 46185.098
A24: 73df5aae-f42a-49a0-9d8f-616ca6dbebaa | B24: 019ecf85-8c83-7334-b02c-3507c1e46c82 | C24: 46189.348 | D24: debit | E24: 43516.22 | F24: cash_isa | G24: 9bc00e6b-ce5f-48c5-ae3a-1baabe00f337 | H24: d7cdd0e3-4ed8-45e6-9437-21b31d2214e9 | AD24: =IFERROR(__xludf.DUMMYFUNCTION("""COMPUTED_VALUE"""),"73df5aae-f42a-49a0-9d8f-616ca6dbebaa") -> 73df5aae-f42a-49a0-9d8f-616ca6dbebaa | AE24: =IFERROR(__xludf.DUMMYFUNCTION("""COMPUTED_VALUE"""),"019ecf76-bf63-76d6-aa04-0abf78a5d505") -> 019ecf76-bf63-76d6-aa04-0abf78a5d505 | AF24: =IFERROR(__xludf.DUMMYFUNCTION("""COMPUTED_VALUE"""),46189.337118055555) -> 46189.337 | AG24: =IFERROR(__xludf.DUMMYFUNCTION("""COMPUTED_VALUE"""),"debit") -> debit | AH24: =IFERROR(__xludf.DUMMYFUNCTION("""COMPUTED_VALUE"""),21791.12) -> 21791.12 | AI24: =IFERROR(__xludf.DUMMYFUNCTION("""COMPUTED_VALUE"""),"cash_isa") -> cash_isa | AJ24: =IFERROR(__xludf.DUMMYFUNCTION("""COMPUTED_VALUE"""),"9bc00e6b-ce5f-48c5-ae3a-1baabe00f337") -> 9bc00e6b-ce5f-48c5-ae3a-1baabe00f337 | AK24: =IFERROR(__xludf.DUMMYFUNCTION("""COMPUTED_VALUE"""),"68bf96ba-6b4e-4626-989e-f5394ed71986") -> 68bf96ba-6b4e-4626-989e-f5394ed71986 | AR24: =ROUND(VALUE(AH24),2)&"_"&TRIM(LOWER(AG24)) -> 21791.12_debit | AS24: =IF(AH24="", "", LET(current_amt, ROUND(VALUE(AH24), 2), current_dir, TRIM(LOWER(AG24)), opposite_dir, IF(current_dir="credit", "debit", "credit"), occ, COUNTIFS($AH$3:AH24, AH24, $AG$3:AG24, AG24), opp_total, COUNTIFS($AH$3:$AH$1000, AH24, $AG$3:$AG$1000, opposite_dir), IF(opp_total >= occ, "DROP", "KEEP"))) -> DROP | AU24: =IFERROR(__xludf.DUMMYFUNCTION("""COMPUTED_VALUE"""),"73df5aae-f42a-49a0-9d8f-616ca6dbebaa") -> 73df5aae-f42a-49a0-9d8f-616ca6dbebaa | AV24: =IFERROR(__xludf.DUMMYFUNCTION("""COMPUTED_VALUE"""),"019ed0b1-3052-7f73-9d08-db917a292c59") -> 019ed0b1-3052-7f73-9d08-db917a292c59 | AW24: =IFERROR(__xludf.DUMMYFUNCTION("""COMPUTED_VALUE"""),46189.575625) -> 46189.576 | AX24: =IFERROR(__xludf.DUMMYFUNCTION("""COMPUTED_VALUE"""),"credit") -> credit | AY24: =IFERROR(__xludf.DUMMYFUNCTION("""COMPUTED_VALUE"""),14930.71) -> 14930.71 | AZ24: =IFERROR(__xludf.DUMMYFUNCTION("""COMPUTED_VALUE"""),"cash_isa") -> cash_isa | BA24: =IFERROR(__xludf.DUMMYFUNCTION("""COMPUTED_VALUE"""),"9bc00e6b-ce5f-48c5-ae3a-1baabe00f337") -> 9bc00e6b-ce5f-48c5-ae3a-1baabe00f337 | BB24: =IFERROR(__xludf.DUMMYFUNCTION("""COMPUTED_VALUE"""),"37db9098-7f00-401d-be6f-68777404753c") -> 37db9098-7f00-401d-be6f-68777404753c | BI24: =IFERROR(__xludf.DUMMYFUNCTION("""COMPUTED_VALUE"""),"73df5aae-f42a-49a0-9d8f-616ca6dbebaa") -> 73df5aae-f42a-49a0-9d8f-616ca6dbebaa | BJ24: =IFERROR(__xludf.DUMMYFUNCTION("""COMPUTED_VALUE"""),"019ed124-a6d9-770c-a0e0-67d2a0908bde") -> 019ed124-a6d9-770c-a0e0-67d2a0908bde | BK24: =IFERROR(__xludf.DUMMYFUNCTION("""COMPUTED_VALUE"""),46189.66320601852) -> 46189.663 | BL24: =IFERROR(__xludf.DUMMYFUNCTION("""COMPUTED_VALUE"""),"credit") -> credit | BM24: =IFERROR(__xludf.DUMMYFUNCTION("""COMPUTED_VALUE"""),15800.69) -> 15800.69 | BN24: =IFERROR(__xludf.DUMMYFUNCTION("""COMPUTED_VALUE"""),"lisa") -> lisa | BO24: =IFERROR(__xludf.DUMMYFUNCTION("""COMPUTED_VALUE"""),"b7a59586-5d10-4989-91c2-f2376c7a6ab2") -> b7a59586-5d10-4989-91c2-f2376c7a6ab2 | BP24: =IFERROR(__xludf.DUMMYFUNCTION("""COMPUTED_VALUE"""),"6c7ca4f4-7fef-4b08-8ff8-2f8d2c79a1e2") -> 6c7ca4f4-7fef-4b08-8ff8-2f8d2c79a1e2 | BQ24: =IFERROR(__xludf.DUMMYFUNCTION("""COMPUTED_VALUE"""),"6c7ca4f4-7fef-4b08-8ff8-2f8d2c79a1e2") -> 6c7ca4f4-7fef-4b08-8ff8-2f8d2c79a1e2 | BR24: =IFERROR(__xludf.DUMMYFUNCTION("""COMPUTED_VALUE"""),"CDF50426-712770789") -> CDF50426-712770789 | BS24: =IFERROR(__xludf.DUMMYFUNCTION("""COMPUTED_VALUE"""),15800.69) -> 15800.69 | BT24: =IFERROR(__xludf.DUMMYFUNCTION("""COMPUTED_VALUE"""),"payin") -> payin | BU24: =IFERROR(__xludf.DUMMYFUNCTION("""COMPUTED_VALUE"""),46188.56484953704) -> 46188.565
A25: 73df5aae-f42a-49a0-9d8f-616ca6dbebaa | B25: 019ecf85-cc66-7aff-abb6-e421b907b077 | C25: 46189.349 | D25: credit | E25: 43175.87 | F25: cash_isa | G25: 9bc00e6b-ce5f-48c5-ae3a-1baabe00f337 | H25: c5f9e2a7-273d-4d39-9244-99e807cc62bb | AD25: =IFERROR(__xludf.DUMMYFUNCTION("""COMPUTED_VALUE"""),"73df5aae-f42a-49a0-9d8f-616ca6dbebaa") -> 73df5aae-f42a-49a0-9d8f-616ca6dbebaa | AE25: =IFERROR(__xludf.DUMMYFUNCTION("""COMPUTED_VALUE"""),"019ecf7a-e489-72cd-9b73-1bd7516d5e2f") -> 019ecf7a-e489-72cd-9b73-1bd7516d5e2f | AF25: =IFERROR(__xludf.DUMMYFUNCTION("""COMPUTED_VALUE"""),46189.34025462963) -> 46189.34 | AG25: =IFERROR(__xludf.DUMMYFUNCTION("""COMPUTED_VALUE"""),"credit") -> credit | AH25: =IFERROR(__xludf.DUMMYFUNCTION("""COMPUTED_VALUE"""),51998.41) -> 51998.41 | AI25: =IFERROR(__xludf.DUMMYFUNCTION("""COMPUTED_VALUE"""),"cash_isa") -> cash_isa | AJ25: =IFERROR(__xludf.DUMMYFUNCTION("""COMPUTED_VALUE"""),"9bc00e6b-ce5f-48c5-ae3a-1baabe00f337") -> 9bc00e6b-ce5f-48c5-ae3a-1baabe00f337 | AK25: =IFERROR(__xludf.DUMMYFUNCTION("""COMPUTED_VALUE"""),"205cdd7c-d2ed-4603-9ba0-b085b08ee3ed") -> 205cdd7c-d2ed-4603-9ba0-b085b08ee3ed | AR25: =ROUND(VALUE(AH25),2)&"_"&TRIM(LOWER(AG25)) -> 51998.41_credit | AS25: =IF(AH25="", "", LET(current_amt, ROUND(VALUE(AH25), 2), current_dir, TRIM(LOWER(AG25)), opposite_dir, IF(current_dir="credit", "debit", "credit"), occ, COUNTIFS($AH$3:AH25, AH25, $AG$3:AG25, AG25), opp_total, COUNTIFS($AH$3:$AH$1000, AH25, $AG$3:$AG$1000, opposite_dir), IF(opp_total >= occ, "DROP", "KEEP"))) -> DROP | AU25: =IFERROR(__xludf.DUMMYFUNCTION("""COMPUTED_VALUE"""),"73df5aae-f42a-49a0-9d8f-616ca6dbebaa") -> 73df5aae-f42a-49a0-9d8f-616ca6dbebaa | AV25: =IFERROR(__xludf.DUMMYFUNCTION("""COMPUTED_VALUE"""),"019ed0fa-b1c2-7819-857e-40a98c4e3541") -> 019ed0fa-b1c2-7819-857e-40a98c4e3541 | AW25: =IFERROR(__xludf.DUMMYFUNCTION("""COMPUTED_VALUE"""),46189.631377314814) -> 46189.631 | AX25: =IFERROR(__xludf.DUMMYFUNCTION("""COMPUTED_VALUE"""),"credit") -> credit | AY25: =IFERROR(__xludf.DUMMYFUNCTION("""COMPUTED_VALUE"""),20000.0) -> 20000 | AZ25: =IFERROR(__xludf.DUMMYFUNCTION("""COMPUTED_VALUE"""),"cash_isa") -> cash_isa | BA25: =IFERROR(__xludf.DUMMYFUNCTION("""COMPUTED_VALUE"""),"9bc00e6b-ce5f-48c5-ae3a-1baabe00f337") -> 9bc00e6b-ce5f-48c5-ae3a-1baabe00f337 | BB25: =IFERROR(__xludf.DUMMYFUNCTION("""COMPUTED_VALUE"""),"fc861623-56a0-47e2-bd62-7aa9db1633a8") -> fc861623-56a0-47e2-bd62-7aa9db1633a8 | BI25: =IFERROR(__xludf.DUMMYFUNCTION("""COMPUTED_VALUE"""),"73df5aae-f42a-49a0-9d8f-616ca6dbebaa") -> 73df5aae-f42a-49a0-9d8f-616ca6dbebaa | BJ25: =IFERROR(__xludf.DUMMYFUNCTION("""COMPUTED_VALUE"""),"019ed124-a6d9-770c-a0e0-67d2a0908bde") -> 019ed124-a6d9-770c-a0e0-67d2a0908bde | BK25: =IFERROR(__xludf.DUMMYFUNCTION("""COMPUTED_VALUE"""),46189.66320601852) -> 46189.663 | BL25: =IFERROR(__xludf.DUMMYFUNCTION("""COMPUTED_VALUE"""),"credit") -> credit | BM25: =IFERROR(__xludf.DUMMYFUNCTION("""COMPUTED_VALUE"""),15800.69) -> 15800.69 | BN25: =IFERROR(__xludf.DUMMYFUNCTION("""COMPUTED_VALUE"""),"lisa") -> lisa | BO25: =IFERROR(__xludf.DUMMYFUNCTION("""COMPUTED_VALUE"""),"b7a59586-5d10-4989-91c2-f2376c7a6ab2") -> b7a59586-5d10-4989-91c2-f2376c7a6ab2 | BP25: =IFERROR(__xludf.DUMMYFUNCTION("""COMPUTED_VALUE"""),"6c7ca4f4-7fef-4b08-8ff8-2f8d2c79a1e2") -> 6c7ca4f4-7fef-4b08-8ff8-2f8d2c79a1e2 | BQ25: =IFERROR(__xludf.DUMMYFUNCTION("""COMPUTED_VALUE"""),"6c7ca4f4-7fef-4b08-8ff8-2f8d2c79a1e2") -> 6c7ca4f4-7fef-4b08-8ff8-2f8d2c79a1e2 | BR25: =IFERROR(__xludf.DUMMYFUNCTION("""COMPUTED_VALUE"""),"CDF50426-712770789") -> CDF50426-712770789 | BS25: =IFERROR(__xludf.DUMMYFUNCTION("""COMPUTED_VALUE"""),15800.69) -> 15800.69 | BT25: =IFERROR(__xludf.DUMMYFUNCTION("""COMPUTED_VALUE"""),"payin") -> payin | BU25: =IFERROR(__xludf.DUMMYFUNCTION("""COMPUTED_VALUE"""),46188.56484953704) -> 46188.565
A26: 73df5aae-f42a-49a0-9d8f-616ca6dbebaa | B26: 019ecf86-7090-7d46-93ff-eadf6515cf6a | C26: 46189.349 | D26: debit | E26: 33950.32 | F26: cash_isa | G26: 9bc00e6b-ce5f-48c5-ae3a-1baabe00f337 | H26: b62bdbfd-3364-49ee-bdea-86f10c50c819 | AD26: =IFERROR(__xludf.DUMMYFUNCTION("""COMPUTED_VALUE"""),"73df5aae-f42a-49a0-9d8f-616ca6dbebaa") -> 73df5aae-f42a-49a0-9d8f-616ca6dbebaa | AE26: =IFERROR(__xludf.DUMMYFUNCTION("""COMPUTED_VALUE"""),"019ecf7c-55ad-7427-9bb9-58b36cfaddae") -> 019ecf7c-55ad-7427-9bb9-58b36cfaddae | AF26: =IFERROR(__xludf.DUMMYFUNCTION("""COMPUTED_VALUE"""),46189.34135416667) -> 46189.341 | AG26: =IFERROR(__xludf.DUMMYFUNCTION("""COMPUTED_VALUE"""),"debit") -> debit | AH26: =IFERROR(__xludf.DUMMYFUNCTION("""COMPUTED_VALUE"""),51998.41) -> 51998.41 | AI26: =IFERROR(__xludf.DUMMYFUNCTION("""COMPUTED_VALUE"""),"cash_isa") -> cash_isa | AJ26: =IFERROR(__xludf.DUMMYFUNCTION("""COMPUTED_VALUE"""),"9bc00e6b-ce5f-48c5-ae3a-1baabe00f337") -> 9bc00e6b-ce5f-48c5-ae3a-1baabe00f337 | AK26: =IFERROR(__xludf.DUMMYFUNCTION("""COMPUTED_VALUE"""),"205cdd7c-d2ed-4603-9ba0-b085b08ee3ed") -> 205cdd7c-d2ed-4603-9ba0-b085b08ee3ed | AR26: =ROUND(VALUE(AH26),2)&"_"&TRIM(LOWER(AG26)) -> 51998.41_debit | AS26: =IF(AH26="", "", LET(current_amt, ROUND(VALUE(AH26), 2), current_dir, TRIM(LOWER(AG26)), opposite_dir, IF(current_dir="credit", "debit", "credit"), occ, COUNTIFS($AH$3:AH26, AH26, $AG$3:AG26, AG26), opp_total, COUNTIFS($AH$3:$AH$1000, AH26, $AG$3:$AG$1000, opposite_dir), IF(opp_total >= occ, "DROP", "KEEP"))) -> DROP | AU26: =IFERROR(__xludf.DUMMYFUNCTION("""COMPUTED_VALUE"""),"73df5aae-f42a-49a0-9d8f-616ca6dbebaa") -> 73df5aae-f42a-49a0-9d8f-616ca6dbebaa | AV26: =IFERROR(__xludf.DUMMYFUNCTION("""COMPUTED_VALUE"""),"019ed113-db36-7cc1-bf1f-f2778d3e3a69") -> 019ed113-db36-7cc1-bf1f-f2778d3e3a69 | AW26: =IFERROR(__xludf.DUMMYFUNCTION("""COMPUTED_VALUE"""),46189.65046296296) -> 46189.65 | AX26: =IFERROR(__xludf.DUMMYFUNCTION("""COMPUTED_VALUE"""),"debit") -> debit | AY26: =IFERROR(__xludf.DUMMYFUNCTION("""COMPUTED_VALUE"""),21672.66) -> 21672.66 | AZ26: =IFERROR(__xludf.DUMMYFUNCTION("""COMPUTED_VALUE"""),"cash_isa") -> cash_isa | BA26: =IFERROR(__xludf.DUMMYFUNCTION("""COMPUTED_VALUE"""),"9bc00e6b-ce5f-48c5-ae3a-1baabe00f337") -> 9bc00e6b-ce5f-48c5-ae3a-1baabe00f337 | BB26: =IFERROR(__xludf.DUMMYFUNCTION("""COMPUTED_VALUE"""),"98dfe598-22b1-4ae2-919c-cdeeecf42108") -> 98dfe598-22b1-4ae2-919c-cdeeecf42108 | BC26: =IFERROR(__xludf.DUMMYFUNCTION("""COMPUTED_VALUE"""),"98dfe598-22b1-4ae2-919c-cdeeecf42108") -> 98dfe598-22b1-4ae2-919c-cdeeecf42108 | BD26: =IFERROR(__xludf.DUMMYFUNCTION("""COMPUTED_VALUE"""),"NOREF-2119575534") -> NOREF-2119575534 | BE26: =IFERROR(__xludf.DUMMYFUNCTION("""COMPUTED_VALUE"""),21672.66) -> 21672.66 | BF26: =IFERROR(__xludf.DUMMYFUNCTION("""COMPUTED_VALUE"""),"payin") -> payin | BG26: =IFERROR(__xludf.DUMMYFUNCTION("""COMPUTED_VALUE"""),46153.67741898148) -> 46153.677 | BI26: =IFERROR(__xludf.DUMMYFUNCTION("""COMPUTED_VALUE"""),"73df5aae-f42a-49a0-9d8f-616ca6dbebaa") -> 73df5aae-f42a-49a0-9d8f-616ca6dbebaa | BJ26: =IFERROR(__xludf.DUMMYFUNCTION("""COMPUTED_VALUE"""),"019ed129-5b0c-7dce-adaa-6bdb0e9e7e19") -> 019ed129-5b0c-7dce-adaa-6bdb0e9e7e19 | BK26: =IFERROR(__xludf.DUMMYFUNCTION("""COMPUTED_VALUE"""),46189.66677083333) -> 46189.667 | BL26: =IFERROR(__xludf.DUMMYFUNCTION("""COMPUTED_VALUE"""),"debit") -> debit | BM26: =IFERROR(__xludf.DUMMYFUNCTION("""COMPUTED_VALUE"""),1000.44) -> 1000.44 | BN26: =IFERROR(__xludf.DUMMYFUNCTION("""COMPUTED_VALUE"""),"lisa") -> lisa | BO26: =IFERROR(__xludf.DUMMYFUNCTION("""COMPUTED_VALUE"""),"b7a59586-5d10-4989-91c2-f2376c7a6ab2") -> b7a59586-5d10-4989-91c2-f2376c7a6ab2 | BP26: =IFERROR(__xludf.DUMMYFUNCTION("""COMPUTED_VALUE"""),"0007e97e-74a0-43ac-b3f7-38fcfed1342d") -> 0007e97e-74a0-43ac-b3f7-38fcfed1342d | BQ26: =IFERROR(__xludf.DUMMYFUNCTION("""COMPUTED_VALUE"""),"0007e97e-74a0-43ac-b3f7-38fcfed1342d") -> 0007e97e-74a0-43ac-b3f7-38fcfed1342d | BR26: =IFERROR(__xludf.DUMMYFUNCTION("""COMPUTED_VALUE"""),"NOREF-1430831478") -> NOREF-1430831478 | BS26: =IFERROR(__xludf.DUMMYFUNCTION("""COMPUTED_VALUE"""),1000.44) -> 1000.44 | BT26: =IFERROR(__xludf.DUMMYFUNCTION("""COMPUTED_VALUE"""),"payin") -> payin | BU26: =IFERROR(__xludf.DUMMYFUNCTION("""COMPUTED_VALUE"""),46183.41357638889) -> 46183.414
A27: 73df5aae-f42a-49a0-9d8f-616ca6dbebaa | B27: 019ecf88-6644-7bb9-ad1c-7b69816bf46a | C27: 46189.35 | D27: credit | E27: 20619.97 | F27: cash_isa | G27: 9bc00e6b-ce5f-48c5-ae3a-1baabe00f337 | H27: 8b616f8a-bd8e-41d8-90df-75136e898d98 | AD27: =IFERROR(__xludf.DUMMYFUNCTION("""COMPUTED_VALUE"""),"73df5aae-f42a-49a0-9d8f-616ca6dbebaa") -> 73df5aae-f42a-49a0-9d8f-616ca6dbebaa | AE27: =IFERROR(__xludf.DUMMYFUNCTION("""COMPUTED_VALUE"""),"019ecf7e-7e01-76e2-ad1b-8a434ab054a0") -> 019ecf7e-7e01-76e2-ad1b-8a434ab054a0 | AF27: =IFERROR(__xludf.DUMMYFUNCTION("""COMPUTED_VALUE"""),46189.34298611111) -> 46189.343 | AG27: =IFERROR(__xludf.DUMMYFUNCTION("""COMPUTED_VALUE"""),"credit") -> credit | AH27: =IFERROR(__xludf.DUMMYFUNCTION("""COMPUTED_VALUE"""),41.57) -> 41.57 | AI27: =IFERROR(__xludf.DUMMYFUNCTION("""COMPUTED_VALUE"""),"cash_isa") -> cash_isa | AJ27: =IFERROR(__xludf.DUMMYFUNCTION("""COMPUTED_VALUE"""),"9bc00e6b-ce5f-48c5-ae3a-1baabe00f337") -> 9bc00e6b-ce5f-48c5-ae3a-1baabe00f337 | AK27: =IFERROR(__xludf.DUMMYFUNCTION("""COMPUTED_VALUE"""),"5d9ab65f-d47d-440b-86fc-aada0df5983e") -> 5d9ab65f-d47d-440b-86fc-aada0df5983e | AR27: =ROUND(VALUE(AH27),2)&"_"&TRIM(LOWER(AG27)) -> 41.57_credit | AS27: =IF(AH27="", "", LET(current_amt, ROUND(VALUE(AH27), 2), current_dir, TRIM(LOWER(AG27)), opposite_dir, IF(current_dir="credit", "debit", "credit"), occ, COUNTIFS($AH$3:AH27, AH27, $AG$3:AG27, AG27), opp_total, COUNTIFS($AH$3:$AH$1000, AH27, $AG$3:$AG$1000, opposite_dir), IF(opp_total >= occ, "DROP", "KEEP"))) -> DROP
A28: 73df5aae-f42a-49a0-9d8f-616ca6dbebaa | B28: 019ecf88-dd66-75bc-a72c-3d4ed0285cd1 | C28: 46189.351 | D28: debit | E28: 43175.87 | F28: cash_isa | G28: 9bc00e6b-ce5f-48c5-ae3a-1baabe00f337 | H28: c5f9e2a7-273d-4d39-9244-99e807cc62bb | AD28: =IFERROR(__xludf.DUMMYFUNCTION("""COMPUTED_VALUE"""),"73df5aae-f42a-49a0-9d8f-616ca6dbebaa") -> 73df5aae-f42a-49a0-9d8f-616ca6dbebaa | AE28: =IFERROR(__xludf.DUMMYFUNCTION("""COMPUTED_VALUE"""),"019ecf7f-4053-7b98-956f-d28b77a4465d") -> 019ecf7f-4053-7b98-956f-d28b77a4465d | AF28: =IFERROR(__xludf.DUMMYFUNCTION("""COMPUTED_VALUE"""),46189.343564814815) -> 46189.344 | AG28: =IFERROR(__xludf.DUMMYFUNCTION("""COMPUTED_VALUE"""),"credit") -> credit | AH28: =IFERROR(__xludf.DUMMYFUNCTION("""COMPUTED_VALUE"""),64323.91) -> 64323.91 | AI28: =IFERROR(__xludf.DUMMYFUNCTION("""COMPUTED_VALUE"""),"cash_isa") -> cash_isa | AJ28: =IFERROR(__xludf.DUMMYFUNCTION("""COMPUTED_VALUE"""),"9bc00e6b-ce5f-48c5-ae3a-1baabe00f337") -> 9bc00e6b-ce5f-48c5-ae3a-1baabe00f337 | AK28: =IFERROR(__xludf.DUMMYFUNCTION("""COMPUTED_VALUE"""),"0e6bf5a2-5f83-4dba-882b-f61da8185090") -> 0e6bf5a2-5f83-4dba-882b-f61da8185090 | AR28: =ROUND(VALUE(AH28),2)&"_"&TRIM(LOWER(AG28)) -> 64323.91_credit | AS28: =IF(AH28="", "", LET(current_amt, ROUND(VALUE(AH28), 2), current_dir, TRIM(LOWER(AG28)), opposite_dir, IF(current_dir="credit", "debit", "credit"), occ, COUNTIFS($AH$3:AH28, AH28, $AG$3:AG28, AG28), opp_total, COUNTIFS($AH$3:$AH$1000, AH28, $AG$3:$AG$1000, opposite_dir), IF(opp_total >= occ, "DROP", "KEEP"))) -> DROP
A29: 73df5aae-f42a-49a0-9d8f-616ca6dbebaa | B29: 019ecf89-311d-7d31-a446-1a62bd0f20e0 | C29: 46189.351 | D29: credit | E29: 41791.17 | F29: cash_isa | G29: 9bc00e6b-ce5f-48c5-ae3a-1baabe00f337 | H29: 845dcc7b-e80c-47ba-978d-eaf51da59982 | AD29: =IFERROR(__xludf.DUMMYFUNCTION("""COMPUTED_VALUE"""),"73df5aae-f42a-49a0-9d8f-616ca6dbebaa") -> 73df5aae-f42a-49a0-9d8f-616ca6dbebaa | AE29: =IFERROR(__xludf.DUMMYFUNCTION("""COMPUTED_VALUE"""),"019ecf80-33b1-7893-b131-a45c80eb3ade") -> 019ecf80-33b1-7893-b131-a45c80eb3ade | AF29: =IFERROR(__xludf.DUMMYFUNCTION("""COMPUTED_VALUE"""),46189.34428240741) -> 46189.344 | AG29: =IFERROR(__xludf.DUMMYFUNCTION("""COMPUTED_VALUE"""),"debit") -> debit | AH29: =IFERROR(__xludf.DUMMYFUNCTION("""COMPUTED_VALUE"""),41.57) -> 41.57 | AI29: =IFERROR(__xludf.DUMMYFUNCTION("""COMPUTED_VALUE"""),"cash_isa") -> cash_isa | AJ29: =IFERROR(__xludf.DUMMYFUNCTION("""COMPUTED_VALUE"""),"9bc00e6b-ce5f-48c5-ae3a-1baabe00f337") -> 9bc00e6b-ce5f-48c5-ae3a-1baabe00f337 | AK29: =IFERROR(__xludf.DUMMYFUNCTION("""COMPUTED_VALUE"""),"5d9ab65f-d47d-440b-86fc-aada0df5983e") -> 5d9ab65f-d47d-440b-86fc-aada0df5983e | AR29: =ROUND(VALUE(AH29),2)&"_"&TRIM(LOWER(AG29)) -> 41.57_debit | AS29: =IF(AH29="", "", LET(current_amt, ROUND(VALUE(AH29), 2), current_dir, TRIM(LOWER(AG29)), opposite_dir, IF(current_dir="credit", "debit", "credit"), occ, COUNTIFS($AH$3:AH29, AH29, $AG$3:AG29, AG29), opp_total, COUNTIFS($AH$3:$AH$1000, AH29, $AG$3:$AG$1000, opposite_dir), IF(opp_total >= occ, "DROP", "KEEP"))) -> DROP
A30: 73df5aae-f42a-49a0-9d8f-616ca6dbebaa | B30: 019ecf8a-5132-7f8f-a6e1-5446a97d8314 | C30: 46189.352 | D30: debit | E30: 41791.17 | F30: cash_isa | G30: 9bc00e6b-ce5f-48c5-ae3a-1baabe00f337 | H30: 845dcc7b-e80c-47ba-978d-eaf51da59982 | AD30: =IFERROR(__xludf.DUMMYFUNCTION("""COMPUTED_VALUE"""),"73df5aae-f42a-49a0-9d8f-616ca6dbebaa") -> 73df5aae-f42a-49a0-9d8f-616ca6dbebaa | AE30: =IFERROR(__xludf.DUMMYFUNCTION("""COMPUTED_VALUE"""),"019ecf81-99d5-7b76-843e-8be19854b4e5") -> 019ecf81-99d5-7b76-843e-8be19854b4e5 | AF30: =IFERROR(__xludf.DUMMYFUNCTION("""COMPUTED_VALUE"""),46189.34534722222) -> 46189.345 | AG30: =IFERROR(__xludf.DUMMYFUNCTION("""COMPUTED_VALUE"""),"credit") -> credit | AH30: =IFERROR(__xludf.DUMMYFUNCTION("""COMPUTED_VALUE"""),5983.9) -> 5983.9 | AI30: =IFERROR(__xludf.DUMMYFUNCTION("""COMPUTED_VALUE"""),"cash_isa") -> cash_isa | AJ30: =IFERROR(__xludf.DUMMYFUNCTION("""COMPUTED_VALUE"""),"9bc00e6b-ce5f-48c5-ae3a-1baabe00f337") -> 9bc00e6b-ce5f-48c5-ae3a-1baabe00f337 | AK30: =IFERROR(__xludf.DUMMYFUNCTION("""COMPUTED_VALUE"""),"c2e67f69-0639-42c8-ad6e-b466688be698") -> c2e67f69-0639-42c8-ad6e-b466688be698 | AR30: =ROUND(VALUE(AH30),2)&"_"&TRIM(LOWER(AG30)) -> 5983.9_credit | AS30: =IF(AH30="", "", LET(current_amt, ROUND(VALUE(AH30), 2), current_dir, TRIM(LOWER(AG30)), opposite_dir, IF(current_dir="credit", "debit", "credit"), occ, COUNTIFS($AH$3:AH30, AH30, $AG$3:AG30, AG30), opp_total, COUNTIFS($AH$3:$AH$1000, AH30, $AG$3:$AG$1000, opposite_dir), IF(opp_total >= occ, "DROP", "KEEP"))) -> DROP
A31: 73df5aae-f42a-49a0-9d8f-616ca6dbebaa | B31: 019ecf8a-53f3-7688-812f-62e1e9ae6177 | C31: 46189.352 | D31: debit | E31: 20619.97 | F31: cash_isa | G31: 9bc00e6b-ce5f-48c5-ae3a-1baabe00f337 | H31: 8b616f8a-bd8e-41d8-90df-75136e898d98 | AD31: =IFERROR(__xludf.DUMMYFUNCTION("""COMPUTED_VALUE"""),"73df5aae-f42a-49a0-9d8f-616ca6dbebaa") -> 73df5aae-f42a-49a0-9d8f-616ca6dbebaa | AE31: =IFERROR(__xludf.DUMMYFUNCTION("""COMPUTED_VALUE"""),"019ecf82-6586-7984-9b18-d51401b605bd") -> 019ecf82-6586-7984-9b18-d51401b605bd | AF31: =IFERROR(__xludf.DUMMYFUNCTION("""COMPUTED_VALUE"""),46189.34594907408) -> 46189.346 | AG31: =IFERROR(__xludf.DUMMYFUNCTION("""COMPUTED_VALUE"""),"debit") -> debit | AH31: =IFERROR(__xludf.DUMMYFUNCTION("""COMPUTED_VALUE"""),64323.91) -> 64323.91 | AI31: =IFERROR(__xludf.DUMMYFUNCTION("""COMPUTED_VALUE"""),"cash_isa") -> cash_isa | AJ31: =IFERROR(__xludf.DUMMYFUNCTION("""COMPUTED_VALUE"""),"9bc00e6b-ce5f-48c5-ae3a-1baabe00f337") -> 9bc00e6b-ce5f-48c5-ae3a-1baabe00f337 | AK31: =IFERROR(__xludf.DUMMYFUNCTION("""COMPUTED_VALUE"""),"0e6bf5a2-5f83-4dba-882b-f61da8185090") -> 0e6bf5a2-5f83-4dba-882b-f61da8185090 | AR31: =ROUND(VALUE(AH31),2)&"_"&TRIM(LOWER(AG31)) -> 64323.91_debit | AS31: =IF(AH31="", "", LET(current_amt, ROUND(VALUE(AH31), 2), current_dir, TRIM(LOWER(AG31)), opposite_dir, IF(current_dir="credit", "debit", "credit"), occ, COUNTIFS($AH$3:AH31, AH31, $AG$3:AG31, AG31), opp_total, COUNTIFS($AH$3:$AH$1000, AH31, $AG$3:$AG$1000, opposite_dir), IF(opp_total >= occ, "DROP", "KEEP"))) -> DROP
A32: 73df5aae-f42a-49a0-9d8f-616ca6dbebaa | B32: 019ecf8a-bd53-71e8-baeb-d5cc3ee5c011 | C32: 46189.352 | D32: credit | E32: 20902.73 | F32: cash_isa | G32: 9bc00e6b-ce5f-48c5-ae3a-1baabe00f337 | H32: 0ca1b8b4-66c3-47cf-9239-c860dddc4cc9 | AD32: =IFERROR(__xludf.DUMMYFUNCTION("""COMPUTED_VALUE"""),"73df5aae-f42a-49a0-9d8f-616ca6dbebaa") -> 73df5aae-f42a-49a0-9d8f-616ca6dbebaa | AE32: =IFERROR(__xludf.DUMMYFUNCTION("""COMPUTED_VALUE"""),"019ecf82-dc4b-7660-bc65-34689d6a0cb5") -> 019ecf82-dc4b-7660-bc65-34689d6a0cb5 | AF32: =IFERROR(__xludf.DUMMYFUNCTION("""COMPUTED_VALUE"""),46189.346296296295) -> 46189.346 | AG32: =IFERROR(__xludf.DUMMYFUNCTION("""COMPUTED_VALUE"""),"debit") -> debit | AH32: =IFERROR(__xludf.DUMMYFUNCTION("""COMPUTED_VALUE"""),5983.9) -> 5983.9 | AI32: =IFERROR(__xludf.DUMMYFUNCTION("""COMPUTED_VALUE"""),"cash_isa") -> cash_isa | AJ32: =IFERROR(__xludf.DUMMYFUNCTION("""COMPUTED_VALUE"""),"9bc00e6b-ce5f-48c5-ae3a-1baabe00f337") -> 9bc00e6b-ce5f-48c5-ae3a-1baabe00f337 | AK32: =IFERROR(__xludf.DUMMYFUNCTION("""COMPUTED_VALUE"""),"c2e67f69-0639-42c8-ad6e-b466688be698") -> c2e67f69-0639-42c8-ad6e-b466688be698 | AR32: =ROUND(VALUE(AH32),2)&"_"&TRIM(LOWER(AG32)) -> 5983.9_debit | AS32: =IF(AH32="", "", LET(current_amt, ROUND(VALUE(AH32), 2), current_dir, TRIM(LOWER(AG32)), opposite_dir, IF(current_dir="credit", "debit", "credit"), occ, COUNTIFS($AH$3:AH32, AH32, $AG$3:AG32, AG32), opp_total, COUNTIFS($AH$3:$AH$1000, AH32, $AG$3:$AG$1000, opposite_dir), IF(opp_total >= occ, "DROP", "KEEP"))) -> DROP
A33: 73df5aae-f42a-49a0-9d8f-616ca6dbebaa | B33: 019ecf8b-0bd9-7b32-9575-e7e5238114eb | C33: 46189.353 | D33: credit | E33: 42620.95 | F33: cash_isa | G33: 9bc00e6b-ce5f-48c5-ae3a-1baabe00f337 | H33: 1162a08c-59f0-42e2-9c3a-dc7b5d58bef3 | AD33: =IFERROR(__xludf.DUMMYFUNCTION("""COMPUTED_VALUE"""),"73df5aae-f42a-49a0-9d8f-616ca6dbebaa") -> 73df5aae-f42a-49a0-9d8f-616ca6dbebaa | AE33: =IFERROR(__xludf.DUMMYFUNCTION("""COMPUTED_VALUE"""),"019ecf84-2564-7568-86d7-f5bc38db90ce") -> 019ecf84-2564-7568-86d7-f5bc38db90ce | AF33: =IFERROR(__xludf.DUMMYFUNCTION("""COMPUTED_VALUE"""),46189.347280092596) -> 46189.347 | AG33: =IFERROR(__xludf.DUMMYFUNCTION("""COMPUTED_VALUE"""),"credit") -> credit | AH33: =IFERROR(__xludf.DUMMYFUNCTION("""COMPUTED_VALUE"""),43516.22) -> 43516.22 | AI33: =IFERROR(__xludf.DUMMYFUNCTION("""COMPUTED_VALUE"""),"cash_isa") -> cash_isa | AJ33: =IFERROR(__xludf.DUMMYFUNCTION("""COMPUTED_VALUE"""),"9bc00e6b-ce5f-48c5-ae3a-1baabe00f337") -> 9bc00e6b-ce5f-48c5-ae3a-1baabe00f337 | AK33: =IFERROR(__xludf.DUMMYFUNCTION("""COMPUTED_VALUE"""),"d7cdd0e3-4ed8-45e6-9437-21b31d2214e9") -> d7cdd0e3-4ed8-45e6-9437-21b31d2214e9 | AR33: =ROUND(VALUE(AH33),2)&"_"&TRIM(LOWER(AG33)) -> 43516.22_credit | AS33: =IF(AH33="", "", LET(current_amt, ROUND(VALUE(AH33), 2), current_dir, TRIM(LOWER(AG33)), opposite_dir, IF(current_dir="credit", "debit", "credit"), occ, COUNTIFS($AH$3:AH33, AH33, $AG$3:AG33, AG33), opp_total, COUNTIFS($AH$3:$AH$1000, AH33, $AG$3:$AG$1000, opposite_dir), IF(opp_total >= occ, "DROP", "KEEP"))) -> DROP
A34: 73df5aae-f42a-49a0-9d8f-616ca6dbebaa | B34: 019ecf8c-1110-78f0-aa0c-9d38f0eb2166 | C34: 46189.353 | D34: credit | E34: 21429.12 | F34: cash_isa | G34: 9bc00e6b-ce5f-48c5-ae3a-1baabe00f337 | H34: 5500a291-d4a3-4c20-8f81-385002437c7b | AD34: =IFERROR(__xludf.DUMMYFUNCTION("""COMPUTED_VALUE"""),"73df5aae-f42a-49a0-9d8f-616ca6dbebaa") -> 73df5aae-f42a-49a0-9d8f-616ca6dbebaa | AE34: =IFERROR(__xludf.DUMMYFUNCTION("""COMPUTED_VALUE"""),"019ecf85-3437-7732-9d69-781ef136ee47") -> 019ecf85-3437-7732-9d69-781ef136ee47 | AF34: =IFERROR(__xludf.DUMMYFUNCTION("""COMPUTED_VALUE"""),46189.348078703704) -> 46189.348 | AG34: =IFERROR(__xludf.DUMMYFUNCTION("""COMPUTED_VALUE"""),"credit") -> credit | AH34: =IFERROR(__xludf.DUMMYFUNCTION("""COMPUTED_VALUE"""),33950.32) -> 33950.32 | AI34: =IFERROR(__xludf.DUMMYFUNCTION("""COMPUTED_VALUE"""),"cash_isa") -> cash_isa | AJ34: =IFERROR(__xludf.DUMMYFUNCTION("""COMPUTED_VALUE"""),"9bc00e6b-ce5f-48c5-ae3a-1baabe00f337") -> 9bc00e6b-ce5f-48c5-ae3a-1baabe00f337 | AK34: =IFERROR(__xludf.DUMMYFUNCTION("""COMPUTED_VALUE"""),"b62bdbfd-3364-49ee-bdea-86f10c50c819") -> b62bdbfd-3364-49ee-bdea-86f10c50c819 | AR34: =ROUND(VALUE(AH34),2)&"_"&TRIM(LOWER(AG34)) -> 33950.32_credit | AS34: =IF(AH34="", "", LET(current_amt, ROUND(VALUE(AH34), 2), current_dir, TRIM(LOWER(AG34)), opposite_dir, IF(current_dir="credit", "debit", "credit"), occ, COUNTIFS($AH$3:AH34, AH34, $AG$3:AG34, AG34), opp_total, COUNTIFS($AH$3:$AH$1000, AH34, $AG$3:$AG$1000, opposite_dir), IF(opp_total >= occ, "DROP", "KEEP"))) -> DROP
A35: 73df5aae-f42a-49a0-9d8f-616ca6dbebaa | B35: 019ecf8c-3fa7-7dfe-beb5-d12f795a9f26 | C35: 46189.353 | D35: debit | E35: 20902.73 | F35: cash_isa | G35: 9bc00e6b-ce5f-48c5-ae3a-1baabe00f337 | H35: 0ca1b8b4-66c3-47cf-9239-c860dddc4cc9 | AD35: =IFERROR(__xludf.DUMMYFUNCTION("""COMPUTED_VALUE"""),"73df5aae-f42a-49a0-9d8f-616ca6dbebaa") -> 73df5aae-f42a-49a0-9d8f-616ca6dbebaa | AE35: =IFERROR(__xludf.DUMMYFUNCTION("""COMPUTED_VALUE"""),"019ecf85-8c83-7334-b02c-3507c1e46c82") -> 019ecf85-8c83-7334-b02c-3507c1e46c82 | AF35: =IFERROR(__xludf.DUMMYFUNCTION("""COMPUTED_VALUE"""),46189.34834490741) -> 46189.348 | AG35: =IFERROR(__xludf.DUMMYFUNCTION("""COMPUTED_VALUE"""),"debit") -> debit | AH35: =IFERROR(__xludf.DUMMYFUNCTION("""COMPUTED_VALUE"""),43516.22) -> 43516.22 | AI35: =IFERROR(__xludf.DUMMYFUNCTION("""COMPUTED_VALUE"""),"cash_isa") -> cash_isa | AJ35: =IFERROR(__xludf.DUMMYFUNCTION("""COMPUTED_VALUE"""),"9bc00e6b-ce5f-48c5-ae3a-1baabe00f337") -> 9bc00e6b-ce5f-48c5-ae3a-1baabe00f337 | AK35: =IFERROR(__xludf.DUMMYFUNCTION("""COMPUTED_VALUE"""),"d7cdd0e3-4ed8-45e6-9437-21b31d2214e9") -> d7cdd0e3-4ed8-45e6-9437-21b31d2214e9 | AR35: =ROUND(VALUE(AH35),2)&"_"&TRIM(LOWER(AG35)) -> 43516.22_debit | AS35: =IF(AH35="", "", LET(current_amt, ROUND(VALUE(AH35), 2), current_dir, TRIM(LOWER(AG35)), opposite_dir, IF(current_dir="credit", "debit", "credit"), occ, COUNTIFS($AH$3:AH35, AH35, $AG$3:AG35, AG35), opp_total, COUNTIFS($AH$3:$AH$1000, AH35, $AG$3:$AG$1000, opposite_dir), IF(opp_total >= occ, "DROP", "KEEP"))) -> DROP
A36: 73df5aae-f42a-49a0-9d8f-616ca6dbebaa | B36: 019ecf8d-3769-76ca-b384-c2cb88dd928a | C36: 46189.354 | D36: debit | E36: 42620.95 | F36: cash_isa | G36: 9bc00e6b-ce5f-48c5-ae3a-1baabe00f337 | H36: 1162a08c-59f0-42e2-9c3a-dc7b5d58bef3 | AD36: =IFERROR(__xludf.DUMMYFUNCTION("""COMPUTED_VALUE"""),"73df5aae-f42a-49a0-9d8f-616ca6dbebaa") -> 73df5aae-f42a-49a0-9d8f-616ca6dbebaa | AE36: =IFERROR(__xludf.DUMMYFUNCTION("""COMPUTED_VALUE"""),"019ecf85-cc66-7aff-abb6-e421b907b077") -> 019ecf85-cc66-7aff-abb6-e421b907b077 | AF36: =IFERROR(__xludf.DUMMYFUNCTION("""COMPUTED_VALUE"""),46189.3485300926) -> 46189.349 | AG36: =IFERROR(__xludf.DUMMYFUNCTION("""COMPUTED_VALUE"""),"credit") -> credit | AH36: =IFERROR(__xludf.DUMMYFUNCTION("""COMPUTED_VALUE"""),43175.87) -> 43175.87 | AI36: =IFERROR(__xludf.DUMMYFUNCTION("""COMPUTED_VALUE"""),"cash_isa") -> cash_isa | AJ36: =IFERROR(__xludf.DUMMYFUNCTION("""COMPUTED_VALUE"""),"9bc00e6b-ce5f-48c5-ae3a-1baabe00f337") -> 9bc00e6b-ce5f-48c5-ae3a-1baabe00f337 | AK36: =IFERROR(__xludf.DUMMYFUNCTION("""COMPUTED_VALUE"""),"c5f9e2a7-273d-4d39-9244-99e807cc62bb") -> c5f9e2a7-273d-4d39-9244-99e807cc62bb | AR36: =ROUND(VALUE(AH36),2)&"_"&TRIM(LOWER(AG36)) -> 43175.87_credit | AS36: =IF(AH36="", "", LET(current_amt, ROUND(VALUE(AH36), 2), current_dir, TRIM(LOWER(AG36)), opposite_dir, IF(current_dir="credit", "debit", "credit"), occ, COUNTIFS($AH$3:AH36, AH36, $AG$3:AG36, AG36), opp_total, COUNTIFS($AH$3:$AH$1000, AH36, $AG$3:$AG$1000, opposite_dir), IF(opp_total >= occ, "DROP", "KEEP"))) -> DROP
A37: 73df5aae-f42a-49a0-9d8f-616ca6dbebaa | B37: 019ecf8d-42ca-73b4-9e10-9485842d30d5 | C37: 46189.354 | D37: credit | E37: 30124.06 | F37: cash_isa | G37: 9bc00e6b-ce5f-48c5-ae3a-1baabe00f337 | H37: 0b60b1f8-e681-4814-9643-b035fc4c3e8c | AD37: =IFERROR(__xludf.DUMMYFUNCTION("""COMPUTED_VALUE"""),"73df5aae-f42a-49a0-9d8f-616ca6dbebaa") -> 73df5aae-f42a-49a0-9d8f-616ca6dbebaa | AE37: =IFERROR(__xludf.DUMMYFUNCTION("""COMPUTED_VALUE"""),"019ecf86-7090-7d46-93ff-eadf6515cf6a") -> 019ecf86-7090-7d46-93ff-eadf6515cf6a | AF37: =IFERROR(__xludf.DUMMYFUNCTION("""COMPUTED_VALUE"""),46189.349016203705) -> 46189.349 | AG37: =IFERROR(__xludf.DUMMYFUNCTION("""COMPUTED_VALUE"""),"debit") -> debit | AH37: =IFERROR(__xludf.DUMMYFUNCTION("""COMPUTED_VALUE"""),33950.32) -> 33950.32 | AI37: =IFERROR(__xludf.DUMMYFUNCTION("""COMPUTED_VALUE"""),"cash_isa") -> cash_isa | AJ37: =IFERROR(__xludf.DUMMYFUNCTION("""COMPUTED_VALUE"""),"9bc00e6b-ce5f-48c5-ae3a-1baabe00f337") -> 9bc00e6b-ce5f-48c5-ae3a-1baabe00f337 | AK37: =IFERROR(__xludf.DUMMYFUNCTION("""COMPUTED_VALUE"""),"b62bdbfd-3364-49ee-bdea-86f10c50c819") -> b62bdbfd-3364-49ee-bdea-86f10c50c819 | AR37: =ROUND(VALUE(AH37),2)&"_"&TRIM(LOWER(AG37)) -> 33950.32_debit | AS37: =IF(AH37="", "", LET(current_amt, ROUND(VALUE(AH37), 2), current_dir, TRIM(LOWER(AG37)), opposite_dir, IF(current_dir="credit", "debit", "credit"), occ, COUNTIFS($AH$3:AH37, AH37, $AG$3:AG37, AG37), opp_total, COUNTIFS($AH$3:$AH$1000, AH37, $AG$3:$AG$1000, opposite_dir), IF(opp_total >= occ, "DROP", "KEEP"))) -> DROP
A38: 73df5aae-f42a-49a0-9d8f-616ca6dbebaa | B38: 019ecf8e-2d29-7ad4-b61a-380cbb8924fb | C38: 46189.355 | D38: debit | E38: 21429.12 | F38: cash_isa | G38: 9bc00e6b-ce5f-48c5-ae3a-1baabe00f337 | H38: 5500a291-d4a3-4c20-8f81-385002437c7b | AD38: =IFERROR(__xludf.DUMMYFUNCTION("""COMPUTED_VALUE"""),"73df5aae-f42a-49a0-9d8f-616ca6dbebaa") -> 73df5aae-f42a-49a0-9d8f-616ca6dbebaa | AE38: =IFERROR(__xludf.DUMMYFUNCTION("""COMPUTED_VALUE"""),"019ecf88-6644-7bb9-ad1c-7b69816bf46a") -> 019ecf88-6644-7bb9-ad1c-7b69816bf46a | AF38: =IFERROR(__xludf.DUMMYFUNCTION("""COMPUTED_VALUE"""),46189.350497685184) -> 46189.351 | AG38: =IFERROR(__xludf.DUMMYFUNCTION("""COMPUTED_VALUE"""),"credit") -> credit | AH38: =IFERROR(__xludf.DUMMYFUNCTION("""COMPUTED_VALUE"""),20619.97) -> 20619.97 | AI38: =IFERROR(__xludf.DUMMYFUNCTION("""COMPUTED_VALUE"""),"cash_isa") -> cash_isa | AJ38: =IFERROR(__xludf.DUMMYFUNCTION("""COMPUTED_VALUE"""),"9bc00e6b-ce5f-48c5-ae3a-1baabe00f337") -> 9bc00e6b-ce5f-48c5-ae3a-1baabe00f337 | AK38: =IFERROR(__xludf.DUMMYFUNCTION("""COMPUTED_VALUE"""),"8b616f8a-bd8e-41d8-90df-75136e898d98") -> 8b616f8a-bd8e-41d8-90df-75136e898d98 | AR38: =ROUND(VALUE(AH38),2)&"_"&TRIM(LOWER(AG38)) -> 20619.97_credit | AS38: =IF(AH38="", "", LET(current_amt, ROUND(VALUE(AH38), 2), current_dir, TRIM(LOWER(AG38)), opposite_dir, IF(current_dir="credit", "debit", "credit"), occ, COUNTIFS($AH$3:AH38, AH38, $AG$3:AG38, AG38), opp_total, COUNTIFS($AH$3:$AH$1000, AH38, $AG$3:$AG$1000, opposite_dir), IF(opp_total >= occ, "DROP", "KEEP"))) -> DROP
A39: 73df5aae-f42a-49a0-9d8f-616ca6dbebaa | B39: 019ecf8f-25aa-766e-97c7-ca1f7294dff4 | C39: 46189.356 | D39: credit | E39: 15678.39 | F39: cash_isa | G39: 9bc00e6b-ce5f-48c5-ae3a-1baabe00f337 | H39: 14a3d68f-c132-4f17-8952-1c4b7e23fe77 | AD39: =IFERROR(__xludf.DUMMYFUNCTION("""COMPUTED_VALUE"""),"73df5aae-f42a-49a0-9d8f-616ca6dbebaa") -> 73df5aae-f42a-49a0-9d8f-616ca6dbebaa | AE39: =IFERROR(__xludf.DUMMYFUNCTION("""COMPUTED_VALUE"""),"019ecf88-dd66-75bc-a72c-3d4ed0285cd1") -> 019ecf88-dd66-75bc-a72c-3d4ed0285cd1 | AF39: =IFERROR(__xludf.DUMMYFUNCTION("""COMPUTED_VALUE"""),46189.350856481484) -> 46189.351 | AG39: =IFERROR(__xludf.DUMMYFUNCTION("""COMPUTED_VALUE"""),"debit") -> debit | AH39: =IFERROR(__xludf.DUMMYFUNCTION("""COMPUTED_VALUE"""),43175.87) -> 43175.87 | AI39: =IFERROR(__xludf.DUMMYFUNCTION("""COMPUTED_VALUE"""),"cash_isa") -> cash_isa | AJ39: =IFERROR(__xludf.DUMMYFUNCTION("""COMPUTED_VALUE"""),"9bc00e6b-ce5f-48c5-ae3a-1baabe00f337") -> 9bc00e6b-ce5f-48c5-ae3a-1baabe00f337 | AK39: =IFERROR(__xludf.DUMMYFUNCTION("""COMPUTED_VALUE"""),"c5f9e2a7-273d-4d39-9244-99e807cc62bb") -> c5f9e2a7-273d-4d39-9244-99e807cc62bb | AR39: =ROUND(VALUE(AH39),2)&"_"&TRIM(LOWER(AG39)) -> 43175.87_debit | AS39: =IF(AH39="", "", LET(current_amt, ROUND(VALUE(AH39), 2), current_dir, TRIM(LOWER(AG39)), opposite_dir, IF(current_dir="credit", "debit", "credit"), occ, COUNTIFS($AH$3:AH39, AH39, $AG$3:AG39, AG39), opp_total, COUNTIFS($AH$3:$AH$1000, AH39, $AG$3:$AG$1000, opposite_dir), IF(opp_total >= occ, "DROP", "KEEP"))) -> DROP
A40: 73df5aae-f42a-49a0-9d8f-616ca6dbebaa | B40: 019ecf90-396e-705f-9580-362a52fee9e5 | C40: 46189.356 | D40: debit | E40: 30124.06 | F40: cash_isa | G40: 9bc00e6b-ce5f-48c5-ae3a-1baabe00f337 | H40: 0b60b1f8-e681-4814-9643-b035fc4c3e8c | AD40: =IFERROR(__xludf.DUMMYFUNCTION("""COMPUTED_VALUE"""),"73df5aae-f42a-49a0-9d8f-616ca6dbebaa") -> 73df5aae-f42a-49a0-9d8f-616ca6dbebaa | AE40: =IFERROR(__xludf.DUMMYFUNCTION("""COMPUTED_VALUE"""),"019ecf89-311d-7d31-a446-1a62bd0f20e0") -> 019ecf89-311d-7d31-a446-1a62bd0f20e0 | AF40: =IFERROR(__xludf.DUMMYFUNCTION("""COMPUTED_VALUE"""),46189.35109953704) -> 46189.351 | AG40: =IFERROR(__xludf.DUMMYFUNCTION("""COMPUTED_VALUE"""),"credit") -> credit | AH40: =IFERROR(__xludf.DUMMYFUNCTION("""COMPUTED_VALUE"""),41791.17) -> 41791.17 | AI40: =IFERROR(__xludf.DUMMYFUNCTION("""COMPUTED_VALUE"""),"cash_isa") -> cash_isa | AJ40: =IFERROR(__xludf.DUMMYFUNCTION("""COMPUTED_VALUE"""),"9bc00e6b-ce5f-48c5-ae3a-1baabe00f337") -> 9bc00e6b-ce5f-48c5-ae3a-1baabe00f337 | AK40: =IFERROR(__xludf.DUMMYFUNCTION("""COMPUTED_VALUE"""),"845dcc7b-e80c-47ba-978d-eaf51da59982") -> 845dcc7b-e80c-47ba-978d-eaf51da59982 | AR40: =ROUND(VALUE(AH40),2)&"_"&TRIM(LOWER(AG40)) -> 41791.17_credit | AS40: =IF(AH40="", "", LET(current_amt, ROUND(VALUE(AH40), 2), current_dir, TRIM(LOWER(AG40)), opposite_dir, IF(current_dir="credit", "debit", "credit"), occ, COUNTIFS($AH$3:AH40, AH40, $AG$3:AG40, AG40), opp_total, COUNTIFS($AH$3:$AH$1000, AH40, $AG$3:$AG$1000, opposite_dir), IF(opp_total >= occ, "DROP", "KEEP"))) -> DROP
A41: 73df5aae-f42a-49a0-9d8f-616ca6dbebaa | B41: 019ecf91-8372-70ee-9010-f68eefd42fb9 | C41: 46189.357 | D41: debit | E41: 15678.39 | F41: cash_isa | G41: 9bc00e6b-ce5f-48c5-ae3a-1baabe00f337 | H41: 14a3d68f-c132-4f17-8952-1c4b7e23fe77 | AD41: =IFERROR(__xludf.DUMMYFUNCTION("""COMPUTED_VALUE"""),"73df5aae-f42a-49a0-9d8f-616ca6dbebaa") -> 73df5aae-f42a-49a0-9d8f-616ca6dbebaa | AE41: =IFERROR(__xludf.DUMMYFUNCTION("""COMPUTED_VALUE"""),"019ecf8a-5132-7f8f-a6e1-5446a97d8314") -> 019ecf8a-5132-7f8f-a6e1-5446a97d8314 | AF41: =IFERROR(__xludf.DUMMYFUNCTION("""COMPUTED_VALUE"""),46189.35195601852) -> 46189.352 | AG41: =IFERROR(__xludf.DUMMYFUNCTION("""COMPUTED_VALUE"""),"debit") -> debit | AH41: =IFERROR(__xludf.DUMMYFUNCTION("""COMPUTED_VALUE"""),41791.17) -> 41791.17 | AI41: =IFERROR(__xludf.DUMMYFUNCTION("""COMPUTED_VALUE"""),"cash_isa") -> cash_isa | AJ41: =IFERROR(__xludf.DUMMYFUNCTION("""COMPUTED_VALUE"""),"9bc00e6b-ce5f-48c5-ae3a-1baabe00f337") -> 9bc00e6b-ce5f-48c5-ae3a-1baabe00f337 | AK41: =IFERROR(__xludf.DUMMYFUNCTION("""COMPUTED_VALUE"""),"845dcc7b-e80c-47ba-978d-eaf51da59982") -> 845dcc7b-e80c-47ba-978d-eaf51da59982 | AR41: =ROUND(VALUE(AH41),2)&"_"&TRIM(LOWER(AG41)) -> 41791.17_debit | AS41: =IF(AH41="", "", LET(current_amt, ROUND(VALUE(AH41), 2), current_dir, TRIM(LOWER(AG41)), opposite_dir, IF(current_dir="credit", "debit", "credit"), occ, COUNTIFS($AH$3:AH41, AH41, $AG$3:AG41, AG41), opp_total, COUNTIFS($AH$3:$AH$1000, AH41, $AG$3:$AG$1000, opposite_dir), IF(opp_total >= occ, "DROP", "KEEP"))) -> DROP
A42: 73df5aae-f42a-49a0-9d8f-616ca6dbebaa | B42: 019ecf98-733d-72a0-a05c-1a32af726a8d | C42: 46189.363 | D42: credit | E42: 41788.29 | F42: cash_isa | G42: 9bc00e6b-ce5f-48c5-ae3a-1baabe00f337 | H42: 0285c1e8-83b6-480d-816e-e296ce32b465 | AD42: =IFERROR(__xludf.DUMMYFUNCTION("""COMPUTED_VALUE"""),"73df5aae-f42a-49a0-9d8f-616ca6dbebaa") -> 73df5aae-f42a-49a0-9d8f-616ca6dbebaa | AE42: =IFERROR(__xludf.DUMMYFUNCTION("""COMPUTED_VALUE"""),"019ecf8a-53f3-7688-812f-62e1e9ae6177") -> 019ecf8a-53f3-7688-812f-62e1e9ae6177 | AF42: =IFERROR(__xludf.DUMMYFUNCTION("""COMPUTED_VALUE"""),46189.35196759259) -> 46189.352 | AG42: =IFERROR(__xludf.DUMMYFUNCTION("""COMPUTED_VALUE"""),"debit") -> debit | AH42: =IFERROR(__xludf.DUMMYFUNCTION("""COMPUTED_VALUE"""),20619.97) -> 20619.97 | AI42: =IFERROR(__xludf.DUMMYFUNCTION("""COMPUTED_VALUE"""),"cash_isa") -> cash_isa | AJ42: =IFERROR(__xludf.DUMMYFUNCTION("""COMPUTED_VALUE"""),"9bc00e6b-ce5f-48c5-ae3a-1baabe00f337") -> 9bc00e6b-ce5f-48c5-ae3a-1baabe00f337 | AK42: =IFERROR(__xludf.DUMMYFUNCTION("""COMPUTED_VALUE"""),"8b616f8a-bd8e-41d8-90df-75136e898d98") -> 8b616f8a-bd8e-41d8-90df-75136e898d98 | AR42: =ROUND(VALUE(AH42),2)&"_"&TRIM(LOWER(AG42)) -> 20619.97_debit | AS42: =IF(AH42="", "", LET(current_amt, ROUND(VALUE(AH42), 2), current_dir, TRIM(LOWER(AG42)), opposite_dir, IF(current_dir="credit", "debit", "credit"), occ, COUNTIFS($AH$3:AH42, AH42, $AG$3:AG42, AG42), opp_total, COUNTIFS($AH$3:$AH$1000, AH42, $AG$3:$AG$1000, opposite_dir), IF(opp_total >= occ, "DROP", "KEEP"))) -> DROP
A43: 73df5aae-f42a-49a0-9d8f-616ca6dbebaa | B43: 019ecf9a-3fb2-726a-9cfc-134ad8836621 | C43: 46189.364 | D43: credit | E43: 41464.02 | F43: cash_isa | G43: 9bc00e6b-ce5f-48c5-ae3a-1baabe00f337 | H43: 1b095b3a-bec1-4b04-b23d-6104525e3eb2 | AD43: =IFERROR(__xludf.DUMMYFUNCTION("""COMPUTED_VALUE"""),"73df5aae-f42a-49a0-9d8f-616ca6dbebaa") -> 73df5aae-f42a-49a0-9d8f-616ca6dbebaa | AE43: =IFERROR(__xludf.DUMMYFUNCTION("""COMPUTED_VALUE"""),"019ecf8a-bd53-71e8-baeb-d5cc3ee5c011") -> 019ecf8a-bd53-71e8-baeb-d5cc3ee5c011 | AF43: =IFERROR(__xludf.DUMMYFUNCTION("""COMPUTED_VALUE"""),46189.35228009259) -> 46189.352 | AG43: =IFERROR(__xludf.DUMMYFUNCTION("""COMPUTED_VALUE"""),"credit") -> credit | AH43: =IFERROR(__xludf.DUMMYFUNCTION("""COMPUTED_VALUE"""),20902.73) -> 20902.73 | AI43: =IFERROR(__xludf.DUMMYFUNCTION("""COMPUTED_VALUE"""),"cash_isa") -> cash_isa | AJ43: =IFERROR(__xludf.DUMMYFUNCTION("""COMPUTED_VALUE"""),"9bc00e6b-ce5f-48c5-ae3a-1baabe00f337") -> 9bc00e6b-ce5f-48c5-ae3a-1baabe00f337 | AK43: =IFERROR(__xludf.DUMMYFUNCTION("""COMPUTED_VALUE"""),"0ca1b8b4-66c3-47cf-9239-c860dddc4cc9") -> 0ca1b8b4-66c3-47cf-9239-c860dddc4cc9 | AR43: =ROUND(VALUE(AH43),2)&"_"&TRIM(LOWER(AG43)) -> 20902.73_credit | AS43: =IF(AH43="", "", LET(current_amt, ROUND(VALUE(AH43), 2), current_dir, TRIM(LOWER(AG43)), opposite_dir, IF(current_dir="credit", "debit", "credit"), occ, COUNTIFS($AH$3:AH43, AH43, $AG$3:AG43, AG43), opp_total, COUNTIFS($AH$3:$AH$1000, AH43, $AG$3:$AG$1000, opposite_dir), IF(opp_total >= occ, "DROP", "KEEP"))) -> DROP
A44: 73df5aae-f42a-49a0-9d8f-616ca6dbebaa | B44: 019ecf9b-58da-7469-9667-1796b687fa1c | C44: 46189.365 | D44: debit | E44: 41788.29 | F44: cash_isa | G44: 9bc00e6b-ce5f-48c5-ae3a-1baabe00f337 | H44: 0285c1e8-83b6-480d-816e-e296ce32b465 | AD44: =IFERROR(__xludf.DUMMYFUNCTION("""COMPUTED_VALUE"""),"73df5aae-f42a-49a0-9d8f-616ca6dbebaa") -> 73df5aae-f42a-49a0-9d8f-616ca6dbebaa | AE44: =IFERROR(__xludf.DUMMYFUNCTION("""COMPUTED_VALUE"""),"019ecf8b-0bd9-7b32-9575-e7e5238114eb") -> 019ecf8b-0bd9-7b32-9575-e7e5238114eb | AF44: =IFERROR(__xludf.DUMMYFUNCTION("""COMPUTED_VALUE"""),46189.35251157408) -> 46189.353 | AG44: =IFERROR(__xludf.DUMMYFUNCTION("""COMPUTED_VALUE"""),"credit") -> credit | AH44: =IFERROR(__xludf.DUMMYFUNCTION("""COMPUTED_VALUE"""),42620.95) -> 42620.95 | AI44: =IFERROR(__xludf.DUMMYFUNCTION("""COMPUTED_VALUE"""),"cash_isa") -> cash_isa | AJ44: =IFERROR(__xludf.DUMMYFUNCTION("""COMPUTED_VALUE"""),"9bc00e6b-ce5f-48c5-ae3a-1baabe00f337") -> 9bc00e6b-ce5f-48c5-ae3a-1baabe00f337 | AK44: =IFERROR(__xludf.DUMMYFUNCTION("""COMPUTED_VALUE"""),"1162a08c-59f0-42e2-9c3a-dc7b5d58bef3") -> 1162a08c-59f0-42e2-9c3a-dc7b5d58bef3 | AR44: =ROUND(VALUE(AH44),2)&"_"&TRIM(LOWER(AG44)) -> 42620.95_credit | AS44: =IF(AH44="", "", LET(current_amt, ROUND(VALUE(AH44), 2), current_dir, TRIM(LOWER(AG44)), opposite_dir, IF(current_dir="credit", "debit", "credit"), occ, COUNTIFS($AH$3:AH44, AH44, $AG$3:AG44, AG44), opp_total, COUNTIFS($AH$3:$AH$1000, AH44, $AG$3:$AG$1000, opposite_dir), IF(opp_total >= occ, "DROP", "KEEP"))) -> DROP
A45: 73df5aae-f42a-49a0-9d8f-616ca6dbebaa | B45: 019ecf9c-8fb5-7f14-bc37-2c5eddcd0c9c | C45: 46189.366 | D45: debit | E45: 41464.02 | F45: cash_isa | G45: 9bc00e6b-ce5f-48c5-ae3a-1baabe00f337 | H45: 1b095b3a-bec1-4b04-b23d-6104525e3eb2 | AD45: =IFERROR(__xludf.DUMMYFUNCTION("""COMPUTED_VALUE"""),"73df5aae-f42a-49a0-9d8f-616ca6dbebaa") -> 73df5aae-f42a-49a0-9d8f-616ca6dbebaa | AE45: =IFERROR(__xludf.DUMMYFUNCTION("""COMPUTED_VALUE"""),"019ecf8c-1110-78f0-aa0c-9d38f0eb2166") -> 019ecf8c-1110-78f0-aa0c-9d38f0eb2166 | AF45: =IFERROR(__xludf.DUMMYFUNCTION("""COMPUTED_VALUE"""),46189.35328703704) -> 46189.353 | AG45: =IFERROR(__xludf.DUMMYFUNCTION("""COMPUTED_VALUE"""),"credit") -> credit | AH45: =IFERROR(__xludf.DUMMYFUNCTION("""COMPUTED_VALUE"""),21429.12) -> 21429.12 | AI45: =IFERROR(__xludf.DUMMYFUNCTION("""COMPUTED_VALUE"""),"cash_isa") -> cash_isa | AJ45: =IFERROR(__xludf.DUMMYFUNCTION("""COMPUTED_VALUE"""),"9bc00e6b-ce5f-48c5-ae3a-1baabe00f337") -> 9bc00e6b-ce5f-48c5-ae3a-1baabe00f337 | AK45: =IFERROR(__xludf.DUMMYFUNCTION("""COMPUTED_VALUE"""),"5500a291-d4a3-4c20-8f81-385002437c7b") -> 5500a291-d4a3-4c20-8f81-385002437c7b | AR45: =ROUND(VALUE(AH45),2)&"_"&TRIM(LOWER(AG45)) -> 21429.12_credit | AS45: =IF(AH45="", "", LET(current_amt, ROUND(VALUE(AH45), 2), current_dir, TRIM(LOWER(AG45)), opposite_dir, IF(current_dir="credit", "debit", "credit"), occ, COUNTIFS($AH$3:AH45, AH45, $AG$3:AG45, AG45), opp_total, COUNTIFS($AH$3:$AH$1000, AH45, $AG$3:$AG$1000, opposite_dir), IF(opp_total >= occ, "DROP", "KEEP"))) -> DROP
A46: 73df5aae-f42a-49a0-9d8f-616ca6dbebaa | B46: 019ecf9c-e80e-7ff5-b563-e60cf12dd0a3 | C46: 46189.366 | D46: credit | E46: 20858.76 | F46: cash_isa | G46: 9bc00e6b-ce5f-48c5-ae3a-1baabe00f337 | H46: 7431ff90-4b3c-41d6-b433-d7eb0ee49d31 | AD46: =IFERROR(__xludf.DUMMYFUNCTION("""COMPUTED_VALUE"""),"73df5aae-f42a-49a0-9d8f-616ca6dbebaa") -> 73df5aae-f42a-49a0-9d8f-616ca6dbebaa | AE46: =IFERROR(__xludf.DUMMYFUNCTION("""COMPUTED_VALUE"""),"019ecf8c-3fa7-7dfe-beb5-d12f795a9f26") -> 019ecf8c-3fa7-7dfe-beb5-d12f795a9f26 | AF46: =IFERROR(__xludf.DUMMYFUNCTION("""COMPUTED_VALUE"""),46189.353425925925) -> 46189.353 | AG46: =IFERROR(__xludf.DUMMYFUNCTION("""COMPUTED_VALUE"""),"debit") -> debit | AH46: =IFERROR(__xludf.DUMMYFUNCTION("""COMPUTED_VALUE"""),20902.73) -> 20902.73 | AI46: =IFERROR(__xludf.DUMMYFUNCTION("""COMPUTED_VALUE"""),"cash_isa") -> cash_isa | AJ46: =IFERROR(__xludf.DUMMYFUNCTION("""COMPUTED_VALUE"""),"9bc00e6b-ce5f-48c5-ae3a-1baabe00f337") -> 9bc00e6b-ce5f-48c5-ae3a-1baabe00f337 | AK46: =IFERROR(__xludf.DUMMYFUNCTION("""COMPUTED_VALUE"""),"0ca1b8b4-66c3-47cf-9239-c860dddc4cc9") -> 0ca1b8b4-66c3-47cf-9239-c860dddc4cc9 | AR46: =ROUND(VALUE(AH46),2)&"_"&TRIM(LOWER(AG46)) -> 20902.73_debit | AS46: =IF(AH46="", "", LET(current_amt, ROUND(VALUE(AH46), 2), current_dir, TRIM(LOWER(AG46)), opposite_dir, IF(current_dir="credit", "debit", "credit"), occ, COUNTIFS($AH$3:AH46, AH46, $AG$3:AG46, AG46), opp_total, COUNTIFS($AH$3:$AH$1000, AH46, $AG$3:$AG$1000, opposite_dir), IF(opp_total >= occ, "DROP", "KEEP"))) -> DROP
A47: 73df5aae-f42a-49a0-9d8f-616ca6dbebaa | B47: 019ecf9f-8449-7522-9db7-a30e43628c8e | C47: 46189.368 | D47: debit | E47: 20858.76 | F47: cash_isa | G47: 9bc00e6b-ce5f-48c5-ae3a-1baabe00f337 | H47: 7431ff90-4b3c-41d6-b433-d7eb0ee49d31 | AD47: =IFERROR(__xludf.DUMMYFUNCTION("""COMPUTED_VALUE"""),"73df5aae-f42a-49a0-9d8f-616ca6dbebaa") -> 73df5aae-f42a-49a0-9d8f-616ca6dbebaa | AE47: =IFERROR(__xludf.DUMMYFUNCTION("""COMPUTED_VALUE"""),"019ecf8d-3769-76ca-b384-c2cb88dd928a") -> 019ecf8d-3769-76ca-b384-c2cb88dd928a | AF47: =IFERROR(__xludf.DUMMYFUNCTION("""COMPUTED_VALUE"""),46189.35415509259) -> 46189.354 | AG47: =IFERROR(__xludf.DUMMYFUNCTION("""COMPUTED_VALUE"""),"debit") -> debit | AH47: =IFERROR(__xludf.DUMMYFUNCTION("""COMPUTED_VALUE"""),42620.95) -> 42620.95 | AI47: =IFERROR(__xludf.DUMMYFUNCTION("""COMPUTED_VALUE"""),"cash_isa") -> cash_isa | AJ47: =IFERROR(__xludf.DUMMYFUNCTION("""COMPUTED_VALUE"""),"9bc00e6b-ce5f-48c5-ae3a-1baabe00f337") -> 9bc00e6b-ce5f-48c5-ae3a-1baabe00f337 | AK47: =IFERROR(__xludf.DUMMYFUNCTION("""COMPUTED_VALUE"""),"1162a08c-59f0-42e2-9c3a-dc7b5d58bef3") -> 1162a08c-59f0-42e2-9c3a-dc7b5d58bef3 | AR47: =ROUND(VALUE(AH47),2)&"_"&TRIM(LOWER(AG47)) -> 42620.95_debit | AS47: =IF(AH47="", "", LET(current_amt, ROUND(VALUE(AH47), 2), current_dir, TRIM(LOWER(AG47)), opposite_dir, IF(current_dir="credit", "debit", "credit"), occ, COUNTIFS($AH$3:AH47, AH47, $AG$3:AG47, AG47), opp_total, COUNTIFS($AH$3:$AH$1000, AH47, $AG$3:$AG$1000, opposite_dir), IF(opp_total >= occ, "DROP", "KEEP"))) -> DROP
A48: 73df5aae-f42a-49a0-9d8f-616ca6dbebaa | B48: 019ecf9f-861e-7c86-bcca-0ec31ba3c4e5 | C48: 46189.368 | D48: credit | E48: 42213.57 | F48: cash_isa | G48: 9bc00e6b-ce5f-48c5-ae3a-1baabe00f337 | H48: b66586bc-b32a-4693-b8da-db48ee5bceb3 | AD48: =IFERROR(__xludf.DUMMYFUNCTION("""COMPUTED_VALUE"""),"73df5aae-f42a-49a0-9d8f-616ca6dbebaa") -> 73df5aae-f42a-49a0-9d8f-616ca6dbebaa | AE48: =IFERROR(__xludf.DUMMYFUNCTION("""COMPUTED_VALUE"""),"019ecf8d-42ca-73b4-9e10-9485842d30d5") -> 019ecf8d-42ca-73b4-9e10-9485842d30d5 | AF48: =IFERROR(__xludf.DUMMYFUNCTION("""COMPUTED_VALUE"""),46189.35418981481) -> 46189.354 | AG48: =IFERROR(__xludf.DUMMYFUNCTION("""COMPUTED_VALUE"""),"credit") -> credit | AH48: =IFERROR(__xludf.DUMMYFUNCTION("""COMPUTED_VALUE"""),30124.06) -> 30124.06 | AI48: =IFERROR(__xludf.DUMMYFUNCTION("""COMPUTED_VALUE"""),"cash_isa") -> cash_isa | AJ48: =IFERROR(__xludf.DUMMYFUNCTION("""COMPUTED_VALUE"""),"9bc00e6b-ce5f-48c5-ae3a-1baabe00f337") -> 9bc00e6b-ce5f-48c5-ae3a-1baabe00f337 | AK48: =IFERROR(__xludf.DUMMYFUNCTION("""COMPUTED_VALUE"""),"0b60b1f8-e681-4814-9643-b035fc4c3e8c") -> 0b60b1f8-e681-4814-9643-b035fc4c3e8c | AR48: =ROUND(VALUE(AH48),2)&"_"&TRIM(LOWER(AG48)) -> 30124.06_credit | AS48: =IF(AH48="", "", LET(current_amt, ROUND(VALUE(AH48), 2), current_dir, TRIM(LOWER(AG48)), opposite_dir, IF(current_dir="credit", "debit", "credit"), occ, COUNTIFS($AH$3:AH48, AH48, $AG$3:AG48, AG48), opp_total, COUNTIFS($AH$3:$AH$1000, AH48, $AG$3:$AG$1000, opposite_dir), IF(opp_total >= occ, "DROP", "KEEP"))) -> DROP
A49: 73df5aae-f42a-49a0-9d8f-616ca6dbebaa | B49: 019ecfa1-69af-7300-9a1f-616dd17b956a | C49: 46189.369 | D49: credit | E49: 27138.16 | F49: cash_isa | G49: 9bc00e6b-ce5f-48c5-ae3a-1baabe00f337 | H49: 7656788e-1cb3-4ca4-89c4-a220c453ea4c | AD49: =IFERROR(__xludf.DUMMYFUNCTION("""COMPUTED_VALUE"""),"73df5aae-f42a-49a0-9d8f-616ca6dbebaa") -> 73df5aae-f42a-49a0-9d8f-616ca6dbebaa | AE49: =IFERROR(__xludf.DUMMYFUNCTION("""COMPUTED_VALUE"""),"019ecf8e-2d29-7ad4-b61a-380cbb8924fb") -> 019ecf8e-2d29-7ad4-b61a-380cbb8924fb | AF49: =IFERROR(__xludf.DUMMYFUNCTION("""COMPUTED_VALUE"""),46189.35488425926) -> 46189.355 | AG49: =IFERROR(__xludf.DUMMYFUNCTION("""COMPUTED_VALUE"""),"debit") -> debit | AH49: =IFERROR(__xludf.DUMMYFUNCTION("""COMPUTED_VALUE"""),21429.12) -> 21429.12 | AI49: =IFERROR(__xludf.DUMMYFUNCTION("""COMPUTED_VALUE"""),"cash_isa") -> cash_isa | AJ49: =IFERROR(__xludf.DUMMYFUNCTION("""COMPUTED_VALUE"""),"9bc00e6b-ce5f-48c5-ae3a-1baabe00f337") -> 9bc00e6b-ce5f-48c5-ae3a-1baabe00f337 | AK49: =IFERROR(__xludf.DUMMYFUNCTION("""COMPUTED_VALUE"""),"5500a291-d4a3-4c20-8f81-385002437c7b") -> 5500a291-d4a3-4c20-8f81-385002437c7b | AR49: =ROUND(VALUE(AH49),2)&"_"&TRIM(LOWER(AG49)) -> 21429.12_debit | AS49: =IF(AH49="", "", LET(current_amt, ROUND(VALUE(AH49), 2), current_dir, TRIM(LOWER(AG49)), opposite_dir, IF(current_dir="credit", "debit", "credit"), occ, COUNTIFS($AH$3:AH49, AH49, $AG$3:AG49, AG49), opp_total, COUNTIFS($AH$3:$AH$1000, AH49, $AG$3:$AG$1000, opposite_dir), IF(opp_total >= occ, "DROP", "KEEP"))) -> DROP
A50: 73df5aae-f42a-49a0-9d8f-616ca6dbebaa | B50: 019ecfa1-ea2d-7221-8eda-3be9471854a7 | C50: 46189.37 | D50: debit | E50: 42213.57 | F50: cash_isa | G50: 9bc00e6b-ce5f-48c5-ae3a-1baabe00f337 | H50: b66586bc-b32a-4693-b8da-db48ee5bceb3 | AD50: =IFERROR(__xludf.DUMMYFUNCTION("""COMPUTED_VALUE"""),"73df5aae-f42a-49a0-9d8f-616ca6dbebaa") -> 73df5aae-f42a-49a0-9d8f-616ca6dbebaa | AE50: =IFERROR(__xludf.DUMMYFUNCTION("""COMPUTED_VALUE"""),"019ecf8f-25aa-766e-97c7-ca1f7294dff4") -> 019ecf8f-25aa-766e-97c7-ca1f7294dff4 | AF50: =IFERROR(__xludf.DUMMYFUNCTION("""COMPUTED_VALUE"""),46189.355625) -> 46189.356 | AG50: =IFERROR(__xludf.DUMMYFUNCTION("""COMPUTED_VALUE"""),"credit") -> credit | AH50: =IFERROR(__xludf.DUMMYFUNCTION("""COMPUTED_VALUE"""),15678.39) -> 15678.39 | AI50: =IFERROR(__xludf.DUMMYFUNCTION("""COMPUTED_VALUE"""),"cash_isa") -> cash_isa | AJ50: =IFERROR(__xludf.DUMMYFUNCTION("""COMPUTED_VALUE"""),"9bc00e6b-ce5f-48c5-ae3a-1baabe00f337") -> 9bc00e6b-ce5f-48c5-ae3a-1baabe00f337 | AK50: =IFERROR(__xludf.DUMMYFUNCTION("""COMPUTED_VALUE"""),"14a3d68f-c132-4f17-8952-1c4b7e23fe77") -> 14a3d68f-c132-4f17-8952-1c4b7e23fe77 | AR50: =ROUND(VALUE(AH50),2)&"_"&TRIM(LOWER(AG50)) -> 15678.39_credit | AS50: =IF(AH50="", "", LET(current_amt, ROUND(VALUE(AH50), 2), current_dir, TRIM(LOWER(AG50)), opposite_dir, IF(current_dir="credit", "debit", "credit"), occ, COUNTIFS($AH$3:AH50, AH50, $AG$3:AG50, AG50), opp_total, COUNTIFS($AH$3:$AH$1000, AH50, $AG$3:$AG$1000, opposite_dir), IF(opp_total >= occ, "DROP", "KEEP"))) -> DROP
A51: 73df5aae-f42a-49a0-9d8f-616ca6dbebaa | B51: 019ecfa3-36bf-76b9-a6ee-d5038c340978 | C51: 46189.371 | D51: credit | E51: 20708.18 | F51: cash_isa | G51: 9bc00e6b-ce5f-48c5-ae3a-1baabe00f337 | H51: 887de5c0-de23-4ec2-8e28-5f7a3d8297b1 | AD51: =IFERROR(__xludf.DUMMYFUNCTION("""COMPUTED_VALUE"""),"73df5aae-f42a-49a0-9d8f-616ca6dbebaa") -> 73df5aae-f42a-49a0-9d8f-616ca6dbebaa | AE51: =IFERROR(__xludf.DUMMYFUNCTION("""COMPUTED_VALUE"""),"019ecf90-396e-705f-9580-362a52fee9e5") -> 019ecf90-396e-705f-9580-362a52fee9e5 | AF51: =IFERROR(__xludf.DUMMYFUNCTION("""COMPUTED_VALUE"""),46189.35643518518) -> 46189.356 | AG51: =IFERROR(__xludf.DUMMYFUNCTION("""COMPUTED_VALUE"""),"debit") -> debit | AH51: =IFERROR(__xludf.DUMMYFUNCTION("""COMPUTED_VALUE"""),30124.06) -> 30124.06 | AI51: =IFERROR(__xludf.DUMMYFUNCTION("""COMPUTED_VALUE"""),"cash_isa") -> cash_isa | AJ51: =IFERROR(__xludf.DUMMYFUNCTION("""COMPUTED_VALUE"""),"9bc00e6b-ce5f-48c5-ae3a-1baabe00f337") -> 9bc00e6b-ce5f-48c5-ae3a-1baabe00f337 | AK51: =IFERROR(__xludf.DUMMYFUNCTION("""COMPUTED_VALUE"""),"0b60b1f8-e681-4814-9643-b035fc4c3e8c") -> 0b60b1f8-e681-4814-9643-b035fc4c3e8c | AR51: =ROUND(VALUE(AH51),2)&"_"&TRIM(LOWER(AG51)) -> 30124.06_debit | AS51: =IF(AH51="", "", LET(current_amt, ROUND(VALUE(AH51), 2), current_dir, TRIM(LOWER(AG51)), opposite_dir, IF(current_dir="credit", "debit", "credit"), occ, COUNTIFS($AH$3:AH51, AH51, $AG$3:AG51, AG51), opp_total, COUNTIFS($AH$3:$AH$1000, AH51, $AG$3:$AG$1000, opposite_dir), IF(opp_total >= occ, "DROP", "KEEP"))) -> DROP
A52: 73df5aae-f42a-49a0-9d8f-616ca6dbebaa | B52: 019ecfa3-c30a-7245-a1b8-e52f58dce3a8 | C52: 46189.371 | D52: credit | E52: 20910.88 | F52: cash_isa | G52: 9bc00e6b-ce5f-48c5-ae3a-1baabe00f337 | H52: e7447f5e-e526-4c5f-adf1-8e8cd0b72125 | AD52: =IFERROR(__xludf.DUMMYFUNCTION("""COMPUTED_VALUE"""),"73df5aae-f42a-49a0-9d8f-616ca6dbebaa") -> 73df5aae-f42a-49a0-9d8f-616ca6dbebaa | AE52: =IFERROR(__xludf.DUMMYFUNCTION("""COMPUTED_VALUE"""),"019ecf91-8372-70ee-9010-f68eefd42fb9") -> 019ecf91-8372-70ee-9010-f68eefd42fb9 | AF52: =IFERROR(__xludf.DUMMYFUNCTION("""COMPUTED_VALUE"""),46189.35741898148) -> 46189.357 | AG52: =IFERROR(__xludf.DUMMYFUNCTION("""COMPUTED_VALUE"""),"debit") -> debit | AH52: =IFERROR(__xludf.DUMMYFUNCTION("""COMPUTED_VALUE"""),15678.39) -> 15678.39 | AI52: =IFERROR(__xludf.DUMMYFUNCTION("""COMPUTED_VALUE"""),"cash_isa") -> cash_isa | AJ52: =IFERROR(__xludf.DUMMYFUNCTION("""COMPUTED_VALUE"""),"9bc00e6b-ce5f-48c5-ae3a-1baabe00f337") -> 9bc00e6b-ce5f-48c5-ae3a-1baabe00f337 | AK52: =IFERROR(__xludf.DUMMYFUNCTION("""COMPUTED_VALUE"""),"14a3d68f-c132-4f17-8952-1c4b7e23fe77") -> 14a3d68f-c132-4f17-8952-1c4b7e23fe77 | AR52: =ROUND(VALUE(AH52),2)&"_"&TRIM(LOWER(AG52)) -> 15678.39_debit | AS52: =IF(AH52="", "", LET(current_amt, ROUND(VALUE(AH52), 2), current_dir, TRIM(LOWER(AG52)), opposite_dir, IF(current_dir="credit", "debit", "credit"), occ, COUNTIFS($AH$3:AH52, AH52, $AG$3:AG52, AG52), opp_total, COUNTIFS($AH$3:$AH$1000, AH52, $AG$3:$AG$1000, opposite_dir), IF(opp_total >= occ, "DROP", "KEEP"))) -> DROP
A53: 73df5aae-f42a-49a0-9d8f-616ca6dbebaa | B53: 019ecfa4-1488-7afd-9c60-e29637613cce | C53: 46189.371 | D53: credit | E53: 600 | F53: cash_isa | G53: 9bc00e6b-ce5f-48c5-ae3a-1baabe00f337 | H53: 085b2804-8667-41d1-bb69-7a8e9fc6fb9c | AD53: =IFERROR(__xludf.DUMMYFUNCTION("""COMPUTED_VALUE"""),"73df5aae-f42a-49a0-9d8f-616ca6dbebaa") -> 73df5aae-f42a-49a0-9d8f-616ca6dbebaa | AE53: =IFERROR(__xludf.DUMMYFUNCTION("""COMPUTED_VALUE"""),"019ecf98-733d-72a0-a05c-1a32af726a8d") -> 019ecf98-733d-72a0-a05c-1a32af726a8d | AF53: =IFERROR(__xludf.DUMMYFUNCTION("""COMPUTED_VALUE"""),46189.36267361111) -> 46189.363 | AG53: =IFERROR(__xludf.DUMMYFUNCTION("""COMPUTED_VALUE"""),"credit") -> credit | AH53: =IFERROR(__xludf.DUMMYFUNCTION("""COMPUTED_VALUE"""),41788.29) -> 41788.29 | AI53: =IFERROR(__xludf.DUMMYFUNCTION("""COMPUTED_VALUE"""),"cash_isa") -> cash_isa | AJ53: =IFERROR(__xludf.DUMMYFUNCTION("""COMPUTED_VALUE"""),"9bc00e6b-ce5f-48c5-ae3a-1baabe00f337") -> 9bc00e6b-ce5f-48c5-ae3a-1baabe00f337 | AK53: =IFERROR(__xludf.DUMMYFUNCTION("""COMPUTED_VALUE"""),"0285c1e8-83b6-480d-816e-e296ce32b465") -> 0285c1e8-83b6-480d-816e-e296ce32b465 | AR53: =ROUND(VALUE(AH53),2)&"_"&TRIM(LOWER(AG53)) -> 41788.29_credit | AS53: =IF(AH53="", "", LET(current_amt, ROUND(VALUE(AH53), 2), current_dir, TRIM(LOWER(AG53)), opposite_dir, IF(current_dir="credit", "debit", "credit"), occ, COUNTIFS($AH$3:AH53, AH53, $AG$3:AG53, AG53), opp_total, COUNTIFS($AH$3:$AH$1000, AH53, $AG$3:$AG$1000, opposite_dir), IF(opp_total >= occ, "DROP", "KEEP"))) -> DROP
A54: 73df5aae-f42a-49a0-9d8f-616ca6dbebaa | B54: 019ecfa4-95ab-78b2-9df6-0cc0395860c0 | C54: 46189.372 | D54: debit | E54: 27138.16 | F54: cash_isa | G54: 9bc00e6b-ce5f-48c5-ae3a-1baabe00f337 | H54: 7656788e-1cb3-4ca4-89c4-a220c453ea4c | AD54: =IFERROR(__xludf.DUMMYFUNCTION("""COMPUTED_VALUE"""),"73df5aae-f42a-49a0-9d8f-616ca6dbebaa") -> 73df5aae-f42a-49a0-9d8f-616ca6dbebaa | AE54: =IFERROR(__xludf.DUMMYFUNCTION("""COMPUTED_VALUE"""),"019ecf9a-3fb2-726a-9cfc-134ad8836621") -> 019ecf9a-3fb2-726a-9cfc-134ad8836621 | AF54: =IFERROR(__xludf.DUMMYFUNCTION("""COMPUTED_VALUE"""),46189.36403935185) -> 46189.364 | AG54: =IFERROR(__xludf.DUMMYFUNCTION("""COMPUTED_VALUE"""),"credit") -> credit | AH54: =IFERROR(__xludf.DUMMYFUNCTION("""COMPUTED_VALUE"""),41464.02) -> 41464.02 | AI54: =IFERROR(__xludf.DUMMYFUNCTION("""COMPUTED_VALUE"""),"cash_isa") -> cash_isa | AJ54: =IFERROR(__xludf.DUMMYFUNCTION("""COMPUTED_VALUE"""),"9bc00e6b-ce5f-48c5-ae3a-1baabe00f337") -> 9bc00e6b-ce5f-48c5-ae3a-1baabe00f337 | AK54: =IFERROR(__xludf.DUMMYFUNCTION("""COMPUTED_VALUE"""),"1b095b3a-bec1-4b04-b23d-6104525e3eb2") -> 1b095b3a-bec1-4b04-b23d-6104525e3eb2 | AR54: =ROUND(VALUE(AH54),2)&"_"&TRIM(LOWER(AG54)) -> 41464.02_credit | AS54: =IF(AH54="", "", LET(current_amt, ROUND(VALUE(AH54), 2), current_dir, TRIM(LOWER(AG54)), opposite_dir, IF(current_dir="credit", "debit", "credit"), occ, COUNTIFS($AH$3:AH54, AH54, $AG$3:AG54, AG54), opp_total, COUNTIFS($AH$3:$AH$1000, AH54, $AG$3:$AG$1000, opposite_dir), IF(opp_total >= occ, "DROP", "KEEP"))) -> DROP
A55: 73df5aae-f42a-49a0-9d8f-616ca6dbebaa | B55: 019ecfa5-a521-7820-94ee-27e0e26b36f4 | C55: 46189.373 | D55: credit | E55: 15731.47 | F55: cash_isa | G55: 9bc00e6b-ce5f-48c5-ae3a-1baabe00f337 | H55: cc1d8e4c-a245-4b9d-a206-5c73b7275d86 | AD55: =IFERROR(__xludf.DUMMYFUNCTION("""COMPUTED_VALUE"""),"73df5aae-f42a-49a0-9d8f-616ca6dbebaa") -> 73df5aae-f42a-49a0-9d8f-616ca6dbebaa | AE55: =IFERROR(__xludf.DUMMYFUNCTION("""COMPUTED_VALUE"""),"019ecf9b-58da-7469-9667-1796b687fa1c") -> 019ecf9b-58da-7469-9667-1796b687fa1c | AF55: =IFERROR(__xludf.DUMMYFUNCTION("""COMPUTED_VALUE"""),46189.36487268518) -> 46189.365 | AG55: =IFERROR(__xludf.DUMMYFUNCTION("""COMPUTED_VALUE"""),"debit") -> debit | AH55: =IFERROR(__xludf.DUMMYFUNCTION("""COMPUTED_VALUE"""),41788.29) -> 41788.29 | AI55: =IFERROR(__xludf.DUMMYFUNCTION("""COMPUTED_VALUE"""),"cash_isa") -> cash_isa | AJ55: =IFERROR(__xludf.DUMMYFUNCTION("""COMPUTED_VALUE"""),"9bc00e6b-ce5f-48c5-ae3a-1baabe00f337") -> 9bc00e6b-ce5f-48c5-ae3a-1baabe00f337 | AK55: =IFERROR(__xludf.DUMMYFUNCTION("""COMPUTED_VALUE"""),"0285c1e8-83b6-480d-816e-e296ce32b465") -> 0285c1e8-83b6-480d-816e-e296ce32b465 | AR55: =ROUND(VALUE(AH55),2)&"_"&TRIM(LOWER(AG55)) -> 41788.29_debit | AS55: =IF(AH55="", "", LET(current_amt, ROUND(VALUE(AH55), 2), current_dir, TRIM(LOWER(AG55)), opposite_dir, IF(current_dir="credit", "debit", "credit"), occ, COUNTIFS($AH$3:AH55, AH55, $AG$3:AG55, AG55), opp_total, COUNTIFS($AH$3:$AH$1000, AH55, $AG$3:$AG$1000, opposite_dir), IF(opp_total >= occ, "DROP", "KEEP"))) -> DROP
A56: 73df5aae-f42a-49a0-9d8f-616ca6dbebaa | B56: 019ecfa5-f985-75d7-9239-6f575e107b7b | C56: 46189.373 | D56: debit | E56: 20708.18 | F56: cash_isa | G56: 9bc00e6b-ce5f-48c5-ae3a-1baabe00f337 | H56: 887de5c0-de23-4ec2-8e28-5f7a3d8297b1 | AD56: =IFERROR(__xludf.DUMMYFUNCTION("""COMPUTED_VALUE"""),"73df5aae-f42a-49a0-9d8f-616ca6dbebaa") -> 73df5aae-f42a-49a0-9d8f-616ca6dbebaa | AE56: =IFERROR(__xludf.DUMMYFUNCTION("""COMPUTED_VALUE"""),"019ecf9c-8fb5-7f14-bc37-2c5eddcd0c9c") -> 019ecf9c-8fb5-7f14-bc37-2c5eddcd0c9c | AF56: =IFERROR(__xludf.DUMMYFUNCTION("""COMPUTED_VALUE"""),46189.36579861111) -> 46189.366 | AG56: =IFERROR(__xludf.DUMMYFUNCTION("""COMPUTED_VALUE"""),"debit") -> debit | AH56: =IFERROR(__xludf.DUMMYFUNCTION("""COMPUTED_VALUE"""),41464.02) -> 41464.02 | AI56: =IFERROR(__xludf.DUMMYFUNCTION("""COMPUTED_VALUE"""),"cash_isa") -> cash_isa | AJ56: =IFERROR(__xludf.DUMMYFUNCTION("""COMPUTED_VALUE"""),"9bc00e6b-ce5f-48c5-ae3a-1baabe00f337") -> 9bc00e6b-ce5f-48c5-ae3a-1baabe00f337 | AK56: =IFERROR(__xludf.DUMMYFUNCTION("""COMPUTED_VALUE"""),"1b095b3a-bec1-4b04-b23d-6104525e3eb2") -> 1b095b3a-bec1-4b04-b23d-6104525e3eb2 | AR56: =ROUND(VALUE(AH56),2)&"_"&TRIM(LOWER(AG56)) -> 41464.02_debit | AS56: =IF(AH56="", "", LET(current_amt, ROUND(VALUE(AH56), 2), current_dir, TRIM(LOWER(AG56)), opposite_dir, IF(current_dir="credit", "debit", "credit"), occ, COUNTIFS($AH$3:AH56, AH56, $AG$3:AG56, AG56), opp_total, COUNTIFS($AH$3:$AH$1000, AH56, $AG$3:$AG$1000, opposite_dir), IF(opp_total >= occ, "DROP", "KEEP"))) -> DROP
A57: 73df5aae-f42a-49a0-9d8f-616ca6dbebaa | B57: 019ecfa6-3ef4-7337-b7fd-41d0ca08caa1 | C57: 46189.373 | D57: debit | E57: 600 | F57: cash_isa | G57: 9bc00e6b-ce5f-48c5-ae3a-1baabe00f337 | H57: 085b2804-8667-41d1-bb69-7a8e9fc6fb9c | AD57: =IFERROR(__xludf.DUMMYFUNCTION("""COMPUTED_VALUE"""),"73df5aae-f42a-49a0-9d8f-616ca6dbebaa") -> 73df5aae-f42a-49a0-9d8f-616ca6dbebaa | AE57: =IFERROR(__xludf.DUMMYFUNCTION("""COMPUTED_VALUE"""),"019ecf9c-e80e-7ff5-b563-e60cf12dd0a3") -> 019ecf9c-e80e-7ff5-b563-e60cf12dd0a3 | AF57: =IFERROR(__xludf.DUMMYFUNCTION("""COMPUTED_VALUE"""),46189.36605324074) -> 46189.366 | AG57: =IFERROR(__xludf.DUMMYFUNCTION("""COMPUTED_VALUE"""),"credit") -> credit | AH57: =IFERROR(__xludf.DUMMYFUNCTION("""COMPUTED_VALUE"""),20858.76) -> 20858.76 | AI57: =IFERROR(__xludf.DUMMYFUNCTION("""COMPUTED_VALUE"""),"cash_isa") -> cash_isa | AJ57: =IFERROR(__xludf.DUMMYFUNCTION("""COMPUTED_VALUE"""),"9bc00e6b-ce5f-48c5-ae3a-1baabe00f337") -> 9bc00e6b-ce5f-48c5-ae3a-1baabe00f337 | AK57: =IFERROR(__xludf.DUMMYFUNCTION("""COMPUTED_VALUE"""),"7431ff90-4b3c-41d6-b433-d7eb0ee49d31") -> 7431ff90-4b3c-41d6-b433-d7eb0ee49d31 | AR57: =ROUND(VALUE(AH57),2)&"_"&TRIM(LOWER(AG57)) -> 20858.76_credit | AS57: =IF(AH57="", "", LET(current_amt, ROUND(VALUE(AH57), 2), current_dir, TRIM(LOWER(AG57)), opposite_dir, IF(current_dir="credit", "debit", "credit"), occ, COUNTIFS($AH$3:AH57, AH57, $AG$3:AG57, AG57), opp_total, COUNTIFS($AH$3:$AH$1000, AH57, $AG$3:$AG$1000, opposite_dir), IF(opp_total >= occ, "DROP", "KEEP"))) -> DROP
A58: 73df5aae-f42a-49a0-9d8f-616ca6dbebaa | B58: 019ecfa6-40b7-76ab-ae6c-74db43f45680 | C58: 46189.373 | D58: debit | E58: 20910.88 | F58: cash_isa | G58: 9bc00e6b-ce5f-48c5-ae3a-1baabe00f337 | H58: e7447f5e-e526-4c5f-adf1-8e8cd0b72125 | AD58: =IFERROR(__xludf.DUMMYFUNCTION("""COMPUTED_VALUE"""),"73df5aae-f42a-49a0-9d8f-616ca6dbebaa") -> 73df5aae-f42a-49a0-9d8f-616ca6dbebaa | AE58: =IFERROR(__xludf.DUMMYFUNCTION("""COMPUTED_VALUE"""),"019ecf9f-8449-7522-9db7-a30e43628c8e") -> 019ecf9f-8449-7522-9db7-a30e43628c8e | AF58: =IFERROR(__xludf.DUMMYFUNCTION("""COMPUTED_VALUE"""),46189.36803240741) -> 46189.368 | AG58: =IFERROR(__xludf.DUMMYFUNCTION("""COMPUTED_VALUE"""),"debit") -> debit | AH58: =IFERROR(__xludf.DUMMYFUNCTION("""COMPUTED_VALUE"""),20858.76) -> 20858.76 | AI58: =IFERROR(__xludf.DUMMYFUNCTION("""COMPUTED_VALUE"""),"cash_isa") -> cash_isa | AJ58: =IFERROR(__xludf.DUMMYFUNCTION("""COMPUTED_VALUE"""),"9bc00e6b-ce5f-48c5-ae3a-1baabe00f337") -> 9bc00e6b-ce5f-48c5-ae3a-1baabe00f337 | AK58: =IFERROR(__xludf.DUMMYFUNCTION("""COMPUTED_VALUE"""),"7431ff90-4b3c-41d6-b433-d7eb0ee49d31") -> 7431ff90-4b3c-41d6-b433-d7eb0ee49d31 | AR58: =ROUND(VALUE(AH58),2)&"_"&TRIM(LOWER(AG58)) -> 20858.76_debit | AS58: =IF(AH58="", "", LET(current_amt, ROUND(VALUE(AH58), 2), current_dir, TRIM(LOWER(AG58)), opposite_dir, IF(current_dir="credit", "debit", "credit"), occ, COUNTIFS($AH$3:AH58, AH58, $AG$3:AG58, AG58), opp_total, COUNTIFS($AH$3:$AH$1000, AH58, $AG$3:$AG$1000, opposite_dir), IF(opp_total >= occ, "DROP", "KEEP"))) -> DROP
A59: 73df5aae-f42a-49a0-9d8f-616ca6dbebaa | B59: 019ecfa8-36c0-75fc-b091-53d4fd822c98 | C59: 46189.375 | D59: credit | E59: 40854.07 | F59: cash_isa | G59: 9bc00e6b-ce5f-48c5-ae3a-1baabe00f337 | H59: 806f931e-51a6-4b29-8854-3f9befa1d615 | AD59: =IFERROR(__xludf.DUMMYFUNCTION("""COMPUTED_VALUE"""),"73df5aae-f42a-49a0-9d8f-616ca6dbebaa") -> 73df5aae-f42a-49a0-9d8f-616ca6dbebaa | AE59: =IFERROR(__xludf.DUMMYFUNCTION("""COMPUTED_VALUE"""),"019ecf9f-861e-7c86-bcca-0ec31ba3c4e5") -> 019ecf9f-861e-7c86-bcca-0ec31ba3c4e5 | AF59: =IFERROR(__xludf.DUMMYFUNCTION("""COMPUTED_VALUE"""),46189.36804398148) -> 46189.368 | AG59: =IFERROR(__xludf.DUMMYFUNCTION("""COMPUTED_VALUE"""),"credit") -> credit | AH59: =IFERROR(__xludf.DUMMYFUNCTION("""COMPUTED_VALUE"""),42213.57) -> 42213.57 | AI59: =IFERROR(__xludf.DUMMYFUNCTION("""COMPUTED_VALUE"""),"cash_isa") -> cash_isa | AJ59: =IFERROR(__xludf.DUMMYFUNCTION("""COMPUTED_VALUE"""),"9bc00e6b-ce5f-48c5-ae3a-1baabe00f337") -> 9bc00e6b-ce5f-48c5-ae3a-1baabe00f337 | AK59: =IFERROR(__xludf.DUMMYFUNCTION("""COMPUTED_VALUE"""),"b66586bc-b32a-4693-b8da-db48ee5bceb3") -> b66586bc-b32a-4693-b8da-db48ee5bceb3 | AR59: =ROUND(VALUE(AH59),2)&"_"&TRIM(LOWER(AG59)) -> 42213.57_credit | AS59: =IF(AH59="", "", LET(current_amt, ROUND(VALUE(AH59), 2), current_dir, TRIM(LOWER(AG59)), opposite_dir, IF(current_dir="credit", "debit", "credit"), occ, COUNTIFS($AH$3:AH59, AH59, $AG$3:AG59, AG59), opp_total, COUNTIFS($AH$3:$AH$1000, AH59, $AG$3:$AG$1000, opposite_dir), IF(opp_total >= occ, "DROP", "KEEP"))) -> DROP
A60: 73df5aae-f42a-49a0-9d8f-616ca6dbebaa | B60: 019ecfa8-a63d-7ba2-9de3-567700e8661e | C60: 46189.375 | D60: credit | E60: 21033.77 | F60: cash_isa | G60: 9bc00e6b-ce5f-48c5-ae3a-1baabe00f337 | H60: d64c241a-b8b6-4195-9500-aaa8e44ec56d | AD60: =IFERROR(__xludf.DUMMYFUNCTION("""COMPUTED_VALUE"""),"73df5aae-f42a-49a0-9d8f-616ca6dbebaa") -> 73df5aae-f42a-49a0-9d8f-616ca6dbebaa | AE60: =IFERROR(__xludf.DUMMYFUNCTION("""COMPUTED_VALUE"""),"019ecfa1-69af-7300-9a1f-616dd17b956a") -> 019ecfa1-69af-7300-9a1f-616dd17b956a | AF60: =IFERROR(__xludf.DUMMYFUNCTION("""COMPUTED_VALUE"""),46189.369479166664) -> 46189.369 | AG60: =IFERROR(__xludf.DUMMYFUNCTION("""COMPUTED_VALUE"""),"credit") -> credit | AH60: =IFERROR(__xludf.DUMMYFUNCTION("""COMPUTED_VALUE"""),27138.16) -> 27138.16 | AI60: =IFERROR(__xludf.DUMMYFUNCTION("""COMPUTED_VALUE"""),"cash_isa") -> cash_isa | AJ60: =IFERROR(__xludf.DUMMYFUNCTION("""COMPUTED_VALUE"""),"9bc00e6b-ce5f-48c5-ae3a-1baabe00f337") -> 9bc00e6b-ce5f-48c5-ae3a-1baabe00f337 | AK60: =IFERROR(__xludf.DUMMYFUNCTION("""COMPUTED_VALUE"""),"7656788e-1cb3-4ca4-89c4-a220c453ea4c") -> 7656788e-1cb3-4ca4-89c4-a220c453ea4c | AR60: =ROUND(VALUE(AH60),2)&"_"&TRIM(LOWER(AG60)) -> 27138.16_credit | AS60: =IF(AH60="", "", LET(current_amt, ROUND(VALUE(AH60), 2), current_dir, TRIM(LOWER(AG60)), opposite_dir, IF(current_dir="credit", "debit", "credit"), occ, COUNTIFS($AH$3:AH60, AH60, $AG$3:AG60, AG60), opp_total, COUNTIFS($AH$3:$AH$1000, AH60, $AG$3:$AG$1000, opposite_dir), IF(opp_total >= occ, "DROP", "KEEP"))) -> DROP
A61: 73df5aae-f42a-49a0-9d8f-616ca6dbebaa | B61: 019ecfa8-c18d-7ac0-baeb-e1e953df29fb | C61: 46189.375 | D61: debit | E61: 15731.47 | F61: cash_isa | G61: 9bc00e6b-ce5f-48c5-ae3a-1baabe00f337 | H61: cc1d8e4c-a245-4b9d-a206-5c73b7275d86 | AD61: =IFERROR(__xludf.DUMMYFUNCTION("""COMPUTED_VALUE"""),"73df5aae-f42a-49a0-9d8f-616ca6dbebaa") -> 73df5aae-f42a-49a0-9d8f-616ca6dbebaa | AE61: =IFERROR(__xludf.DUMMYFUNCTION("""COMPUTED_VALUE"""),"019ecfa1-ea2d-7221-8eda-3be9471854a7") -> 019ecfa1-ea2d-7221-8eda-3be9471854a7 | AF61: =IFERROR(__xludf.DUMMYFUNCTION("""COMPUTED_VALUE"""),46189.36986111111) -> 46189.37 | AG61: =IFERROR(__xludf.DUMMYFUNCTION("""COMPUTED_VALUE"""),"debit") -> debit | AH61: =IFERROR(__xludf.DUMMYFUNCTION("""COMPUTED_VALUE"""),42213.57) -> 42213.57 | AI61: =IFERROR(__xludf.DUMMYFUNCTION("""COMPUTED_VALUE"""),"cash_isa") -> cash_isa | AJ61: =IFERROR(__xludf.DUMMYFUNCTION("""COMPUTED_VALUE"""),"9bc00e6b-ce5f-48c5-ae3a-1baabe00f337") -> 9bc00e6b-ce5f-48c5-ae3a-1baabe00f337 | AK61: =IFERROR(__xludf.DUMMYFUNCTION("""COMPUTED_VALUE"""),"b66586bc-b32a-4693-b8da-db48ee5bceb3") -> b66586bc-b32a-4693-b8da-db48ee5bceb3 | AR61: =ROUND(VALUE(AH61),2)&"_"&TRIM(LOWER(AG61)) -> 42213.57_debit | AS61: =IF(AH61="", "", LET(current_amt, ROUND(VALUE(AH61), 2), current_dir, TRIM(LOWER(AG61)), opposite_dir, IF(current_dir="credit", "debit", "credit"), occ, COUNTIFS($AH$3:AH61, AH61, $AG$3:AG61, AG61), opp_total, COUNTIFS($AH$3:$AH$1000, AH61, $AG$3:$AG$1000, opposite_dir), IF(opp_total >= occ, "DROP", "KEEP"))) -> DROP
A62: 73df5aae-f42a-49a0-9d8f-616ca6dbebaa | B62: 019ecfaa-c79a-7a3d-b3c5-2d6e0a16ac20 | C62: 46189.377 | D62: debit | E62: 40854.07 | F62: cash_isa | G62: 9bc00e6b-ce5f-48c5-ae3a-1baabe00f337 | H62: 806f931e-51a6-4b29-8854-3f9befa1d615 | AD62: =IFERROR(__xludf.DUMMYFUNCTION("""COMPUTED_VALUE"""),"73df5aae-f42a-49a0-9d8f-616ca6dbebaa") -> 73df5aae-f42a-49a0-9d8f-616ca6dbebaa | AE62: =IFERROR(__xludf.DUMMYFUNCTION("""COMPUTED_VALUE"""),"019ecfa3-36bf-76b9-a6ee-d5038c340978") -> 019ecfa3-36bf-76b9-a6ee-d5038c340978 | AF62: =IFERROR(__xludf.DUMMYFUNCTION("""COMPUTED_VALUE"""),46189.370844907404) -> 46189.371 | AG62: =IFERROR(__xludf.DUMMYFUNCTION("""COMPUTED_VALUE"""),"credit") -> credit | AH62: =IFERROR(__xludf.DUMMYFUNCTION("""COMPUTED_VALUE"""),20708.18) -> 20708.18 | AI62: =IFERROR(__xludf.DUMMYFUNCTION("""COMPUTED_VALUE"""),"cash_isa") -> cash_isa | AJ62: =IFERROR(__xludf.DUMMYFUNCTION("""COMPUTED_VALUE"""),"9bc00e6b-ce5f-48c5-ae3a-1baabe00f337") -> 9bc00e6b-ce5f-48c5-ae3a-1baabe00f337 | AK62: =IFERROR(__xludf.DUMMYFUNCTION("""COMPUTED_VALUE"""),"887de5c0-de23-4ec2-8e28-5f7a3d8297b1") -> 887de5c0-de23-4ec2-8e28-5f7a3d8297b1 | AR62: =ROUND(VALUE(AH62),2)&"_"&TRIM(LOWER(AG62)) -> 20708.18_credit | AS62: =IF(AH62="", "", LET(current_amt, ROUND(VALUE(AH62), 2), current_dir, TRIM(LOWER(AG62)), opposite_dir, IF(current_dir="credit", "debit", "credit"), occ, COUNTIFS($AH$3:AH62, AH62, $AG$3:AG62, AG62), opp_total, COUNTIFS($AH$3:$AH$1000, AH62, $AG$3:$AG$1000, opposite_dir), IF(opp_total >= occ, "DROP", "KEEP"))) -> DROP
A63: 73df5aae-f42a-49a0-9d8f-616ca6dbebaa | B63: 019ecfab-c336-7820-8c3d-91db6724f641 | C63: 46189.377 | D63: debit | E63: 21033.77 | F63: cash_isa | G63: 9bc00e6b-ce5f-48c5-ae3a-1baabe00f337 | H63: d64c241a-b8b6-4195-9500-aaa8e44ec56d | AD63: =IFERROR(__xludf.DUMMYFUNCTION("""COMPUTED_VALUE"""),"73df5aae-f42a-49a0-9d8f-616ca6dbebaa") -> 73df5aae-f42a-49a0-9d8f-616ca6dbebaa | AE63: =IFERROR(__xludf.DUMMYFUNCTION("""COMPUTED_VALUE"""),"019ecfa3-c30a-7245-a1b8-e52f58dce3a8") -> 019ecfa3-c30a-7245-a1b8-e52f58dce3a8 | AF63: =IFERROR(__xludf.DUMMYFUNCTION("""COMPUTED_VALUE"""),46189.37126157407) -> 46189.371 | AG63: =IFERROR(__xludf.DUMMYFUNCTION("""COMPUTED_VALUE"""),"credit") -> credit | AH63: =IFERROR(__xludf.DUMMYFUNCTION("""COMPUTED_VALUE"""),20910.88) -> 20910.88 | AI63: =IFERROR(__xludf.DUMMYFUNCTION("""COMPUTED_VALUE"""),"cash_isa") -> cash_isa | AJ63: =IFERROR(__xludf.DUMMYFUNCTION("""COMPUTED_VALUE"""),"9bc00e6b-ce5f-48c5-ae3a-1baabe00f337") -> 9bc00e6b-ce5f-48c5-ae3a-1baabe00f337 | AK63: =IFERROR(__xludf.DUMMYFUNCTION("""COMPUTED_VALUE"""),"e7447f5e-e526-4c5f-adf1-8e8cd0b72125") -> e7447f5e-e526-4c5f-adf1-8e8cd0b72125 | AR63: =ROUND(VALUE(AH63),2)&"_"&TRIM(LOWER(AG63)) -> 20910.88_credit | AS63: =IF(AH63="", "", LET(current_amt, ROUND(VALUE(AH63), 2), current_dir, TRIM(LOWER(AG63)), opposite_dir, IF(current_dir="credit", "debit", "credit"), occ, COUNTIFS($AH$3:AH63, AH63, $AG$3:AG63, AG63), opp_total, COUNTIFS($AH$3:$AH$1000, AH63, $AG$3:$AG$1000, opposite_dir), IF(opp_total >= occ, "DROP", "KEEP"))) -> DROP
A64: 73df5aae-f42a-49a0-9d8f-616ca6dbebaa | B64: 019ecfb0-a778-78e7-97d2-b6f41f176b36 | C64: 46189.381 | D64: credit | E64: 23722.56 | F64: cash_isa | G64: 9bc00e6b-ce5f-48c5-ae3a-1baabe00f337 | H64: e9d9ba53-346f-47d3-8481-c47875d3b472 | AD64: =IFERROR(__xludf.DUMMYFUNCTION("""COMPUTED_VALUE"""),"73df5aae-f42a-49a0-9d8f-616ca6dbebaa") -> 73df5aae-f42a-49a0-9d8f-616ca6dbebaa | AE64: =IFERROR(__xludf.DUMMYFUNCTION("""COMPUTED_VALUE"""),"019ecfa4-1488-7afd-9c60-e29637613cce") -> 019ecfa4-1488-7afd-9c60-e29637613cce | AF64: =IFERROR(__xludf.DUMMYFUNCTION("""COMPUTED_VALUE"""),46189.37149305556) -> 46189.371 | AG64: =IFERROR(__xludf.DUMMYFUNCTION("""COMPUTED_VALUE"""),"credit") -> credit | AH64: =IFERROR(__xludf.DUMMYFUNCTION("""COMPUTED_VALUE"""),600.0) -> 600 | AI64: =IFERROR(__xludf.DUMMYFUNCTION("""COMPUTED_VALUE"""),"cash_isa") -> cash_isa | AJ64: =IFERROR(__xludf.DUMMYFUNCTION("""COMPUTED_VALUE"""),"9bc00e6b-ce5f-48c5-ae3a-1baabe00f337") -> 9bc00e6b-ce5f-48c5-ae3a-1baabe00f337 | AK64: =IFERROR(__xludf.DUMMYFUNCTION("""COMPUTED_VALUE"""),"085b2804-8667-41d1-bb69-7a8e9fc6fb9c") -> 085b2804-8667-41d1-bb69-7a8e9fc6fb9c | AR64: =ROUND(VALUE(AH64),2)&"_"&TRIM(LOWER(AG64)) -> 600_credit | AS64: =IF(AH64="", "", LET(current_amt, ROUND(VALUE(AH64), 2), current_dir, TRIM(LOWER(AG64)), opposite_dir, IF(current_dir="credit", "debit", "credit"), occ, COUNTIFS($AH$3:AH64, AH64, $AG$3:AG64, AG64), opp_total, COUNTIFS($AH$3:$AH$1000, AH64, $AG$3:$AG$1000, opposite_dir), IF(opp_total >= occ, "DROP", "KEEP"))) -> DROP
A65: 73df5aae-f42a-49a0-9d8f-616ca6dbebaa | B65: 019ecfb2-c757-7ad1-9dea-6d577be8f156 | C65: 46189.383 | D65: debit | E65: 23722.56 | F65: cash_isa | G65: 9bc00e6b-ce5f-48c5-ae3a-1baabe00f337 | H65: e9d9ba53-346f-47d3-8481-c47875d3b472 | AD65: =IFERROR(__xludf.DUMMYFUNCTION("""COMPUTED_VALUE"""),"73df5aae-f42a-49a0-9d8f-616ca6dbebaa") -> 73df5aae-f42a-49a0-9d8f-616ca6dbebaa | AE65: =IFERROR(__xludf.DUMMYFUNCTION("""COMPUTED_VALUE"""),"019ecfa4-95ab-78b2-9df6-0cc0395860c0") -> 019ecfa4-95ab-78b2-9df6-0cc0395860c0 | AF65: =IFERROR(__xludf.DUMMYFUNCTION("""COMPUTED_VALUE"""),46189.371875) -> 46189.372 | AG65: =IFERROR(__xludf.DUMMYFUNCTION("""COMPUTED_VALUE"""),"debit") -> debit | AH65: =IFERROR(__xludf.DUMMYFUNCTION("""COMPUTED_VALUE"""),27138.16) -> 27138.16 | AI65: =IFERROR(__xludf.DUMMYFUNCTION("""COMPUTED_VALUE"""),"cash_isa") -> cash_isa | AJ65: =IFERROR(__xludf.DUMMYFUNCTION("""COMPUTED_VALUE"""),"9bc00e6b-ce5f-48c5-ae3a-1baabe00f337") -> 9bc00e6b-ce5f-48c5-ae3a-1baabe00f337 | AK65: =IFERROR(__xludf.DUMMYFUNCTION("""COMPUTED_VALUE"""),"7656788e-1cb3-4ca4-89c4-a220c453ea4c") -> 7656788e-1cb3-4ca4-89c4-a220c453ea4c | AR65: =ROUND(VALUE(AH65),2)&"_"&TRIM(LOWER(AG65)) -> 27138.16_debit | AS65: =IF(AH65="", "", LET(current_amt, ROUND(VALUE(AH65), 2), current_dir, TRIM(LOWER(AG65)), opposite_dir, IF(current_dir="credit", "debit", "credit"), occ, COUNTIFS($AH$3:AH65, AH65, $AG$3:AG65, AG65), opp_total, COUNTIFS($AH$3:$AH$1000, AH65, $AG$3:$AG$1000, opposite_dir), IF(opp_total >= occ, "DROP", "KEEP"))) -> DROP
A66: 73df5aae-f42a-49a0-9d8f-616ca6dbebaa | B66: 019ecfb4-549d-755e-958e-c721ba1b4f5d | C66: 46189.384 | D66: credit | E66: 22843.96 | F66: cash_isa | G66: 9bc00e6b-ce5f-48c5-ae3a-1baabe00f337 | H66: c3ff4fac-5b26-4300-8002-b1da8163bf53 | AD66: =IFERROR(__xludf.DUMMYFUNCTION("""COMPUTED_VALUE"""),"73df5aae-f42a-49a0-9d8f-616ca6dbebaa") -> 73df5aae-f42a-49a0-9d8f-616ca6dbebaa | AE66: =IFERROR(__xludf.DUMMYFUNCTION("""COMPUTED_VALUE"""),"019ecfa5-a521-7820-94ee-27e0e26b36f4") -> 019ecfa5-a521-7820-94ee-27e0e26b36f4 | AF66: =IFERROR(__xludf.DUMMYFUNCTION("""COMPUTED_VALUE"""),46189.37268518518) -> 46189.373 | AG66: =IFERROR(__xludf.DUMMYFUNCTION("""COMPUTED_VALUE"""),"credit") -> credit | AH66: =IFERROR(__xludf.DUMMYFUNCTION("""COMPUTED_VALUE"""),15731.47) -> 15731.47 | AI66: =IFERROR(__xludf.DUMMYFUNCTION("""COMPUTED_VALUE"""),"cash_isa") -> cash_isa | AJ66: =IFERROR(__xludf.DUMMYFUNCTION("""COMPUTED_VALUE"""),"9bc00e6b-ce5f-48c5-ae3a-1baabe00f337") -> 9bc00e6b-ce5f-48c5-ae3a-1baabe00f337 | AK66: =IFERROR(__xludf.DUMMYFUNCTION("""COMPUTED_VALUE"""),"cc1d8e4c-a245-4b9d-a206-5c73b7275d86") -> cc1d8e4c-a245-4b9d-a206-5c73b7275d86 | AR66: =ROUND(VALUE(AH66),2)&"_"&TRIM(LOWER(AG66)) -> 15731.47_credit | AS66: =IF(AH66="", "", LET(current_amt, ROUND(VALUE(AH66), 2), current_dir, TRIM(LOWER(AG66)), opposite_dir, IF(current_dir="credit", "debit", "credit"), occ, COUNTIFS($AH$3:AH66, AH66, $AG$3:AG66, AG66), opp_total, COUNTIFS($AH$3:$AH$1000, AH66, $AG$3:$AG$1000, opposite_dir), IF(opp_total >= occ, "DROP", "KEEP"))) -> DROP
A67: 73df5aae-f42a-49a0-9d8f-616ca6dbebaa | B67: 019ecfb6-9633-7d5d-95b8-5d83498d1997 | C67: 46189.386 | D67: debit | E67: 22843.96 | F67: cash_isa | G67: 9bc00e6b-ce5f-48c5-ae3a-1baabe00f337 | H67: c3ff4fac-5b26-4300-8002-b1da8163bf53 | AD67: =IFERROR(__xludf.DUMMYFUNCTION("""COMPUTED_VALUE"""),"73df5aae-f42a-49a0-9d8f-616ca6dbebaa") -> 73df5aae-f42a-49a0-9d8f-616ca6dbebaa | AE67: =IFERROR(__xludf.DUMMYFUNCTION("""COMPUTED_VALUE"""),"019ecfa5-f985-75d7-9239-6f575e107b7b") -> 019ecfa5-f985-75d7-9239-6f575e107b7b | AF67: =IFERROR(__xludf.DUMMYFUNCTION("""COMPUTED_VALUE"""),46189.37293981481) -> 46189.373 | AG67: =IFERROR(__xludf.DUMMYFUNCTION("""COMPUTED_VALUE"""),"debit") -> debit | AH67: =IFERROR(__xludf.DUMMYFUNCTION("""COMPUTED_VALUE"""),20708.18) -> 20708.18 | AI67: =IFERROR(__xludf.DUMMYFUNCTION("""COMPUTED_VALUE"""),"cash_isa") -> cash_isa | AJ67: =IFERROR(__xludf.DUMMYFUNCTION("""COMPUTED_VALUE"""),"9bc00e6b-ce5f-48c5-ae3a-1baabe00f337") -> 9bc00e6b-ce5f-48c5-ae3a-1baabe00f337 | AK67: =IFERROR(__xludf.DUMMYFUNCTION("""COMPUTED_VALUE"""),"887de5c0-de23-4ec2-8e28-5f7a3d8297b1") -> 887de5c0-de23-4ec2-8e28-5f7a3d8297b1 | AR67: =ROUND(VALUE(AH67),2)&"_"&TRIM(LOWER(AG67)) -> 20708.18_debit | AS67: =IF(AH67="", "", LET(current_amt, ROUND(VALUE(AH67), 2), current_dir, TRIM(LOWER(AG67)), opposite_dir, IF(current_dir="credit", "debit", "credit"), occ, COUNTIFS($AH$3:AH67, AH67, $AG$3:AG67, AG67), opp_total, COUNTIFS($AH$3:$AH$1000, AH67, $AG$3:$AG$1000, opposite_dir), IF(opp_total >= occ, "DROP", "KEEP"))) -> DROP
A68: 73df5aae-f42a-49a0-9d8f-616ca6dbebaa | B68: 019ecfb7-09d3-771c-8873-eae6cacf3a3c | C68: 46189.386 | D68: credit | E68: 20740.46 | F68: cash_isa | G68: 9bc00e6b-ce5f-48c5-ae3a-1baabe00f337 | H68: 1c32520d-4809-42ef-b7cd-8930d841a73e | AD68: =IFERROR(__xludf.DUMMYFUNCTION("""COMPUTED_VALUE"""),"73df5aae-f42a-49a0-9d8f-616ca6dbebaa") -> 73df5aae-f42a-49a0-9d8f-616ca6dbebaa | AE68: =IFERROR(__xludf.DUMMYFUNCTION("""COMPUTED_VALUE"""),"019ecfa6-3ef4-7337-b7fd-41d0ca08caa1") -> 019ecfa6-3ef4-7337-b7fd-41d0ca08caa1 | AF68: =IFERROR(__xludf.DUMMYFUNCTION("""COMPUTED_VALUE"""),46189.373136574075) -> 46189.373 | AG68: =IFERROR(__xludf.DUMMYFUNCTION("""COMPUTED_VALUE"""),"debit") -> debit | AH68: =IFERROR(__xludf.DUMMYFUNCTION("""COMPUTED_VALUE"""),600.0) -> 600 | AI68: =IFERROR(__xludf.DUMMYFUNCTION("""COMPUTED_VALUE"""),"cash_isa") -> cash_isa | AJ68: =IFERROR(__xludf.DUMMYFUNCTION("""COMPUTED_VALUE"""),"9bc00e6b-ce5f-48c5-ae3a-1baabe00f337") -> 9bc00e6b-ce5f-48c5-ae3a-1baabe00f337 | AK68: =IFERROR(__xludf.DUMMYFUNCTION("""COMPUTED_VALUE"""),"085b2804-8667-41d1-bb69-7a8e9fc6fb9c") -> 085b2804-8667-41d1-bb69-7a8e9fc6fb9c | AR68: =ROUND(VALUE(AH68),2)&"_"&TRIM(LOWER(AG68)) -> 600_debit | AS68: =IF(AH68="", "", LET(current_amt, ROUND(VALUE(AH68), 2), current_dir, TRIM(LOWER(AG68)), opposite_dir, IF(current_dir="credit", "debit", "credit"), occ, COUNTIFS($AH$3:AH68, AH68, $AG$3:AG68, AG68), opp_total, COUNTIFS($AH$3:$AH$1000, AH68, $AG$3:$AG$1000, opposite_dir), IF(opp_total >= occ, "DROP", "KEEP"))) -> DROP
A69: 73df5aae-f42a-49a0-9d8f-616ca6dbebaa | B69: 019ecfb8-7bab-798c-8afe-74ae2e042828 | C69: 46189.387 | D69: credit | E69: 2755.69 | F69: cash_isa | G69: 9bc00e6b-ce5f-48c5-ae3a-1baabe00f337 | H69: 464c3adf-be90-4c81-865b-cd45ec0d11a2 | AD69: =IFERROR(__xludf.DUMMYFUNCTION("""COMPUTED_VALUE"""),"73df5aae-f42a-49a0-9d8f-616ca6dbebaa") -> 73df5aae-f42a-49a0-9d8f-616ca6dbebaa | AE69: =IFERROR(__xludf.DUMMYFUNCTION("""COMPUTED_VALUE"""),"019ecfa6-40b7-76ab-ae6c-74db43f45680") -> 019ecfa6-40b7-76ab-ae6c-74db43f45680 | AF69: =IFERROR(__xludf.DUMMYFUNCTION("""COMPUTED_VALUE"""),46189.37314814815) -> 46189.373 | AG69: =IFERROR(__xludf.DUMMYFUNCTION("""COMPUTED_VALUE"""),"debit") -> debit | AH69: =IFERROR(__xludf.DUMMYFUNCTION("""COMPUTED_VALUE"""),20910.88) -> 20910.88 | AI69: =IFERROR(__xludf.DUMMYFUNCTION("""COMPUTED_VALUE"""),"cash_isa") -> cash_isa | AJ69: =IFERROR(__xludf.DUMMYFUNCTION("""COMPUTED_VALUE"""),"9bc00e6b-ce5f-48c5-ae3a-1baabe00f337") -> 9bc00e6b-ce5f-48c5-ae3a-1baabe00f337 | AK69: =IFERROR(__xludf.DUMMYFUNCTION("""COMPUTED_VALUE"""),"e7447f5e-e526-4c5f-adf1-8e8cd0b72125") -> e7447f5e-e526-4c5f-adf1-8e8cd0b72125 | AR69: =ROUND(VALUE(AH69),2)&"_"&TRIM(LOWER(AG69)) -> 20910.88_debit | AS69: =IF(AH69="", "", LET(current_amt, ROUND(VALUE(AH69), 2), current_dir, TRIM(LOWER(AG69)), opposite_dir, IF(current_dir="credit", "debit", "credit"), occ, COUNTIFS($AH$3:AH69, AH69, $AG$3:AG69, AG69), opp_total, COUNTIFS($AH$3:$AH$1000, AH69, $AG$3:$AG$1000, opposite_dir), IF(opp_total >= occ, "DROP", "KEEP"))) -> DROP
A70: 73df5aae-f42a-49a0-9d8f-616ca6dbebaa | B70: 019ecfb8-b6c2-7b9b-8ba0-e446d15e83a5 | C70: 46189.387 | D70: credit | E70: 41156.98 | F70: cash_isa | G70: 9bc00e6b-ce5f-48c5-ae3a-1baabe00f337 | H70: e6e73ee3-1c63-4f16-ad0c-75d3997b34a6 | AD70: =IFERROR(__xludf.DUMMYFUNCTION("""COMPUTED_VALUE"""),"73df5aae-f42a-49a0-9d8f-616ca6dbebaa") -> 73df5aae-f42a-49a0-9d8f-616ca6dbebaa | AE70: =IFERROR(__xludf.DUMMYFUNCTION("""COMPUTED_VALUE"""),"019ecfa8-36c0-75fc-b091-53d4fd822c98") -> 019ecfa8-36c0-75fc-b091-53d4fd822c98 | AF70: =IFERROR(__xludf.DUMMYFUNCTION("""COMPUTED_VALUE"""),46189.37462962963) -> 46189.375 | AG70: =IFERROR(__xludf.DUMMYFUNCTION("""COMPUTED_VALUE"""),"credit") -> credit | AH70: =IFERROR(__xludf.DUMMYFUNCTION("""COMPUTED_VALUE"""),40854.07) -> 40854.07 | AI70: =IFERROR(__xludf.DUMMYFUNCTION("""COMPUTED_VALUE"""),"cash_isa") -> cash_isa | AJ70: =IFERROR(__xludf.DUMMYFUNCTION("""COMPUTED_VALUE"""),"9bc00e6b-ce5f-48c5-ae3a-1baabe00f337") -> 9bc00e6b-ce5f-48c5-ae3a-1baabe00f337 | AK70: =IFERROR(__xludf.DUMMYFUNCTION("""COMPUTED_VALUE"""),"806f931e-51a6-4b29-8854-3f9befa1d615") -> 806f931e-51a6-4b29-8854-3f9befa1d615 | AR70: =ROUND(VALUE(AH70),2)&"_"&TRIM(LOWER(AG70)) -> 40854.07_credit | AS70: =IF(AH70="", "", LET(current_amt, ROUND(VALUE(AH70), 2), current_dir, TRIM(LOWER(AG70)), opposite_dir, IF(current_dir="credit", "debit", "credit"), occ, COUNTIFS($AH$3:AH70, AH70, $AG$3:AG70, AG70), opp_total, COUNTIFS($AH$3:$AH$1000, AH70, $AG$3:$AG$1000, opposite_dir), IF(opp_total >= occ, "DROP", "KEEP"))) -> DROP
